Workbook
Name BoxPlot: "BoxPlot"
Name Bubble: "Bubble"
Name Candlestick: "Candlestick"
Name Chart: "Chart"
Name ChartImage: "ChartImage"
Name ColumnRange: "ColumnRange"
Name Dumbbell: "Dumbbell"
Name Heatmap: "Heatmap"
Name Histogram: "Histogram"
Name Map: "Map"
Name OHLC: "OHLC"
Name PieChart: "PieChart"
Name Scatter: "Scatter"
Name Series: "Series"
Name Stripe: "Stripe"
Name Table: "Table"
Name TreeMap: "TreeMap"
Name Waterfall: "Waterfall"

Sheet Activities before completion
A4: Type | B4: A Office
A5: Status | B5: Valid | D5: <- Not included completed projects
A6: Ownership Structure | B6: (All)
A7: Floor Plate > 15,000 sf (NFA) | B7: (All)
B9: Column Labels
B10: Total Sum of Pre-leased space (Usable FA) (sf) | C10: Total Sum of Pre-sold (Usable FA) (sf) | D10: Total Sum of Self-use space (Usable FA) (sf) | O10: KLN & NT | P10: KLN & NT | Q10: KLN & NT | R10: KLN & NT
A11: Row Labels | O11: Sum of Pre-leased space (Usable FA) (sf) | P11: Sum of Pre-sold (Usable FA) (sf) | Q11: Sum of Self-use space (Usable FA) (sf) | R11: Total
A12: Grand Total | O12: =E12+H12 -> 0 | P12: =F12+I12 -> 0 | Q12: =G12+J12 -> 0 | R12: =SUM(O12:Q12) -> 0
O13: =E13+H13 -> 0 | P13: =F13+I13 -> 0 | Q13: =G13+J13 -> 0 | R13: =SUM(O13:Q13) -> 0
O14: =E14+H14 -> 0 | P14: =F14+I14 -> 0 | Q14: =G14+J14 -> 0 | R14: =SUM(O14:Q14) -> 0
O15: =E15+H15 -> 0 | P15: =F15+I15 -> 0 | Q15: =G15+J15 -> 0 | R15: =SUM(O15:Q15) -> 0
N16: =SUM(K16:M16) -> 0
A26: Type | B26: A Office
A27: Status | B27: Valid | D27: <- Not included completed projects
A28: Ownership Structure | B28: (All)
A29: Floor Plate > 15,000 sf (NFA) | B29: (All)
B31: Column Labels
B32: Total Sum of Space available for lease (Usable FA) (sf) | C32: Total Sum of Space available for sale (Usable FA) (sf) | D32: Total Sum of Space available uncertain of use (Usable FA) (sf) | O32: KLN & NT | P32: KLN & NT | Q32: KLN & NT | R32: KLN & NT
A33: Row Labels | O33: Sum of Space available for lease (Usable FA) (sf) | P33: Sum of Space available for sale (Usable FA) (sf) | Q33: Sum of Space available uncertain of use (Usable FA) (sf) | R33: Total
A34: Grand Total | O34: =E34+H34 -> 0 | P34: =F34+I34 -> 0 | Q34: =G34+J34 -> 0 | R34: =SUM(O34:Q34) -> 0
O35: =E35+H35 -> 0 | P35: =F35+I35 -> 0 | Q35: =G35+J35 -> 0 | R35: =SUM(O35:Q35) -> 0
O36: =E36+H36 -> 0 | P36: =F36+I36 -> 0 | Q36: =G36+J36 -> 0 | R36: =SUM(O36:Q36) -> 0
O37: =E37+H37 -> 0 | P37: =F37+I37 -> 0 | Q37: =G37+J37 -> 0 | R37: =SUM(O37:Q37) -> 0
O38: =E38+H38 -> 0 | P38: =F38+I38 -> 0 | Q38: =G38+J38 -> 0 | R38: =SUM(O38:Q38) -> 0
O39: =E39+H39 -> 0 | P39: =F39+I39 -> 0 | Q39: =G39+J39 -> 0 | R39: =SUM(O39:Q39) -> 0

Sheet NEW table
A1: Type | B1: A Office
A2: Status | B2: (Multiple Items) | Q2: Type | R2: A Office
A3: Ownership Structure | B3: (All) | Q3: Status | R3: (Multiple Items)
A4: Floor Plate > 15,000 sf (NFA) | B4: (All) | Q4: Ownership Structure | R4: (All)
A5: Private / Public Sector | B5: (All) | Q5: Floor Plate > 15,000 sf (NFA) | R5: (All)
A7: Sum of Office UFA (Net) (sf) | B7: Column Labels | Q7: Sum of Office UFA (Net) (sf) | S7: CBRE districts
B8: Central | C8: Admiralty & Sheung Wan | D8: Wan Chai & Causeway Bay | E8: Hong Kong East | F8: Wong Chuk Hang | G8: Tsim Sha Tsui West | H8: Kowloon East | I8: Kowloon Others | J8: New Territories | K8: Grand Total | Q8: Year | R8: Qtr | S8: Central | T8: Admiralty & Sheung Wan | U8: Wan Chai & Causeway Bay | V8: Hong Kong East | W8: Wong Chuk Hang | X8: Tsim Sha Tsui | Y8: Kowloon East | Z8: Kowloon Others | AA8: New Territories | AB8: Tsim Sha Tsui West | AC8: Grand Total
A9: Row Labels | Q9: 2008 | R9: 1 | V9: 1214462.6 | AB9: 714454.26 | AC9: 1928916.8
A10: 2022 | B10: 0 | C10: 0 | D10: 0 | E10: 718002 | F10: 291512.85 | G10: 0 | H10: 1880197.9 | I10: 0 | J10: 1246999 | K10: 4136711.7 | R10: 2 | AA10: 431108.96 | AC10: 431108.96
A11: 2023 | B11: 0 | C11: 0 | D11: 0 | E11: 0 | F11: 0 | G11: 0 | H11: 346226.65 | I11: 1265376.8 | J11: 0 | K11: 1611603.4 | R11: 3 | Y11: 2028181.6 | AC11: 2028181.6
A12: 2024 | B12: 752009.51 | C12: 0 | D12: 351511.45 | E12: 0 | F12: 241267.41 | G12: 0 | H12: 211444.8 | I12: 0 | J12: 0 | K12: 1556233.2 | R12: 4
A13: 2025 | B13: 78036.8 | C13: 122128.8 | D13: 466387.68 | E13: 0 | F13: 0 | G13: 1921374 | H13: 328053.53 | I13: 0 | J13: 0 | K13: 2915980.8 | Q13: 2009 | R13: 1 | Z13: 165456.67 | AB13: 607129.38 | AC13: 772586.05
A14: 2026 | B14: 324000 | C14: 477416.54 | D14: 752964 | E14: 0 | F14: 0 | G14: 0 | H14: 178329.6 | I14: 0 | J14: 0 | K14: 1732710.1 | R14: 2
A15: 2027 | B15: 0 | C15: 135224.72 | D15: 0 | E15: 105000 | F15: 0 | G15: 504033.07 | H15: 0 | I15: 379486.41 | J15: 431964 | K15: 1555708.2 | R15: 3 | Y15: 565418.65 | AC15: 565418.65
A16: 2028 | B16: 0 | C16: 0 | D16: 0 | E16: 0 | F16: 0 | G16: 0 | H16: 0 | I16: 242856.91 | J16: 0 | K16: 242856.91 | R16: 4 | Y16: 233710.12 | AC16: 233710.12
A17: 2029 | B17: 0 | C17: 0 | D17: 0 | E17: 0 | F17: 0 | G17: 0 | H17: 0 | I17: 880056.79 | J17: 0 | K17: 880056.79 | Q17: 2010 | R17: 1 | Y17: 291505.5 | AC17: 291505.5
A18: 2030 | B18: 0 | C18: 0 | D18: 0 | E18: 701149.5 | F18: 0 | G18: 0 | H18: 0 | I18: 0 | J18: 266957.96 | K18: 968107.46 | R18: 2 | AB18: 465089.04 | AC18: 465089.04
A19: 2032 | B19: 297000 | C19: 0 | D19: 0 | E19: 0 | F19: 0 | G19: 0 | H19: 0 | I19: 0 | J19: 0 | K19: 297000 | R19: 3 | V19: 375913.75 | AC19: 375913.75
A20: 2033 | B20: 0 | C20: 0 | D20: 0 | E20: 0 | F20: 0 | G20: 0 | H20: 531682.84 | I20: 0 | J20: 0 | K20: 531682.84 | R20: 4
A21: Grand Total | B21: 1451046.3 | C21: 734770.06 | D21: 1570863.1 | E21: 1524151.5 | F21: 532780.26 | G21: 2425407.1 | H21: 3475935.3 | I21: 2767776.9 | J21: 1945921 | K21: 16428651 | Q21: 2011 | R21: 1 | S21: 122648.27 | W21: 491537.15 | Y21: 314640 | AC21: 928825.42
R22: 2 | Y22: 447279 | AC22: 447279
R23: 3
R24: 4 | S24: 215391.02 | AC24: 215391.02
Q25: 2012 | R25: 1 | U25: 222653.53 | Y25: 227618.25 | AC25: 450271.78
R26: 2
R27: 3 | U27: 105603 | Y27: 191442.75 | AC27: 297045.75
R28: 4 | S28: 151474.24 | AA28: 442530.75 | AC28: 594004.99
Q29: 2013 | R29: 1
R30: 2 | W30: 137894.4 | AC30: 137894.4
A31: Type | B31: A Office | R31: 3 | Y31: 714699.41 | AC31: 714699.41
A32: Status | B32: (Multiple Items) | R32: 4 | S32: 50000 | W32: 193064.25 | AC32: 243064.25
A33: Ownership Structure | B33: (All) | Q33: 2014 | R33: 1 | S33: 51630 | Z33: 160988.54 | AC33: 212618.54
A34: Floor Plate > 15,000 sf (NFA) | B34: (All) | R34: 2
R35: 3 | AA35: 293429.24 | AC35: 293429.24
A36: Sum of Office UFA (Net) (sf) | B36: Column Labels | R36: 4 | Y36: 132741 | AC36: 132741
A37: Row Labels | B37: Hong Kong Island | C37: Kowloon | D37: New Territories | E37: Grand Total | G37: KLN/NT | Q37: 2015 | R37: 1 | Y37: 395916.05 | Z37: 115286 | AC37: 511202.05
A38: 2022 | B38: 1009514.8 | C38: 1880197.9 | D38: 1246999 | E38: 4136711.7 | G38: =+C38+D38 -> 3127196.9 | R38: 2 | W38: 82390 | X38: 60889.5 | Y38: 694424.39 | AC38: 837703.89
A39: 2023 | C39: 1611603.4 | E39: 1611603.4 | F39: 1422396.2 | G39: =+C39+D39 -> 1611603.4 | R39: 3 | U39: 128331.7 | AC39: 128331.7
A40: 2024 | B40: 1344788.4 | C40: 211444.8 | E40: 1556233.2 | F40: 381637.69 | G40: =+C40+D40 -> 211444.8 | R40: 4 | W40: 351215.8 | AA40: 170281 | AC40: 521496.8
A41: 2025 | B41: 666553.28 | C41: 2249427.5 | E41: 2915980.8 | F41: 886141.4 | G41: =+C41+D41 -> 2249427.5 | Q41: 2016 | R41: 1 | S41: 61882.8 | Z41: 446760 | AC41: 508642.8
A42: 2026 | B42: 1554380.5 | C42: 178329.6 | E42: 1732710.1 | F42: 1014563.2 | G42: =+C42+D42 -> 178329.6 | R42: 2 | Z42: 208870 | AA42: 215457 | AC42: 424327
A43: 2027 | B43: 240224.72 | C43: 883519.48 | D43: 431964 | E43: 1555708.2 | G43: =+C43+D43 -> 1315483.5 | R43: 3
A44: 2028 | C44: 242856.91 | E44: 242856.91 | F44: 701149.5 | G44: =+C44+D44 -> 242856.91 | R44: 4 | Y44: 497439.15 | AC44: 497439.15
A45: 2029 | C45: 880056.79 | E45: 880056.79 | Q45: 2017 | R45: 1 | W45: 121612.5 | AC45: 121612.5
A46: 2030 | B46: 701149.5 | D46: 266957.96 | E46: 968107.46 | R46: 2
A47: 2032 | B47: 297000 | E47: 297000 | R47: 3 | V47: 285650.1 | X47: 288571.5 | Y47: 342615.6 | Z47: 85794.14 | AC47: 1002631.3
A48: 2033 | C48: 531682.84 | E48: 531682.84 | R48: 4 | U48: 323901.76 | Y48: 498429.6 | Z48: 175602.88 | AC48: 997934.24
A49: Grand Total | B49: 5813611.3 | C49: 8669119.2 | D49: 1945921 | E49: 16428651 | Q49: 2018 | R49: 1 | Y49: 229736.88 | Z49: 128388.08 | AC49: 358124.96
R50: 2 | Y50: 546802.4 | AC50: 546802.4
R51: 3 | V51: 792113.55 | W51: 317234.3 | AC51: 1109347.9
R52: 4
Q53: 2019 | R53: 1 | U53: 185806.5 | Y53: 466830 | AC53: 652636.5
R54: 2 | V54: 384341.73 | Y54: 1014783.9 | AC54: 1399125.7
R55: 3 | S55: 10373 | X55: 278124 | AC55: 288497
R56: 4
Q57: 2020 | R57: 1 | U57: 18689.6 | AC57: 18689.6
R58: 2 | AA58: 279556.9 | AC58: 279556.9
R59: 3
R60: 4
Q61: 2021 | R61: 1
R62: 2 | AA62: 136120.05 | AC62: 136120.05
R63: 3
R64: 4 | Z64: 435501.75 | AC64: 435501.75
Q65: 2022 | R65: 1 | AA65: 539558 | AC65: 539558
R66: 2 | Y66: 201870.38 | AC66: 201870.38
R67: 3 | V67: 718002 | W67: 169122.05 | Y67: 953120 | AA67: 373691 | AC67: 2213935
R68: 4 | W68: 122390.8 | Y68: 725207.5 | AA68: 333750 | AC68: 1181348.3
Q69: 2023 | R69: 1 | Z69: 92617.5 | AC69: 92617.5
R70: 2 | Z70: 330606.75 | AC70: 330606.75
R71: 3 | Y71: 45000.418 | AC71: 45000.418
R72: 4 | Y72: 301226.23 | Z72: 842152.5 | AC72: 1143378.7
Q73: 2024 | R73: 1 | S73: 332392.23 | U73: 351511.45 | W73: 241267.41 | AC73: 925171.09
R74: 2 | S74: 419617.28 | Y74: 211444.8 | AC74: 631062.08
R75: 3
R76: 4
Q77: 2025 | R77: 1 | Y77: 328053.53 | AC77: 328053.53
R78: 2 | T78: 122128.8 | AC78: 122128.8
R79: 3 | U79: 466387.68 | AC79: 466387.68
R80: 4 | S80: 78036.8 | AB80: 1921374 | AC80: 1999410.8
Q81: 2026 | R81: 1
R82: 2
R83: 3 | Y83: 178329.6 | AC83: 178329.6
R84: 4 | S84: 324000 | T84: 477416.54 | U84: 752964 | AC84: 1554380.5
Q85: 2027 | R85: 1 | AB85: 504033.07 | AC85: 504033.07
R86: 2 | Z86: 379486.41 | AC86: 379486.41
R87: 3
R88: 4 | T88: 135224.72 | V88: 105000 | AA88: 431964 | AC88: 672188.72
Q89: 2028 | R89: 1
R90: 2
R91: 3
R92: 4 | Z92: 242856.91 | AC92: 242856.91
Q93: 2029 | R93: 1
R94: 2
R95: 3
R96: 4 | Z96: 880056.79 | AC96: 880056.79
Q97: 2030 | R97: 1
R98: 2
R99: 3
R100: 4 | V100: 701149.5 | AC100: 701149.5
Q101: 2032 | R101: 1
...

Sheet Grade A Office Supply_pre-2020
A1: Chinese Name | B1: Building Name | C1: Street Name | D1: Lot No. | E1: CBRE sub-markets | F1: CBRE districts | G1: District Order | H1: Area | I1: Year | J1: Qtr | K1: CBRE EDC | L1: Type | M1: Status | N1: No. of Blocks | O1: No. of Storeys | P1: No. of Storeys for Office | Q1: Floor Plate (GFA) (sf) | R1: Floor Plate (NFA) (sf) | S1: Floor Plate > 15,000 sf (NFA) | T1: Total GFA (sm) | U1: Total GFA (sf) | V1: Office GFA (sm) | W1: Office GFA (sf) | X1: Office UFA (Net) (sm) | Y1: Office UFA (Net) (sf) | Z1: Pre-leased space (Usable FA) (sf) | AA1: Pre-sold (Usable FA) (sf) | AB1: Self-use space (Usable FA) (sf) | AC1: Space available for lease (Usable FA) (sf) | AD1: Space available for sale (Usable FA) (sf) | AE1: Space available uncertain of use (Usable FA) (sf) | AF1: Pre-commitment Rate (%) | AG1: Building Type | AH1: BD Status | AI1: Source of Information | AJ1: Date of Source | AK1: Date of Entry | AL1: Development | AM1: Developer | AN1: Private / Public Sector | AO1: For Sale or For Lease? | AP1: Ownership Structure | AQ1: Remarks | AR1: Item Code | AS1: ProjectID | AT1: Lat | AU1: Long | AV1: Geometry
A2: 港島東中心 | B2: One Island East | C2: 18 Westlands Road | E2: Quarry Bay | F2: =VLOOKUP(Table1[[#This Row],[CBRE sub-markets]],Reference!$A$2:$B$31,2,FALSE) -> Hong Kong East | G2: =VLOOKUP(Table1[[#This Row],[CBRE sub-markets]],Reference!$A$2:$D$31,3,FALSE) -> 4 | H2: =VLOOKUP(Table1[[#This Row],[CBRE sub-markets]],Reference!$A$2:$D$31,4,FALSE) -> Hong Kong Island | I2: 2008 | J2: 1 | K2: =IF(ISNUMBER(Table1[[#This Row],[Qtr]]),CONCATENATE(Table1[[#This Row],[Year]]," Q",Table1[[#This Row],[Qtr]]),CONCATENATE(Table1[[#This Row],[Year]],Table1[[#This Row],[Qtr]])) -> 2008 Q1 | L2: A Office | M2: Completed | N2: 1 | O2: 68+2 basement | Q2: 25000 | R2: =Q2*(Y2/W2) -> 23000 | S2: =IF(AND(ISNUMBER(R2),R2>=15000),"Yes",IF(R2="","Unknown","No")) -> Yes | V2: 142791.8 | W2: 1320068 | X2: 103258.9 | Y2: 1214462.6 | AC2: =IF(Table1[[#This Row],[For Sale or For Lease?]]="For Lease",Table1[[#This Row],[Office UFA (Net) (sf)]]-Table1[[#This Row],[Pre-leased space (Usable FA) (sf)]]-Table1[[#This Row],[Pre-sold (Usable FA) (sf)]]-Table1[[#This Row],[Self-use space (Usable FA) (sf)]],0) -> 1214462.6 | AD2: =IF(Table1[[#This Row],[For Sale or For Lease?]]="For Sale",Table1[[#This Row],[Office UFA (Net) (sf)]]-Table1[[#This Row],[Pre-leased space (Usable FA) (sf)]]-Table1[[#This Row],[Pre-sold (Usable FA) (sf)]]-Table1[[#This Row],[Self-use space (Usable FA) (sf)]],0) -> 0 | AE2: =IF(Table1[[#This Row],[For Sale or For Lease?]]="Uncertain",Table1[[#This Row],[Office UFA (Net) (sf)]]-Table1[[#This Row],[Pre-leased space (Usable FA) (sf)]]-Table1[[#This Row],[Pre-sold (Usable FA) (sf)]]-Table1[[#This Row],[Self-use space (Usable FA) (sf)]],0) -> 0 | AF2: =1-SUM(Table1[[#This Row],[Space available for lease (Usable FA) (sf)]:[Space available uncertain of use (Usable FA) (sf)]])/Table1[[#This Row],[Office UFA (Net) (sf)]] -> 0 | AG2: Commercial | AH2: OP Issued | AI2: BD Monthly Digest | AJ2: 39508 | AK2: 40043 | AM2: Swire Properties | AN2: Private Sector | AO2: For Lease | AP2: Single owner | AQ2: Completed. Phase 1: 1,000,000 sf to be completed in 2008; Phase 2: 1,500,000 sf to be completed in 2010 | AR2: HE011
A3: 環球貿易廣場1期 | B3: International Commerce Centre Phase 1 | C3: 1 Austin Road West (Union Square Phase 7) | E3: Tsim Sha Tsui West | F3: =VLOOKUP(Table1[[#This Row],[CBRE sub-markets]],Reference!$A$2:$B$31,2,FALSE) -> Tsim Sha Tsui West | G3: =VLOOKUP(Table1[[#This Row],[CBRE sub-markets]],Reference!$A$2:$D$31,3,FALSE) -> 6 | H3: =VLOOKUP(Table1[[#This Row],[CBRE sub-markets]],Reference!$A$2:$D$31,4,FALSE) -> Kowloon | I3: 2008 | J3: 1 | K3: =IF(ISNUMBER(Table1[[#This Row],[Qtr]]),CONCATENATE(Table1[[#This Row],[Year]]," Q",Table1[[#This Row],[Qtr]]),CONCATENATE(Table1[[#This Row],[Year]],Table1[[#This Row],[Qtr]])) -> 2008 Q1 | L3: A Office | M3: Completed | N3: 1 | O3: 108+4 basement (10-47/F Total 32 floors) | Q3: 38000 | R3: =Q3*(Y3/W3) -> 29640 | S3: =IF(AND(ISNUMBER(R3),R3>=15000),"Yes",IF(R3="","Unknown","No")) -> Yes | V3: =W3/10.764 -> 85095.411 | W3: 915967 | X3: =Y3/10.764 -> 66374.42 | Y3: 714454.26 | AC3: =IF(Table1[[#This Row],[For Sale or For Lease?]]="For Lease",Table1[[#This Row],[Office UFA (Net) (sf)]]-Table1[[#This Row],[Pre-leased space (Usable FA) (sf)]]-Table1[[#This Row],[Pre-sold (Usable FA) (sf)]]-Table1[[#This Row],[Self-use space (Usable FA) (sf)]],0) -> 714454.26 | AD3: =IF(Table1[[#This Row],[For Sale or For Lease?]]="For Sale",Table1[[#This Row],[Office UFA (Net) (sf)]]-Table1[[#This Row],[Pre-leased space (Usable FA) (sf)]]-Table1[[#This Row],[Pre-sold (Usable FA) (sf)]]-Table1[[#This Row],[Self-use space (Usable FA) (sf)]],0) -> 0 | AE3: =IF(Table1[[#This Row],[For Sale or For Lease?]]="Uncertain",Table1[[#This Row],[Office UFA (Net) (sf)]]-Table1[[#This Row],[Pre-leased space (Usable FA) (sf)]]-Table1[[#This Row],[Pre-sold (Usable FA) (sf)]]-Table1[[#This Row],[Self-use space (Usable FA) (sf)]],0) -> 0 | AF3: =1-SUM(Table1[[#This Row],[Space available for lease (Usable FA) (sf)]:[Space available uncertain of use (Usable FA) (sf)]])/Table1[[#This Row],[Office UFA (Net) (sf)]] -> 0 | AG3: Commercial/ Hotel | AH3: POP Issued | AI3: Old Database | AK3: 40043 | AL3: Site | AM3: Sun Hung Kai Properties | AN3: Private Sector | AO3: For Lease | AP3: Single owner | AR3: TS031
A4: 九龍貿易中心 1座 | B4: Kowloon Commerce Centre Tower A | C4: 51-53 Kwai Cheong Road & 12-120 Tai Lin Pai Road | E4: Kwai Chung & Tsuen Wan | F4: =VLOOKUP(Table1[[#This Row],[CBRE sub-markets]],Reference!$A$2:$B$31,2,FALSE) -> New Territories | G4: =VLOOKUP(Table1[[#This Row],[CBRE sub-markets]],Reference!$A$2:$D$31,3,FALSE) -> 9 | H4: =VLOOKUP(Table1[[#This Row],[CBRE sub-markets]],Reference!$A$2:$D$31,4,FALSE) -> New Territories | I4: 2008 | J4: 2 | K4: =IF(ISNUMBER(Table1[[#This Row],[Qtr]]),CONCATENATE(Table1[[#This Row],[Year]]," Q",Table1[[#This Row],[Qtr]]),CONCATENATE(Table1[[#This Row],[Year]],Table1[[#This Row],[Qtr]])) -> 2008 Q2 | L4: A Office | M4: Completed | N4: 1 | O4: 26+7 podium+1 basement | Q4: =W4/(26+7) -> 17501.285 | R4: =Q4*(Y4/W4) -> 13063.908 | S4: =IF(AND(ISNUMBER(R4),R4>=15000),"Yes",IF(R4="","Unknown","No")) -> No | V4: 53655 | W4: =V4*10.764 -> 577542.42 | X4: 40051 | Y4: =X4*10.764 -> 431108.96 | AC4: =IF(Table1[[#This Row],[For Sale or For Lease?]]="For Lease",Table1[[#This Row],[Office UFA (Net) (sf)]]-Table1[[#This Row],[Pre-leased space (Usable FA) (sf)]]-Table1[[#This Row],[Pre-sold (Usable FA) (sf)]]-Table1[[#This Row],[Self-use space (Usable FA) (sf)]],0) -> 431108.96 | AD4: =IF(Table1[[#This Row],[For Sale or For Lease?]]="For Sale",Table1[[#This Row],[Office UFA (Net) (sf)]]-Table1[[#This Row],[Pre-leased space (Usable FA) (sf)]]-Table1[[#This Row],[Pre-sold (Usable FA) (sf)]]-Table1[[#This Row],[Self-use space (Usable FA) (sf)]],0) -> 0 | AE4: =IF(Table1[[#This Row],[For Sale or For Lease?]]="Uncertain",Table1[[#This Row],[Office UFA (Net) (sf)]]-Table1[[#This Row],[Pre-leased space (Usable FA) (sf)]]-Table1[[#This Row],[Pre-sold (Usable FA) (sf)]]-Table1[[#This Row],[Self-use space (Usable FA) (sf)]],0) -> 0 | AF4: =1-SUM(Table1[[#This Row],[Space available for lease (Usable FA) (sf)]:[Space available uncertain of use (Usable FA) (sf)]])/Table1[[#This Row],[Office UFA (Net) (sf)]] -> 0 | AG4: Commercial | AH4: OP Issued | AI4: BD Monthly Digest | AJ4: 39600 | AK4: 40043 | AM4: Sun Hung Kai Properties | AN4: Private Sector | AO4: For Lease | AP4: Single owner | AQ4: Almost fully leased | AR4: KF006
A5: 國際交易中心 | B5: Exchange Tower | C5: 33 Wang Chiu Road | E5: Kowloon Bay | F5: =VLOOKUP(Table1[[#This Row],[CBRE sub-markets]],Reference!$A$2:$B$31,2,FALSE) -> Kowloon East | G5: =VLOOKUP(Table1[[#This Row],[CBRE sub-markets]],Reference!$A$2:$D$31,3,FALSE) -> 7 | H5: =VLOOKUP(Table1[[#This Row],[CBRE sub-markets]],Reference!$A$2:$D$31,4,FALSE) -> Kowloon | I5: 2008 | J5: 3 | K5: =IF(ISNUMBER(Table1[[#This Row],[Qtr]]),CONCATENATE(Table1[[#This Row],[Year]]," Q",Table1[[#This Row],[Qtr]]),CONCATENATE(Table1[[#This Row],[Year]],Table1[[#This Row],[Qtr]])) -> 2008 Q3 | L5: A Office | M5: Completed | N5: 1 | O5: 28+3 basement | Q5: =W5/28 -> 21750.93 | R5: =Q5*(Y5/W5) -> 18503.316 | S5: =IF(AND(ISNUMBER(R5),R5>=15000),"Yes",IF(R5="","Unknown","No")) -> Yes | V5: 56579.9 | W5: =V5*10.764 -> 609026.04 | X5: 48132 | Y5: =X5*10.764 -> 518092.85 | AC5: =IF(Table1[[#This Row],[For Sale or For Lease?]]="For Lease",Table1[[#This Row],[Office UFA (Net) (sf)]]-Table1[[#This Row],[Pre-leased space (Usable FA) (sf)]]-Table1[[#This Row],[Pre-sold (Usable FA) (sf)]]-Table1[[#This Row],[Self-use space (Usable FA) (sf)]],0) -> 518092.85 | AD5: =IF(Table1[[#This Row],[For Sale or For Lease?]]="For Sale",Table1[[#This Row],[Office UFA (Net) (sf)]]-Table1[[#This Row],[Pre-leased space (Usable FA) (sf)]]-Table1[[#This Row],[Pre-sold (Usable FA) (sf)]]-Table1[[#This Row],[Self-use space (Usable FA) (sf)]],0) -> 0 | AE5: =IF(Table1[[#This Row],[For Sale or For Lease?]]="Uncertain",Table1[[#This Row],[Office UFA (Net) (sf)]]-Table1[[#This Row],[Pre-leased space (Usable FA) (sf)]]-Table1[[#This Row],[Pre-sold (Usable FA) (sf)]]-Table1[[#This Row],[Self-use space (Usable FA) (sf)]],0) -> 0 | AF5: =1-SUM(Table1[[#This Row],[Space available for lease (Usable FA) (sf)]:[Space available uncertain of use (Usable FA) (sf)]])/Table1[[#This Row],[Office UFA (Net) (sf)]] -> 0 | AG5: Commercial | AH5: OP Issued | AI5: BD Monthly Digest | AJ5: 39692 | AK5: 40043 | AM5: Sino Land | AN5: Private Sector | AO5: For Lease | AP5: Single owner | AQ5: Land premium = $1,282 psf, 16 Mar 07. Sam Li (7 Jun 2011): almost fully leased | AR5: KK019
B6: Manhattan Place | C6: 1 Sheung Yee Road (7 Wang Mau Street & 23 Wang Tai Road) | E6: Kowloon Bay | F6: =VLOOKUP(Table1[[#This Row],[CBRE sub-markets]],Reference!$A$2:$B$31,2,FALSE) -> Kowloon East | G6: =VLOOKUP(Table1[[#This Row],[CBRE sub-markets]],Reference!$A$2:$D$31,3,FALSE) -> 7 | H6: =VLOOKUP(Table1[[#This Row],[CBRE sub-markets]],Reference!$A$2:$D$31,4,FALSE) -> Kowloon | I6: 2008 | J6: 3 | K6: =IF(ISNUMBER(Table1[[#This Row],[Qtr]]),CONCATENATE(Table1[[#This Row],[Year]]," Q",Table1[[#This Row],[Qtr]]),CONCATENATE(Table1[[#This Row],[Year]],Table1[[#This Row],[Qtr]])) -> 2008 Q3 | L6: A Office | M6: Completed | N6: 1 | O6: 41 | Q6: =W6/O6 -> 17256.74 | R6: =Q6*(Y6/W6) -> 13805.268 | S6: =IF(AND(ISNUMBER(R6),R6>=15000),"Yes",IF(R6="","Unknown","No")) -> No | V6: 65730.8 | W6: =V6*10.764 -> 707526.33 | X6: 51142.5 | Y6: 566016 | AC6: =IF(Table1[[#This Row],[For Sale or For Lease?]]="For Lease",Table1[[#This Row],[Office UFA (Net) (sf)]]-Table1[[#This Row],[Pre-leased space (Usable FA) (sf)]]-Table1[[#This Row],[Pre-sold (Usable FA) (sf)]]-Table1[[#This Row],[Self-use space (Usable FA) (sf)]],0) -> 566016 | AD6: =IF(Table1[[#This Row],[For Sale or For Lease?]]="For Sale",Table1[[#This Row],[Office UFA (Net) (sf)]]-Table1[[#This Row],[Pre-leased space (Usable FA) (sf)]]-Table1[[#This Row],[Pre-sold (Usable FA) (sf)]]-Table1[[#This Row],[Self-use space (Usable FA) (sf)]],0) -> 0 | AE6: =IF(Table1[[#This Row],[For Sale or For Lease?]]="Uncertain",Table1[[#This Row],[Office UFA (Net) (sf)]]-Table1[[#This Row],[Pre-leased space (Usable FA) (sf)]]-Table1[[#This Row],[Pre-sold (Usable FA) (sf)]]-Table1[[#This Row],[Self-use space (Usable FA) (sf)]],0) -> 0 | AF6: =1-SUM(Table1[[#This Row],[Space available for lease (Usable FA) (sf)]:[Space available uncertain of use (Usable FA) (sf)]])/Table1[[#This Row],[Office UFA (Net) (sf)]] -> 0 | AG6: Commercial | AH6: OP Issued | AI6: BD Monthly Digest | AJ6: 39661 | AK6: 40043 | AM6: Manhattan Realty | AN6: Private Sector | AO6: For Lease | AP6: Single owner | AQ6: 2 Feb 05 SCMP, EJ 11 Mar 05 Sam Li (7 Jun 2011):Fully leased | AR6: KK018
A7: 城東誌 | B7: One & Two Landmark East | C7: 100 & 102 How Ming Street | E7: Kwun Tong | F7: =VLOOKUP(Table1[[#This Row],[CBRE sub-markets]],Reference!$A$2:$B$31,2,FALSE) -> Kowloon East | G7: =VLOOKUP(Table1[[#This Row],[CBRE sub-markets]],Reference!$A$2:$D$31,3,FALSE) -> 7 | H7: =VLOOKUP(Table1[[#This Row],[CBRE sub-markets]],Reference!$A$2:$D$31,4,FALSE) -> Kowloon | I7: 2008 | J7: 3 | K7: =IF(ISNUMBER(Table1[[#This Row],[Qtr]]),CONCATENATE(Table1[[#This Row],[Year]]," Q",Table1[[#This Row],[Qtr]]),CONCATENATE(Table1[[#This Row],[Year]],Table1[[#This Row],[Qtr]])) -> 2008 Q3 | L7: A Office | M7: Completed | N7: 2 | O7: 2/40/43+2 basement | Q7: =W7/42/2 -> 14315.633 | R7: =Q7*(Y7/W7) -> 11238.961 | S7: =IF(AND(ISNUMBER(R7),R7>=15000),"Yes",IF(R7="","Unknown","No")) -> No | V7: 111716.2 | W7: =V7*10.764 -> 1202513.2 | X7: 87706.5 | Y7: =X7*10.764 -> 944072.77 | AC7: =IF(Table1[[#This Row],[For Sale or For Lease?]]="For Lease",Table1[[#This Row],[Office UFA (Net) (sf)]]-Table1[[#This Row],[Pre-leased space (Usable FA) (sf)]]-Table1[[#This Row],[Pre-sold (Usable FA) (sf)]]-Table1[[#This Row],[Self-use space (Usable FA) (sf)]],0) -> 944072.77 | AD7: =IF(Table1[[#This Row],[For Sale or For Lease?]]="For Sale",Table1[[#This Row],[Office UFA (Net) (sf)]]-Table1[[#This Row],[Pre-leased space (Usable FA) (sf)]]-Table1[[#This Row],[Pre-sold (Usable FA) (sf)]]-Table1[[#This Row],[Self-use space (Usable FA) (sf)]],0) -> 0 | AE7: =IF(Table1[[#This Row],[For Sale or For Lease?]]="Uncertain",Table1[[#This Row],[Office UFA (Net) (sf)]]-Table1[[#This Row],[Pre-leased space (Usable FA) (sf)]]-Table1[[#This Row],[Pre-sold (Usable FA) (sf)]]-Table1[[#This Row],[Self-use space (Usable FA) (sf)]],0) -> 0 | AF7: =1-SUM(Table1[[#This Row],[Space available for lease (Usable FA) (sf)]:[Space available uncertain of use (Usable FA) (sf)]])/Table1[[#This Row],[Office UFA (Net) (sf)]] -> 0 | AG7: Commercial | AH7: OP Issued | AI7: BD Monthly Digest | AJ7: 39692 | AK7: 40043 | AM7: Winsor Properties | AN7: Private Sector | AO7: For Lease | AP7: Single owner | AR7: KK007
A8: 友邦九龍金融中心 | B8: AIA Financial Centre | C8: 712 Prince Edward Road East | E8: San Po Kong | F8: =VLOOKUP(Table1[[#This Row],[CBRE sub-markets]],Reference!$A$2:$B$31,2,FALSE) -> Kowloon Others | G8: =VLOOKUP(Table1[[#This Row],[CBRE sub-markets]],Reference!$A$2:$D$31,3,FALSE) -> 8 | H8: =VLOOKUP(Table1[[#This Row],[CBRE sub-markets]],Reference!$A$2:$D$31,4,FALSE) -> Kowloon | I8: 2009 | J8: 1 | K8: =IF(ISNUMBER(Table1[[#This Row],[Qtr]]),CONCATENATE(Table1[[#This Row],[Year]]," Q",Table1[[#This Row],[Qtr]]),CONCATENATE(Table1[[#This Row],[Year]],Table1[[#This Row],[Qtr]])) -> 2009 Q1 | L8: A Office | M8: Completed | N8: 1 | O8: 27 | Q8: =+W8/O8 -> 8021.9707 | R8: =Q8*(Y8/W8) -> 6128.0249 | S8: =IF(AND(ISNUMBER(R8),R8>=15000),"Yes",IF(R8="","Unknown","No")) -> No | V8: 20122 | W8: =V8*10.764 -> 216593.21 | X8: 15371.3 | Y8: =X8*10.764 -> 165456.67 | AC8: =IF(Table1[[#This Row],[For Sale or For Lease?]]="For Lease",Table1[[#This Row],[Office UFA (Net) (sf)]]-Table1[[#This Row],[Pre-leased space (Usable FA) (sf)]]-Table1[[#This Row],[Pre-sold (Usable FA) (sf)]]-Table1[[#This Row],[Self-use space (Usable FA) (sf)]],0) -> 165456.67 | AD8: =IF(Table1[[#This Row],[For Sale or For Lease?]]="For Sale",Table1[[#This Row],[Office UFA (Net) (sf)]]-Table1[[#This Row],[Pre-leased space (Usable FA) (sf)]]-Table1[[#This Row],[Pre-sold (Usable FA) (sf)]]-Table1[[#This Row],[Self-use space (Usable FA) (sf)]],0) -> 0 | AE8: =IF(Table1[[#This Row],[For Sale or For Lease?]]="Uncertain",Table1[[#This Row],[Office UFA (Net) (sf)]]-Table1[[#This Row],[Pre-leased space (Usable FA) (sf)]]-Table1[[#This Row],[Pre-sold (Usable FA) (sf)]]-Table1[[#This Row],[Self-use space (Usable FA) (sf)]],0) -> 0 | AF8: =1-SUM(Table1[[#This Row],[Space available for lease (Usable FA) (sf)]:[Space available uncertain of use (Usable FA) (sf)]])/Table1[[#This Row],[Office UFA (Net) (sf)]] -> 0 | AG8: Commercial | AH8: OP Issued | AI8: BD Monthly Digest | AJ8: 39814 | AK8: 40043 | AM8: Henderson | AN8: Private Sector | AO8: For Lease | AP8: Single owner | AR8: SP001
A9: 環球貿易廣場2期 | B9: International Commerce Centre Phase 2 | C9: 1 Austin Road West (Union Square Phase 7) | E9: Tsim Sha Tsui West | F9: =VLOOKUP(Table1[[#This Row],[CBRE sub-markets]],Reference!$A$2:$B$31,2,FALSE) -> Tsim Sha Tsui West | G9: =VLOOKUP(Table1[[#This Row],[CBRE sub-markets]],Reference!$A$2:$D$31,3,FALSE) -> 6 | H9: =VLOOKUP(Table1[[#This Row],[CBRE sub-markets]],Reference!$A$2:$D$31,4,FALSE) -> Kowloon | I9: 2009 | J9: 1 | K9: =IF(ISNUMBER(Table1[[#This Row],[Qtr]]),CONCATENATE(Table1[[#This Row],[Year]]," Q",Table1[[#This Row],[Qtr]]),CONCATENATE(Table1[[#This Row],[Year]],Table1[[#This Row],[Qtr]])) -> 2009 Q1 | L9: A Office | M9: Completed | N9: 1 | O9: 108+4 basement (50-77/F Total 22 floors) | Q9: 35000 | R9: =Q9*(Y9/W9) -> 27300 | S9: =IF(AND(ISNUMBER(R9),R9>=15000),"Yes",IF(R9="","Unknown","No")) -> Yes | V9: =W9/10.764 -> 72312.43 | W9: 778371 | X9: =Y9/10.764 -> 56403.696 | Y9: =W9*0.78 -> 607129.38 | AC9: =IF(Table1[[#This Row],[For Sale or For Lease?]]="For Lease",Table1[[#This Row],[Office UFA (Net) (sf)]]-Table1[[#This Row],[Pre-leased space (Usable FA) (sf)]]-Table1[[#This Row],[Pre-sold (Usable FA) (sf)]]-Table1[[#This Row],[Self-use space (Usable FA) (sf)]],0) -> 607129.38 | AD9: =IF(Table1[[#This Row],[For Sale or For Lease?]]="For Sale",Table1[[#This Row],[Office UFA (Net) (sf)]]-Table1[[#This Row],[Pre-leased space (Usable FA) (sf)]]-Table1[[#This Row],[Pre-sold (Usable FA) (sf)]]-Table1[[#This Row],[Self-use space (Usable FA) (sf)]],0) -> 0 | AE9: =IF(Table1[[#This Row],[For Sale or For Lease?]]="Uncertain",Table1[[#This Row],[Office UFA (Net) (sf)]]-Table1[[#This Row],[Pre-leased space (Usable FA) (sf)]]-Table1[[#This Row],[Pre-sold (Usable FA) (sf)]]-Table1[[#This Row],[Self-use space (Usable FA) (sf)]],0) -> 0 | AF9: =1-SUM(Table1[[#This Row],[Space available for lease (Usable FA) (sf)]:[Space available uncertain of use (Usable FA) (sf)]])/Table1[[#This Row],[Office UFA (Net) (sf)]] -> 0 | AG9: Commercial/ Hotel | AH9: POP Issued | AI9: Old Database | AK9: 40043 | AL9: Site | AM9: Sun Hung Kai Properties | AN9: Private Sector | AO9: For Lease | AP9: Single owner | AQ9: OS-KLN Sam Li (May 2009): POP quoted by L/L | AR9: TS031
A10: 億京中心 | B10: Billion Centre | C10: 1 Wang Kwong Road | E10: Kowloon Bay | F10: =VLOOKUP(Table1[[#This Row],[CBRE sub-markets]],Reference!$A$2:$B$31,2,FALSE) -> Kowloon East | G10: =VLOOKUP(Table1[[#This Row],[CBRE sub-markets]],Reference!$A$2:$D$31,3,FALSE) -> 7 | H10: =VLOOKUP(Table1[[#This Row],[CBRE sub-markets]],Reference!$A$2:$D$31,4,FALSE) -> Kowloon | I10: 2009 | J10: 3 | K10: =IF(ISNUMBER(Table1[[#This Row],[Qtr]]),CONCATENATE(Table1[[#This Row],[Year]]," Q",Table1[[#This Row],[Qtr]]),CONCATENATE(Table1[[#This Row],[Year]],Table1[[#This Row],[Qtr]])) -> 2009 Q3 | L10: A Office | M10: Completed | N10: 1 | O10: 31 | Q10: 27000 | R10: =Q10*(Y10/W10) -> 23151.88 | S10: =IF(AND(ISNUMBER(R10),R10>=15000),"Yes",IF(R10="","Unknown","No")) -> Yes | V10: 50101.4 | W10: =V10*10.764 -> 539291.47 | X10: 42960.8 | Y10: =+X10*10.764 -> 462430.05 | AC10: =IF(Table1[[#This Row],[For Sale or For Lease?]]="For Lease",Table1[[#This Row],[Office UFA (Net) (sf)]]-Table1[[#This Row],[Pre-leased space (Usable FA) (sf)]]-Table1[[#This Row],[Pre-sold (Usable FA) (sf)]]-Table1[[#This Row],[Self-use space (Usable FA) (sf)]],0) -> 0 | AD10: =IF(Table1[[#This Row],[For Sale or For Lease?]]="For Sale",Table1[[#This Row],[Office UFA (Net) (sf)]]-Table1[[#This Row],[Pre-leased space (Usable FA) (sf)]]-Table1[[#This Row],[Pre-sold (Usable FA) (sf)]]-Table1[[#This Row],[Self-use space (Usable FA) (sf)]],0) -> 462430.05 | AE10: =IF(Table1[[#This Row],[For Sale or For Lease?]]="Uncertain",Table1[[#This Row],[Office UFA (Net) (sf)]]-Table1[[#This Row],[Pre-leased space (Usable FA) (sf)]]-Table1[[#This Row],[Pre-sold (Usable FA) (sf)]]-Table1[[#This Row],[Self-use space (Usable FA) (sf)]],0) -> 0 | AF10: =1-SUM(Table1[[#This Row],[Space available for lease (Usable FA) (sf)]:[Space available uncertain of use (Usable FA) (sf)]])/Table1[[#This Row],[Office UFA (Net) (sf)]] -> 0 | AG10: Commercial | AH10: OP Issued | AI10: BD Monthly Digest | AJ10: 40026 | AK10: 40092 | AL10: Redevelopment | AM10: Billion Development | AN10: Private Sector | AO10: For Sale | AP10: Strata-title | AQ10: originally was 星島大廈, bought in 2005 at HK$ 37Mn/ Apple Daily 6Oct09: has sold 70% but will keep 7 floors for leasing/Sam Li (7 Jun 2011):all Billion owned portion has been sold | AR10: KK022
A11: 鱷魚恤中心 | B11: Crocodile Centre | C11: 79 Hoi Yuen Road | E11: Kwun Tong | F11: =VLOOKUP(Table1[[#This Row],[CBRE sub-markets]],Reference!$A$2:$B$31,2,FALSE) -> Kowloon East | G11: =VLOOKUP(Table1[[#This Row],[CBRE sub-markets]],Reference!$A$2:$D$31,3,FALSE) -> 7 | H11: =VLOOKUP(Table1[[#This Row],[CBRE sub-markets]],Reference!$A$2:$D$31,4,FALSE) -> Kowloon | I11: 2009 | J11: 3 | K11: =IF(ISNUMBER(Table1[[#This Row],[Qtr]]),CONCATENATE(Table1[[#This Row],[Year]]," Q",Table1[[#This Row],[Qtr]]),CONCATENATE(Table1[[#This Row],[Year]],Table1[[#This Row],[Qtr]])) -> 2009 Q3 | L11: A Office | M11: Completed | N11: 1 | O11: 23+2 basement | Q11: 11080 | R11: =Q11*(Y11/W11) -> 7922.2 | S11: =IF(AND(ISNUMBER(R11),R11>=15000),"Yes",IF(R11="","Unknown","No")) -> No | V11: =W11/10.764 -> 13381.643 | W11: =11080*(25-10-2) -> 144040 | X11: =V11*0.715 -> 9567.8744 | Y11: =X11*10.764 -> 102988.6 | AC11: =IF(Table1[[#This Row],[For Sale or For Lease?]]="For Lease",Table1[[#This Row],[Office UFA (Net) (sf)]]-Table1[[#This Row],[Pre-leased space (Usable FA) (sf)]]-Table1[[#This Row],[Pre-sold (Usable FA) (sf)]]-Table1[[#This Row],[Self-use space (Usable FA) (sf)]],0) -> 102988.6 | AD11: =IF(Table1[[#This Row],[For Sale or For Lease?]]="For Sale",Table1[[#This Row],[Office UFA (Net) (sf)]]-Table1[[#This Row],[Pre-leased space (Usable FA) (sf)]]-Table1[[#This Row],[Pre-sold (Usable FA) (sf)]]-Table1[[#This Row],[Self-use space (Usable FA) (sf)]],0) -> 0 | AE11: =IF(Table1[[#This Row],[For Sale or For Lease?]]="Uncertain",Table1[[#This Row],[Office UFA (Net) (sf)]]-Table1[[#This Row],[Pre-leased space (Usable FA) (sf)]]-Table1[[#This Row],[Pre-sold (Usable FA) (sf)]]-Table1[[#This Row],[Self-use space (Usable FA) (sf)]],0) -> 0 | AF11: =1-SUM(Table1[[#This Row],[Space available for lease (Usable FA) (sf)]:[Space available uncertain of use (Usable FA) (sf)]])/Table1[[#This Row],[Office UFA (Net) (sf)]] -> 0 | AG11: Commercial | AH11: OP Issued | AI11: BD Monthly Digest | AJ11: 40057 | AK11: 40122 | AM11: Lai Sun Development / Crocodile KT Investment Ltd | AN11: Private Sector | AO11: For Lease | AP11: Single owner | AQ11: Total GFA: 240,000 sf for the entire building including the lower retail portion/ Feb 2009./Sam Li (7 Jun 2011):Fully leased | AR11: KK023
A12: 絲寶國際中心 | B12: C-Bons International Centre (formerly: One Harbour East) | C12: 108 Wai Yip Street | E12: Kwun Tong | F12: =VLOOKUP(Table1[[#This Row],[CBRE sub-markets]],Reference!$A$2:$B$31,2,FALSE) -> Kowloon East | G12: =VLOOKUP(Table1[[#This Row],[CBRE sub-markets]],Reference!$A$2:$D$31,3,FALSE) -> 7 | H12: =VLOOKUP(Table1[[#This Row],[CBRE sub-markets]],Reference!$A$2:$D$31,4,FALSE) -> Kowloon | I12: 2009 | J12: 4 | K12: =IF(ISNUMBER(Table1[[#This Row],[Qtr]]),CONCATENATE(Table1[[#This Row],[Year]]," Q",Table1[[#This Row],[Qtr]]),CONCATENATE(Table1[[#This Row],[Year]],Table1[[#This Row],[Qtr]])) -> 2009 Q4 | L12: A Office | M12: Completed | N12: 1 | O12: 25+1 basement | Q12: =W12/25 -> 11697.196 | R12: =Q12*(Y12/W12) -> 9348.4048 | S12: =IF(AND(ISNUMBER(R12),R12>=15000),"Yes",IF(R12="","Unknown","No")) -> No | V12: 27167.4 | W12: =+V12*10.764 -> 292429.89 | X12: 21712.2 | Y12: =+X12*10.764 -> 233710.12 | AC12: =IF(Table1[[#This Row],[For Sale or For Lease?]]="For Lease",Table1[[#This Row],[Office UFA (Net) (sf)]]-Table1[[#This Row],[Pre-leased space (Usable FA) (sf)]]-Table1[[#This Row],[Pre-sold (Usable FA) (sf)]]-Table1[[#This Row],[Self-use space (Usable FA) (sf)]],0) -> 233710.12 | AD12: =IF(Table1[[#This Row],[For Sale or For Lease?]]="For Sale",Table1[[#This Row],[Office UFA (Net) (sf)]]-Table1[[#This Row],[Pre-leased space (Usable FA) (sf)]]-Table1[[#This Row],[Pre-sold (Usable FA) (sf)]]-Table1[[#This Row],[Self-use space (Usable FA) (sf)]],0) -> 0 | AE12: =IF(Table1[[#This Row],[For Sale or For Lease?]]="Uncertain",Table1[[#This Row],[Office UFA (Net) (sf)]]-Table1[[#This Row],[Pre-leased space (Usable FA) (sf)]]-Table1[[#This Row],[Pre-sold (Usable FA) (sf)]]-Table1[[#This Row],[Self-use space (Usable FA) (sf)]],0) -> 0 | AF12: =1-SUM(Table1[[#This Row],[Space available for lease (Usable FA) (sf)]:[Space available uncertain of use (Usable FA) (sf)]])/Table1[[#This Row],[Office UFA (Net) (sf)]] -> 0 | AG12: Commercial | AH12: OP Issued | AI12: BD Monthly Digest | AJ12: 40148 | AK12: 40212 | AL12: Redevelopment | AM12: Sun Hung Kai Properties | AN12: Private Sector | AO12: For Lease | AP12: Strata-title | AQ12: Previously named as MC7/ [21Aug09 OS-Kln: 1) asking price HK$ 5,000 psf on average 2) asking price of carparking space is approx. HK$ 500,000 3) efficiency is 80% as quoted by the landlord 4) tentative OP at Q1 2010 5) presale consent was granted by the Government ] | AR12: KK024
B13: The Cameron | C13: 33 Cameron Road | E13: Tsim Sha Tsui | F13: =VLOOKUP(Table1[[#This Row],[CBRE sub-markets]],Reference!$A$2:$B$31,2,FALSE) -> Tsim Sha Tsui | G13: =VLOOKUP(Table1[[#This Row],[CBRE sub-markets]],Reference!$A$2:$D$31,3,FALSE) -> 6 | H13: =VLOOKUP(Table1[[#This Row],[CBRE sub-markets]],Reference!$A$2:$D$31,4,FALSE) -> Kowloon | I13: 2009 | J13: 4 | K13: =IF(ISNUMBER(Table1[[#This Row],[Qtr]]),CONCATENATE(Table1[[#This Row],[Year]]," Q",Table1[[#This Row],[Qtr]]),CONCATENATE(Table1[[#This Row],[Year]],Table1[[#This Row],[Qtr]])) -> 2009 Q4 | L13: B Office | M13: Completed | N13: 1 | O13: 25 | Q13: 4000 | R13: =Q13*(Y13/W13) -> 2297.3704 | S13: =IF(AND(ISNUMBER(R13),R13>=15000),"Yes",IF(R13="","Unknown","No")) -> No | V13: 8427.2 | W13: 90710.381 | X13: 4840.1 | Y13: 52098.836 | AC13: =IF(Table1[[#This Row],[For Sale or For Lease?]]="For Lease",Table1[[#This Row],[Office UFA (Net) (sf)]]-Table1[[#This Row],[Pre-leased space (Usable FA) (sf)]]-Table1[[#This Row],[Pre-sold (Usable FA) (sf)]]-Table1[[#This Row],[Self-use space (Usable FA) (sf)]],0) -> 52098.836 | AD13: =IF(Table1[[#This Row],[For Sale or For Lease?]]="For Sale",Table1[[#This Row],[Office UFA (Net) (sf)]]-Table1[[#This Row],[Pre-leased space (Usable FA) (sf)]]-Table1[[#This Row],[Pre-sold (Usable FA) (sf)]]-Table1[[#This Row],[Self-use space (Usable FA) (sf)]],0) -> 0 | AE13: =IF(Table1[[#This Row],[For Sale or For Lease?]]="Uncertain",Table1[[#This Row],[Office UFA (Net) (sf)]]-Table1[[#This Row],[Pre-leased space (Usable FA) (sf)]]-Table1[[#This Row],[Pre-sold (Usable FA) (sf)]]-Table1[[#This Row],[Self-use space (Usable FA) (sf)]],0) -> 0 | AF13: =1-SUM(Table1[[#This Row],[Space available for lease (Usable FA) (sf)]:[Space available uncertain of use (Usable FA) (sf)]])/Table1[[#This Row],[Office UFA (Net) (sf)]] -> 0 | AG13: Commercial | AH13: OP Issued | AI13: BD Monthly Digest | AJ13: 40087 | AK13: 40147 | AM13: Lammington Investment Holdings Ltd | AN13: Private Sector | AO13: For Lease | AP13: Single owner | AQ13: 2.8m ceiling height, column free floor plate, ~4000 sf gross typical floor plate/Sam Li (7 Jun 2011):Fully leased | AR13: TS034 | AV13: MULTIPOLYGON (((114.174830346 22.2996842730001,114.174847126 22.2996318240001,114.174942245 22.2996585990001,114.175003454 22.299467296,114.174852672 22.2994253020001,114.174770018 22.2996871050001,114.174824529 22.29970245,114.174830346 22.2996842730001)))
A14: 寧晉中心 | B14: Legend Tower | C14: 7 Shing Yip Street | E14: Kwun Tong | F14: =VLOOKUP(Table1[[#This Row],[CBRE sub-markets]],Reference!$A$2:$B$31,2,FALSE) -> Kowloon East | G14: =VLOOKUP(Table1[[#This Row],[CBRE sub-markets]],Reference!$A$2:$D$31,3,FALSE) -> 7 | H14: =VLOOKUP(Table1[[#This Row],[CBRE sub-markets]],Reference!$A$2:$D$31,4,FALSE) -> Kowloon | I14: 2010 | J14: 1 | K14: =IF(ISNUMBER(Table1[[#This Row],[Qtr]]),CONCATENATE(Table1[[#This Row],[Year]]," Q",Table1[[#This Row],[Qtr]]),CONCATENATE(Table1[[#This Row],[Year]],Table1[[#This Row],[Qtr]])) -> 2010 Q1 | L14: A Office | M14: Completed | N14: 1 | O14: 32 | Q14: 18500 | R14: =Q14*(Y14/W14) -> 13875 | S14: =IF(AND(ISNUMBER(R14),R14>=15000),"Yes",IF(R14="","Unknown","No")) -> No | V14: =Table1[[#This Row],[Office GFA (sf)]]/10.7639 -> 36109.031 | W14: 388674 | X14: =Table1[[#This Row],[Office UFA (Net) (sf)]]/10.7639 -> 27081.773 | Y14: 291505.5 | AC14: =IF(Table1[[#This Row],[For Sale or For Lease?]]="For Lease",Table1[[#This Row],[Office UFA (Net) (sf)]]-Table1[[#This Row],[Pre-leased space (Usable FA) (sf)]]-Table1[[#This Row],[Pre-sold (Usable FA) (sf)]]-Table1[[#This Row],[Self-use space (Usable FA) (sf)]],0) -> 0 | AD14: =IF(Table1[[#This Row],[For Sale or For Lease?]]="For Sale",Table1[[#This Row],[Office UFA (Net) (sf)]]-Table1[[#This Row],[Pre-leased space (Usable FA) (sf)]]-Table1[[#This Row],[Pre-sold (Usable FA) (sf)]]-Table1[[#This Row],[Self-use space (Usable FA) (sf)]],0) -> 291505.5 | AE14: =IF(Table1[[#This Row],[For Sale or For Lease?]]="Uncertain",Table1[[#This Row],[Office UFA (Net) (sf)]]-Table1[[#This Row],[Pre-leased space (Usable FA) (sf)]]-Table1[[#This Row],[Pre-sold (Usable FA) (sf)]]-Table1[[#This Row],[Self-use space (Usable FA) (sf)]],0) -> 0 | AF14: =1-SUM(Table1[[#This Row],[Space available for lease (Usable FA) (sf)]:[Space available uncertain of use (Usable FA) (sf)]])/Table1[[#This Row],[Office UFA (Net) (sf)]] -> 0 | AG14: Commercial | AH14: OP Issued | AI14: BD Monthly Digest | AJ14: 40179 | AK14: 40246 | AM14: Billion Development | AN14: Private Sector | AO14: For Sale | AP14: Strata-title | AR14: KK025
A15: 環球貿易廣場3期 | B15: International Commerce Centre Phase 3 | C15: 1 Austin Road West (Union Square Phase 7) | D15: KIL 11080 | E15: Tsim Sha Tsui West | F15: =VLOOKUP(Table1[[#This Row],[CBRE sub-markets]],Reference!$A$2:$B$31,2,FALSE) -> Tsim Sha Tsui West | G15: =VLOOKUP(Table1[[#This Row],[CBRE sub-markets]],Reference!$A$2:$D$31,3,FALSE) -> 6 | H15: =VLOOKUP(Table1[[#This Row],[CBRE sub-markets]],Reference!$A$2:$D$31,4,FALSE) -> Kowloon | I15: 2010 | J15: 2 | K15: =IF(ISNUMBER(Table1[[#This Row],[Qtr]]),CONCATENATE(Table1[[#This Row],[Year]]," Q",Table1[[#This Row],[Qtr]]),CONCATENATE(Table1[[#This Row],[Year]],Table1[[#This Row],[Qtr]])) -> 2010 Q2 | L15: A Office | M15: Completed | N15: 1 | O15: 108+4basement (78-99/F Total 18 floors) | Q15: 33000 | R15: =Q15*(Y15/W15) -> 25740 | S15: =IF(AND(ISNUMBER(R15),R15>=15000),"Yes",IF(R15="","Unknown","No")) -> Yes | V15: =W15/10.764 -> 55394.649 | W15: =2290606-778371-915967 -> 596268 | X15: =Y15/10.764 -> 43207.826 | Y15: =W15*0.78 -> 465089.04 | AC15: =IF(Table1[[#This Row],[For Sale or For Lease?]]="For Lease",Table1[[#This Row],[Office UFA (Net) (sf)]]-Table1[[#This Row],[Pre-leased space (Usable FA) (sf)]]-Table1[[#This Row],[Pre-sold (Usable FA) (sf)]]-Table1[[#This Row],[Self-use space (Usable FA) (sf)]],0) -> 465089.04 | AD15: =IF(Table1[[#This Row],[For Sale or For Lease?]]="For Sale",Table1[[#This Row],[Office UFA (Net) (sf)]]-Table1[[#This Row],[Pre-leased space (Usable FA) (sf)]]-Table1[[#This Row],[Pre-sold (Usable FA) (sf)]]-Table1[[#This Row],[Self-use space (Usable FA) (sf)]],0) -> 0 | AE15: =IF(Table1[[#This Row],[For Sale or For Lease?]]="Uncertain",Table1[[#This Row],[Office UFA (Net) (sf)]]-Table1[[#This Row],[Pre-leased space (Usable FA) (sf)]]-Table1[[#This Row],[Pre-sold (Usable FA) (sf)]]-Table1[[#This Row],[Self-use space (Usable FA) (sf)]],0) -> 0 | AF15: =1-SUM(Table1[[#This Row],[Space available for lease (Usable FA) (sf)]:[Space available uncertain of use (Usable FA) (sf)]])/Table1[[#This Row],[Office UFA (Net) (sf)]] -> 0 | AG15: Commercial/ Hotel | AH15: OP Issued | AI15: Stacking Plan from OS-Kln | AJ15: 40305 | AK15: 40045 | AL15: Site | AM15: Sun Hung Kai Properties | AN15: Private Sector | AO15: For Lease | AP15: Single owner | AQ15: OS-Kln SamLi (24Mar10): "It is highly likely that verbal confirmation of full OP of the building will be obtained by tomorrow (25 March) and formal OP certificate will be followed in a week time." BD Mar 2010 Mthly Digest: GFA (incl Hotel) = 2,923,189 sf; UFA (incl Hotel) = 1,872,565 sf | AR15: TS031
A16: 嘉里中心 | B16: Kerry Centre | C16: 683 King's Road | E16: Quarry Bay | F16: =VLOOKUP(Table1[[#This Row],[CBRE sub-markets]],Reference!$A$2:$B$31,2,FALSE) -> Hong Kong East | G16: =VLOOKUP(Table1[[#This Row],[CBRE sub-markets]],Reference!$A$2:$D$31,3,FALSE) -> 4 | H16: =VLOOKUP(Table1[[#This Row],[CBRE sub-markets]],Reference!$A$2:$D$31,4,FALSE) -> Hong Kong Island | I16: 2010 | J16: 3 | K16: =IF(ISNUMBER(Table1[[#This Row],[Qtr]]),CONCATENATE(Table1[[#This Row],[Year]]," Q",Table1[[#This Row],[Qtr]]),CONCATENATE(Table1[[#This Row],[Year]],Table1[[#This Row],[Qtr]])) -> 2010 Q3 | L16: A Office | M16: Completed | N16: 1 | O16: 29+4 basement | Q16: =W16/29 -> 14564.655 | R16: =Q16*(Y16/W16) -> 12962.543 | S16: =IF(AND(ISNUMBER(R16),R16>=15000),"Yes",IF(R16="","Unknown","No")) -> No | V16: =Table1[[#This Row],[Office GFA (sf)]]/10.7639 -> 39239.959 | W16: 422375 | X16: =Table1[[#This Row],[Office UFA (Net) (sf)]]/10.7639 -> 34923.564 | Y16: 375913.75 | AC16: =IF(Table1[[#This Row],[For Sale or For Lease?]]="For Lease",Table1[[#This Row],[Office UFA (Net) (sf)]]-Table1[[#This Row],[Pre-leased space (Usable FA) (sf)]]-Table1[[#This Row],[Pre-sold (Usable FA) (sf)]]-Table1[[#This Row],[Self-use space (Usable FA) (sf)]],0) -> 375913.75 | AD16: =IF(Table1[[#This Row],[For Sale or For Lease?]]="For Sale",Table1[[#This Row],[Office UFA (Net) (sf)]]-Table1[[#This Row],[Pre-leased space (Usable FA) (sf)]]-Table1[[#This Row],[Pre-sold (Usable FA) (sf)]]-Table1[[#This Row],[Self-use space (Usable FA) (sf)]],0) -> 0 | AE16: =IF(Table1[[#This Row],[For Sale or For Lease?]]="Uncertain",Table1[[#This Row],[Office UFA (Net) (sf)]]-Table1[[#This Row],[Pre-leased space (Usable FA) (sf)]]-Table1[[#This Row],[Pre-sold (Usable FA) (sf)]]-Table1[[#This Row],[Self-use space (Usable FA) (sf)]],0) -> 0 | AF16: =1-SUM(Table1[[#This Row],[Space available for lease (Usable FA) (sf)]:[Space available uncertain of use (Usable FA) (sf)]])/Table1[[#This Row],[Office UFA (Net) (sf)]] -> 0 | AG16: Commercial | AH16: OP Issued | AI16: BD Monthly Digest | AJ16: 40422 | AK16: 40534 | AM16: Kerry Properties | AN16: Private Sector | AO16: For Lease | AP16: Single owner | AQ16: Completed. AR2008 (Cynthia): Kerry Properties owns 40% of the project; Office + Retail/ Rhodri: Kerry will reserve half of the building for their own use OS-HKI, KT (23Mar10): "the OP is supposed to be completed earlier in Aug 2010 rather than Oct 2010. Expected effective rental for one whole floor is HK$30+." | AR16: HE014
A17: 卓匯中心 | B17: Excel Centre | C17: 483A Castle Peak Road | E17: Cheung Sha Wan | F17: =VLOOKUP(Table1[[#This Row],[CBRE sub-markets]],Reference!$A$2:$B$31,2,FALSE) -> Kowloon Others | G17: =VLOOKUP(Table1[[#This Row],[CBRE sub-markets]],Reference!$A$2:$D$31,3,FALSE) -> 8 | H17: =VLOOKUP(Table1[[#This Row],[CBRE sub-markets]],Reference!$A$2:$D$31,4,FALSE) -> Kowloon | I17: 2010 | J17: 4 | K17: =IF(ISNUMBER(Table1[[#This Row],[Qtr]]),CONCATENATE(Table1[[#This Row],[Year]]," Q",Table1[[#This Row],[Qtr]]),CONCATENATE(Table1[[#This Row],[Year]],Table1[[#This Row],[Qtr]])) -> 2010 Q4 | L17: B Office | M17: Completed | N17: 1 | O17: 32 | Q17: 5961 | R17: =Q17*(Y17/W17) -> 4253.4982 | S17: =IF(AND(ISNUMBER(R17),R17>=15000),"Yes",IF(R17="","Unknown","No")) -> No | V17: 9768 | W17: =+V17*10.764 -> 105142.75 | X17: 6970 | Y17: =+X17*10.764 -> 75025.08 | AC17: =IF(Table1[[#This Row],[For Sale or For Lease?]]="For Lease",Table1[[#This Row],[Office UFA (Net) (sf)]]-Table1[[#This Row],[Pre-leased space (Usable FA) (sf)]]-Table1[[#This Row],[Pre-sold (Usable FA) (sf)]]-Table1[[#This Row],[Self-use space (Usable FA) (sf)]],0) -> 75025.08 | AD17: =IF(Table1[[#This Row],[For Sale or For Lease?]]="For Sale",Table1[[#This Row],[Office UFA (Net) (sf)]]-Table1[[#This Row],[Pre-leased space (Usable FA) (sf)]]-Table1[[#This Row],[Pre-sold (Usable FA) (sf)]]-Table1[[#This Row],[Self-use space (Usable FA) (sf)]],0) -> 0 | AE17: =IF(Table1[[#This Row],[For Sale or For Lease?]]="Uncertain",Table1[[#This Row],[Office UFA (Net) (sf)]]-Table1[[#This Row],[Pre-leased space (Usable FA) (sf)]]-Table1[[#This Row],[Pre-sold (Usable FA) (sf)]]-Table1[[#This Row],[Self-use space (Usable FA) (sf)]],0) -> 0 | AF17: =1-SUM(Table1[[#This Row],[Space available for lease (Usable FA) (sf)]:[Space available uncertain of use (Usable FA) (sf)]])/Table1[[#This Row],[Office UFA (Net) (sf)]] -> 0 | AG17: Commercial | AH17: OP Issued | AI17: BD Monthly Digest | AJ17: 40513 | AK17: 40682 | AL17: Redevelopment | AM17: Sun Hung Kai Properties | AN17: Private Sector | AO17: For Lease | AP17: Single owner | AQ17: OP received Dec 2010 | AR17: NS016 | AV17: MULTIPOLYGON (((114.150213458 22.3388642,114.150290204 22.338671905,114.150094899 22.338604542,114.149998219 22.338847463,114.150031777 22.338858595,114.150050887 22.3388076410001,114.150213458 22.3388642)))
B18: 50 Connaught Road Central | C18: 50 Connaught Road Central | E18: Central | F18: =VLOOKUP(Table1[[#This Row],[CBRE sub-markets]],Reference!$A$2:$B$31,2,FALSE) -> Central | G18: =VLOOKUP(Table1[[#This Row],[CBRE sub-markets]],Reference!$A$2:$D$31,3,FALSE) -> 1 | H18: =VLOOKUP(Table1[[#This Row],[CBRE sub-markets]],Reference!$A$2:$D$31,4,FALSE) -> Hong Kong Island | I18: 2011 | J18: 1 | K18: =IF(ISNUMBER(Table1[[#This Row],[Qtr]]),CONCATENATE(Table1[[#This Row],[Year]]," Q",Table1[[#This Row],[Qtr]]),CONCATENATE(Table1[[#This Row],[Year]],Table1[[#This Row],[Qtr]])) -> 2011 Q1 | L18: A Office | M18: Completed | N18: 1 | O18: 28 | Q18: =W18/O18 -> 5277.4643 | R18: =Q18*(Y18/W18) -> 4380.2954 | S18: =IF(AND(ISNUMBER(R18),R18>=15000),"Yes",IF(R18="","Unknown","No")) -> No | V18: =Table1[[#This Row],[Office GFA (sf)]]/10.7639 -> 13728.203 | W18: 147769 | X18: =Table1[[#This Row],[Office UFA (Net) (sf)]]/10.7639 -> 11394.408 | Y18: 122648.27 | AC18: =IF(Table1[[#This Row],[For Sale or For Lease?]]="For Lease",Table1[[#This Row],[Office UFA (Net) (sf)]]-Table1[[#This Row],[Pre-leased space (Usable FA) (sf)]]-Table1[[#This Row],[Pre-sold (Usable FA) (sf)]]-Table1[[#This Row],[Self-use space (Usable FA) (sf)]],0) -> 122648.27 | AD18: =IF(Table1[[#This Row],[For Sale or For Lease?]]="For Sale",Table1[[#This Row],[Office UFA (Net) (sf)]]-Table1[[#This Row],[Pre-leased space (Usable FA) (sf)]]-Table1[[#This Row],[Pre-sold (Usable FA) (sf)]]-Table1[[#This Row],[Self-use space (Usable FA) (sf)]],0) -> 0 | AE18: =IF(Table1[[#This Row],[For Sale or For Lease?]]="Uncertain",Table1[[#This Row],[Office UFA (Net) (sf)]]-Table1[[#This Row],[Pre-leased space (Usable FA) (sf)]]-Table1[[#This Row],[Pre-sold (Usable FA) (sf)]]-Table1[[#This Row],[Self-use space (Usable FA) (sf)]],0) -> 0 | AF18: =1-SUM(Table1[[#This Row],[Space available for lease (Usable FA) (sf)]:[Space available uncertain of use (Usable FA) (sf)]])/Table1[[#This Row],[Office UFA (Net) (sf)]] -> 0 | AG18: Commercial | AH18: OP Issued | AI18: BD Monthly Digest | AJ18: 40575 | AK18: 40675 | AL18: Redevelopment | AM18: Century Land Ltd (Citi Group/Apollo) / National Properties | AN18: Private Sector | AO18: For Lease | AP18: Single owner | AQ18: May 2012: sold to Agricultural Bank of China for $4.88 billion. Deal done by Colliers. | AR18: CC037
B19: One Island South | C19: 2 Heung Yip Road | E19: Wong Chuk Hang | F19: =VLOOKUP(Table1[[#This Row],[CBRE sub-markets]],Reference!$A$2:$B$31,2,FALSE) -> Wong Chuk Hang | G19: =VLOOKUP(Table1[[#This Row],[CBRE sub-markets]],Reference!$A$2:$D$31,3,FALSE) -> 5 | H19: =VLOOKUP(Table1[[#This Row],[CBRE sub-markets]],Reference!$A$2:$D$31,4,FALSE) -> Hong Kong Island | I19: 2011 | J19: 1 | K19: =IF(ISNUMBER(Table1[[#This Row],[Qtr]]),CONCATENATE(Table1[[#This Row],[Year]]," Q",Table1[[#This Row],[Qtr]]),CONCATENATE(Table1[[#This Row],[Year]],Table1[[#This Row],[Qtr]])) -> 2011 Q1 | L19: A Office | M19: Completed | N19: 1 | O19: 31 | Q19: =W19/O19 -> 20200.355 | R19: =Q19*(Y19/W19) -> 15856.037 | S19: =IF(AND(ISNUMBER(R19),R19>=15000),"Yes",IF(R19="","Unknown","No")) -> Yes | V19: =Table1[[#This Row],[Office GFA (sf)]]/10.7639 -> 58176.962 | W19: 626211 | X19: =Table1[[#This Row],[Office UFA (Net) (sf)]]/10.7639 -> 45665.34 | Y19: 491537.15 | AC19: =IF(Table1[[#This Row],[For Sale or For Lease?]]="For Lease",Table1[[#This Row],[Office UFA (Net) (sf)]]-Table1[[#This Row],[Pre-leased space (Usable FA) (sf)]]-Table1[[#This Row],[Pre-sold (Usable FA) (sf)]]-Table1[[#This Row],[Self-use space (Usable FA) (sf)]],0) -> 0 | AD19: =IF(Table1[[#This Row],[For Sale or For Lease?]]="For Sale",Table1[[#This Row],[Office UFA (Net) (sf)]]-Table1[[#This Row],[Pre-leased space (Usable FA) (sf)]]-Table1[[#This Row],[Pre-sold (Usable FA) (sf)]]-Table1[[#This Row],[Self-use space (Usable FA) (sf)]],0) -> 491537.15 | AE19: =IF(Table1[[#This Row],[For Sale or For Lease?]]="Uncertain",Table1[[#This Row],[Office UFA (Net) (sf)]]-Table1[[#This Row],[Pre-leased space (Usable FA) (sf)]]-Table1[[#This Row],[Pre-sold (Usable FA) (sf)]]-Table1[[#This Row],[Self-use space (Usable FA) (sf)]],0) -> 0 | AF19: =1-SUM(Table1[[#This Row],[Space available for lease (Usable FA) (sf)]:[Space available uncertain of use (Usable FA) (sf)]])/Table1[[#This Row],[Office UFA (Net) (sf)]] -> 0 | AG19: Commercial | AH19: OP Issued | AI19: BD Monthly Digest | AJ19: 40575 | AK19: 40675 | AL19: Redevelopment | AM19: Wheelock Properties | AN19: Private Sector | AO19: For Sale | AP19: Strata-title | AQ19: Aug 2011 (Cynthia): Completed. Building both for sale and lease by landlord. | AR19: WCH003
B20: 18 Kowloon East (Po Lung Centre redevelopment) | C20: 18 Wang Chiu Road | E20: Kowloon Bay | F20: =VLOOKUP(Table1[[#This Row],[CBRE sub-markets]],Reference!$A$2:$B$31,2,FALSE) -> Kowloon East | G20: =VLOOKUP(Table1[[#This Row],[CBRE sub-markets]],Reference!$A$2:$D$31,3,FALSE) -> 7 | H20: =VLOOKUP(Table1[[#This Row],[CBRE sub-markets]],Reference!$A$2:$D$31,4,FALSE) -> Kowloon | I20: 2011 | J20: 1 | K20: =IF(ISNUMBER(Table1[[#This Row],[Qtr]]),CONCATENATE(Table1[[#This Row],[Year]]," Q",Table1[[#This Row],[Qtr]]),CONCATENATE(Table1[[#This Row],[Year]],Table1[[#This Row],[Qtr]])) -> 2011 Q1 | L20: A Office | M20: Completed | N20: 1 | O20: 27 | Q20: 22000 | R20: =Q20*(Y20/W20) -> 16720 | S20: =IF(AND(ISNUMBER(R20),R20>=15000),"Yes",IF(R20="","Unknown","No")) -> Yes | V20: =Table1[[#This Row],[Office GFA (sf)]]/10.7639 -> 38461.896 | W20: 414000 | X20: =Table1[[#This Row],[Office UFA (Net) (sf)]]/10.7639 -> 29231.041 | Y20: 314640 | AC20: =IF(Table1[[#This Row],[For Sale or For Lease?]]="For Lease",Table1[[#This Row],[Office UFA (Net) (sf)]]-Table1[[#This Row],[Pre-leased space (Usable FA) (sf)]]-Table1[[#This Row],[Pre-sold (Usable FA) (sf)]]-Table1[[#This Row],[Self-use space (Usable FA) (sf)]],0) -> 314640 | AD20: =IF(Table1[[#This Row],[For Sale or For Lease?]]="For Sale",Table1[[#This Row],[Office UFA (Net) (sf)]]-Table1[[#This Row],[Pre-leased space (Usable FA) (sf)]]-Table1[[#This Row],[Pre-sold (Usable FA) (sf)]]-Table1[[#This Row],[Self-use space (Usable FA) (sf)]],0) -> 0 | AE20: =IF(Table1[[#This Row],[For Sale or For Lease?]]="Uncertain",Table1[[#This Row],[Office UFA (Net) (sf)]]-Table1[[#This Row],[Pre-leased space (Usable FA) (sf)]]-Table1[[#This Row],[Pre-sold (Usable FA) (sf)]]-Table1[[#This Row],[Self-use space (Usable FA) (sf)]],0) -> 0 | AF20: =1-SUM(Table1[[#This Row],[Space available for lease (Usable FA) (sf)]:[Space available uncertain of use (Usable FA) (sf)]])/Table1[[#This Row],[Office UFA (Net) (sf)]] -> 0 | AG20: Commercial | AH20: OP Issued | AI20: BD Monthly Digest | AJ20: 40544 | AK20: 40675 | AL20: Redevelopment | AM20: Sino Land | AN20: Private Sector | AO20: For Lease | AP20: Single owner | AQ20: 03Nov2010 (SamLi): Low zone for lease – landlord expects HK$21 effective, benchmarking ET recent transactions (HK$21 for a 5k sfg unit); High zone for sale – looking for over HK$6k psf. Will be handled by different team from Sino Land/ With retail area, sky garden on 9/Fr Raised floor system, in-house caparking spaces. | AR20: CC040
A21: 萬兆豐中心 | B21: MG Tower | C21: 133 Hoi Bun Road | E21: Kwun Tong | F21: =VLOOKUP(Table1[[#This Row],[CBRE sub-markets]],Reference!$A$2:$B$31,2,FALSE) -> Kowloon East | G21: =VLOOKUP(Table1[[#This Row],[CBRE sub-markets]],Reference!$A$2:$D$31,3,FALSE) -> 7 | H21: =VLOOKUP(Table1[[#This Row],[CBRE sub-markets]],Reference!$A$2:$D$31,4,FALSE) -> Kowloon | I21: 2011 | J21: 2 | K21: =IF(ISNUMBER(Table1[[#This Row],[Qtr]]),CONCATENATE(Table1[[#This Row],[Year]]," Q",Table1[[#This Row],[Qtr]]),CONCATENATE(Table1[[#This Row],[Year]],Table1[[#This Row],[Qtr]])) -> 2011 Q2 | L21: A Office | M21: Completed | N21: 1 | O21: 25 | Q21: =+W21/O21 -> 24519.4 | R21: =Q21*(Y21/W21) -> 17891.16 | S21: =IF(AND(ISNUMBER(R21),R21>=15000),"Yes",IF(R21="","Unknown","No")) -> Yes | V21: =Table1[[#This Row],[Office GFA (sf)]]/10.7639 -> 56948.225 | W21: 612985 | X21: =Table1[[#This Row],[Office UFA (Net) (sf)]]/10.7639 -> 41553.619 | Y21: 447279 | AC21: =IF(Table1[[#This Row],[For Sale or For Lease?]]="For Lease",Table1[[#This Row],[Office UFA (Net) (sf)]]-Table1[[#This Row],[Pre-leased space (Usable FA) (sf)]]-Table1[[#This Row],[Pre-sold (Usable FA) (sf)]]-Table1[[#This Row],[Self-use space (Usable FA) (sf)]],0) -> 0 | AD21: =IF(Table1[[#This Row],[For Sale or For Lease?]]="For Sale",Table1[[#This Row],[Office UFA (Net) (sf)]]-Table1[[#This Row],[Pre-leased space (Usable FA) (sf)]]-Table1[[#This Row],[Pre-sold (Usable FA) (sf)]]-Table1[[#This Row],[Self-use space (Usable FA) (sf)]],0) -> 447279 | AE21: =IF(Table1[[#This Row],[For Sale or For Lease?]]="Uncertain",Table1[[#This Row],[Office UFA (Net) (sf)]]-Table1[[#This Row],[Pre-leased space (Usable FA) (sf)]]-Table1[[#This Row],[Pre-sold (Usable FA) (sf)]]-Table1[[#This Row],[Self-use space (Usable FA) (sf)]],0) -> 0 | AF21: =1-SUM(Table1[[#This Row],[Space available for lease (Usable FA) (sf)]:[Space available uncertain of use (Usable FA) (sf)]])/Table1[[#This Row],[Office UFA (Net) (sf)]] -> 0 | AG21: Commercial | AH21: OP Issued | AI21: BD Monthly Digest | AJ21: 40664 | AK21: 40764 | AL21: Redevelopment | AM21: Billion Development | AN21: Private Sector | AO21: For Sale | AP21: Strata-title | AR21: KK035
B22: 16 Hart Avenue | C22: 16 Hart Avenue | E22: Tsim Sha Tsui | F22: =VLOOKUP(Table1[[#This Row],[CBRE sub-markets]],Reference!$A$2:$B$31,2,FALSE) -> Tsim Sha Tsui | G22: =VLOOKUP(Table1[[#This Row],[CBRE sub-markets]],Reference!$A$2:$D$31,3,FALSE) -> 6 | H22: =VLOOKUP(Table1[[#This Row],[CBRE sub-markets]],Reference!$A$2:$D$31,4,FALSE) -> Kowloon | I22: 2011 | J22: 3 | K22: =IF(ISNUMBER(Table1[[#This Row],[Qtr]]),CONCATENATE(Table1[[#This Row],[Year]]," Q",Table1[[#This Row],[Qtr]]),CONCATENATE(Table1[[#This Row],[Year]],Table1[[#This Row],[Qtr]])) -> 2011 Q3 | L22: B Office | M22: Completed | N22: 1 | O22: 23 | Q22: =W22/O22 -> 1035.6372 | R22: =Q22*0.75 -> 776.7279 | S22: =IF(AND(ISNUMBER(R22),R22>=15000),"Yes",IF(R22="","Unknown","No")) -> No | V22: 2212.9 | W22: =+V22*10.764 -> 23819.656 | X22: =Y22/10.764 -> 1659.675 | Y22: =W22*0.75 -> 17864.742 | AC22: =IF(Table1[[#This Row],[For Sale or For Lease?]]="For Lease",Table1[[#This Row],[Office UFA (Net) (sf)]]-Table1[[#This Row],[Pre-leased space (Usable FA) (sf)]]-Table1[[#This Row],[Pre-sold (Usable FA) (sf)]]-Table1[[#This Row],[Self-use space (Usable FA) (sf)]],0) -> 17864.742 | AD22: =IF(Table1[[#This Row],[For Sale or For Lease?]]="For Sale",Table1[[#This Row],[Office UFA (Net) (sf)]]-Table1[[#This Row],[Pre-leased space (Usable FA) (sf)]]-Table1[[#This Row],[Pre-sold (Usable FA) (sf)]]-Table1[[#This Row],[Self-use space (Usable FA) (sf)]],0) -> 0 | AE22: =IF(Table1[[#This Row],[For Sale or For Lease?]]="Uncertain",Table1[[#This Row],[Office UFA (Net) (sf)]]-Table1[[#This Row],[Pre-leased space (Usable FA) (sf)]]-Table1[[#This Row],[Pre-sold (Usable FA) (sf)]]-Table1[[#This Row],[Self-use space (Usable FA) (sf)]],0) -> 0 | AF22: =1-SUM(Table1[[#This Row],[Space available for lease (Usable FA) (sf)]:[Space available uncertain of use (Usable FA) (sf)]])/Table1[[#This Row],[Office UFA (Net) (sf)]] -> 0 | AG22: Commercial | AH22: Plans Approved | AI22: BD Monthly Digest | AJ22: 40057 | AK22: 40122 | AM22: Cheong Ming Investment Co Ltd | AN22: Private Sector | AO22: For Lease | AP22: Single owner | AQ22: Sep 2011: OS to check whether it's office, retail, or serviced apartment near the Masterpiece | AR22: NS021 | AV22: MULTIPOLYGON (((114.175063536 22.2982295270001,114.175053883 22.2983822330001,114.175115847 22.2983857720001,114.175126259 22.2982331290001,114.175063536 22.2982295270001)))
A23: 陸海通大廈 | B23: LHT Tower | C23: 31 Queen's Road Central & 1-7 Theatre Lane | E23: Central | F23: =VLOOKUP(Table1[[#This Row],[CBRE sub-markets]],Reference!$A$2:$B$31,2,FALSE) -> Central | G23: =VLOOKUP(Table1[[#This Row],[CBRE sub-markets]],Reference!$A$2:$D$31,3,FALSE) -> 1 | H23: =VLOOKUP(Table1[[#This Row],[CBRE sub-markets]],Reference!$A$2:$D$31,4,FALSE) -> Hong Kong Island | I23: 2011 | J23: 4 | K23: =IF(ISNUMBER(Table1[[#This Row],[Qtr]]),CONCATENATE(Table1[[#This Row],[Year]]," Q",Table1[[#This Row],[Qtr]]),CONCATENATE(Table1[[#This Row],[Year]],Table1[[#This Row],[Qtr]])) -> 2011 Q4 | L23: A Office | M23: Completed | N23: 1 | O23: 28+1 basement | Q23: =W23/28 -> 4170.75 | R23: =Q23*(Y23/W23) -> 3781.8214 | S23: =IF(AND(ISNUMBER(R23),R23>=15000),"Yes",IF(R23="","Unknown","No")) -> No | V23: =Table1[[#This Row],[Office GFA (sf)]]/10.7639 -> 10849.32 | W23: 116781 | X23: =Table1[[#This Row],[Office UFA (Net) (sf)]]/10.7639 -> 9837.6053 | Y23: 105891 | AC23: =IF(Table1[[#This Row],[For Sale or For Lease?]]="For Lease",Table1[[#This Row],[Office UFA (Net) (sf)]]-Table1[[#This Row],[Pre-leased space (Usable FA) (sf)]]-Table1[[#This Row],[Pre-sold (Usable FA) (sf)]]-Table1[[#This Row],[Self-use space (Usable FA) (sf)]],0) -> 105891 | AD23: =IF(Table1[[#This Row],[For Sale or For Lease?]]="For Sale",Table1[[#This Row],[Office UFA (Net) (sf)]]-Table1[[#This Row],[Pre-leased space (Usable FA) (sf)]]-Table1[[#This Row],[Pre-sold (Usable FA) (sf)]]-Table1[[#This Row],[Self-use space (Usable FA) (sf)]],0) -> 0 | AE23: =IF(Table1[[#This Row],[For Sale or For Lease?]]="Uncertain",Table1[[#This Row],[Office UFA (Net) (sf)]]-Table1[[#This Row],[Pre-leased space (Usable FA) (sf)]]-Table1[[#This Row],[Pre-sold (Usable FA) (sf)]]-Table1[[#This Row],[Self-use space (Usable FA) (sf)]],0) -> 0 | AF23: =1-SUM(Table1[[#This Row],[Space available for lease (Usable FA) (sf)]:[Space available uncertain of use (Usable FA) (sf)]])/Table1[[#This Row],[Office UFA (Net) (sf)]] -> 0 | AG23: Commercial | AH23: OP Issued | AI23: BD Monthly Digest | AJ23: 40878 | AK23: 40941 | AL23: Redevelopment | AM23: The Luk Hoi Tong Corporation Ltd | AN23: Private Sector | AO23: For Lease | AP23: Single owner | AR23: CC038
A24: 龍子行大廈 | B24: Prosperity Tower (Dragon Seed Building redevelopment) | C24: 39 Queen's Road Central 19, 20, 21, 22, 23, 25 & 26 Li Yuen Street East | E24: Central | F24: =VLOOKUP(Table1[[#This Row],[CBRE sub-markets]],Reference!$A$2:$B$31,2,FALSE) -> Central | G24: =VLOOKUP(Table1[[#This Row],[CBRE sub-markets]],Reference!$A$2:$D$31,3,FALSE) -> 1 | H24: =VLOOKUP(Table1[[#This Row],[CBRE sub-markets]],Reference!$A$2:$D$31,4,FALSE) -> Hong Kong Island | I24: 2011 | J24: 4 | K24: =IF(ISNUMBER(Table1[[#This Row],[Qtr]]),CONCATENATE(Table1[[#This Row],[Year]]," Q",Table1[[#This Row],[Qtr]]),CONCATENATE(Table1[[#This Row],[Year]],Table1[[#This Row],[Qtr]])) -> 2011 Q4 | L24: A Office | M24: Completed | N24: 1 | O24: 30+1 basement | Q24: =W24/31 -> 4524.3523 | R24: =Q24*(Y24/W24) -> 3532.2587 | S24: =IF(AND(ISNUMBER(R24),R24>=15000),"Yes",IF(R24="","Unknown","No")) -> No | V24: 13030 | W24: =V24*10.764 -> 140254.92 | X24: 10172.8 | Y24: =X24*10.764 -> 109500.02 | AC24: =IF(Table1[[#This Row],[For Sale or For Lease?]]="For Lease",Table1[[#This Row],[Office UFA (Net) (sf)]]-Table1[[#This Row],[Pre-leased space (Usable FA) (sf)]]-Table1[[#This Row],[Pre-sold (Usable FA) (sf)]]-Table1[[#This Row],[Self-use space (Usable FA) (sf)]],0) -> 109500.02 | AD24: =IF(Table1[[#This Row],[For Sale or For Lease?]]="For Sale",Table1[[#This Row],[Office UFA (Net) (sf)]]-Table1[[#This Row],[Pre-leased space (Usable FA) (sf)]]-Table1[[#This Row],[Pre-sold (Usable FA) (sf)]]-Table1[[#This Row],[Self-use space (Usable FA) (sf)]],0) -> 0 | AE24: =IF(Table1[[#This Row],[For Sale or For Lease?]]="Uncertain",Table1[[#This Row],[Office UFA (Net) (sf)]]-Table1[[#This Row],[Pre-leased space (Usable FA) (sf)]]-Table1[[#This Row],[Pre-sold (Usable FA) (sf)]]-Table1[[#This Row],[Self-use space (Usable FA) (sf)]],0) -> 0 | AF24: =1-SUM(Table1[[#This Row],[Space available for lease (Usable FA) (sf)]:[Space available uncertain of use (Usable FA) (sf)]])/Table1[[#This Row],[Office UFA (Net) (sf)]] -> 0 | AG24: Commercial | AH24: OP Issued | AI24: BD Monthly Digest | AJ24: 40848 | AK24: 40941 | AL24: Redevelopment | AM24: New World | AN24: Private Sector | AO24: For Lease | AP24: Single owner | AQ24: Sep 2011: OP yet to be issued. Exp Oct 2011. Urban Group contact: Ken Wong (6543 6221) New World bought the building in 1999 for 136 million. | AR24: CC039
A25: 希慎廣場 | B25: Hysan Place | C25: 500 Hennessy Road | E25: Causeway Bay | F25: =VLOOKUP(Table1[[#This Row],[CBRE sub-markets]],Reference!$A$2:$B$31,2,FALSE) -> Wan Chai & Causeway Bay | G25: =VLOOKUP(Table1[[#This Row],[CBRE sub-markets]],Reference!$A$2:$D$31,3,FALSE) -> 3 | H25: =VLOOKUP(Table1[[#This Row],[CBRE sub-markets]],Reference!$A$2:$D$31,4,FALSE) -> Hong Kong Island | I25: 2012 | J25: 1 | K25: =IF(ISNUMBER(Table1[[#This Row],[Qtr]]),CONCATENATE(Table1[[#This Row],[Year]]," Q",Table1[[#This Row],[Qtr]]),CONCATENATE(Table1[[#This Row],[Year]],Table1[[#This Row],[Qtr]])) -> 2012 Q1 | L25: A Office | M25: Completed | N25: 1 | O25: 37+4 basement | Q25: 16000 | R25: =Q25*(Y25/W25) -> 14610.112 | S25: =IF(AND(ISNUMBER(R25),R25>=15000),"Yes",IF(R25="","Unknown","No")) -> No | V25: =+W25/10.764 -> 22652.824 | W25: 243835 | X25: =+V25*0.92 -> 20840.598 | Y25: 222653.53 | AC25: =IF(Table1[[#This Row],[For Sale or For Lease?]]="For Lease",Table1[[#This Row],[Office UFA (Net) (sf)]]-Table1[[#This Row],[Pre-leased space (Usable FA) (sf)]]-Table1[[#This Row],[Pre-sold (Usable FA) (sf)]]-Table1[[#This Row],[Self-use space (Usable FA) (sf)]],0) -> 222653.53 | AD25: =IF(Table1[[#This Row],[For Sale or For Lease?]]="For Sale",Table1[[#This Row],[Office UFA (Net) (sf)]]-Table1[[#This Row],[Pre-leased space (Usable FA) (sf)]]-Table1[[#This Row],[Pre-sold (Usable FA) (sf)]]-Table1[[#This Row],[Self-use space (Usable FA) (sf)]],0) -> 0 | AE25: =IF(Table1[[#This Row],[For Sale or For Lease?]]="Uncertain",Table1[[#This Row],[Office UFA (Net) (sf)]]-Table1[[#This Row],[Pre-leased space (Usable FA) (sf)]]-Table1[[#This Row],[Pre-sold (Usable FA) (sf)]]-Table1[[#This Row],[Self-use space (Usable FA) (sf)]],0) -> 0 | AF25: =1-SUM(Table1[[#This Row],[Space available for lease (Usable FA) (sf)]:[Space available uncertain of use (Usable FA) (sf)]])/Table1[[#This Row],[Office UFA (Net) (sf)]] -> 0 | AG25: Commercial | AH25: OP Issued | AI25: BD Monthly Digest | AJ25: 40969 | AK25: 41073 | AL25: Redevelopment | AM25: Hysan Development Co Ltd | AN25: Private Sector | AO25: For Lease | AP25: Single owner | AR25: CW017
B26: King Palace Plaza (55 King Yip Street) | C26: 24 Hing Yip Street & 55 King Yip Street | E26: Kwun Tong | F26: =VLOOKUP(Table1[[#This Row],[CBRE sub-markets]],Reference!$A$2:$B$31,2,FALSE) -> Kowloon East | G26: =VLOOKUP(Table1[[#This Row],[CBRE sub-markets]],Reference!$A$2:$D$31,3,FALSE) -> 7 | H26: =VLOOKUP(Table1[[#This Row],[CBRE sub-markets]],Reference!$A$2:$D$31,4,FALSE) -> Kowloon | I26: 2012 | J26: 1 | K26: =IF(ISNUMBER(Table1[[#This Row],[Qtr]]),CONCATENATE(Table1[[#This Row],[Year]]," Q",Table1[[#This Row],[Qtr]]),CONCATENATE(Table1[[#This Row],[Year]],Table1[[#This Row],[Qtr]])) -> 2012 Q1 | L26: A Office | M26: Completed | N26: 1 | O26: 30 | Q26: =+W26/O26 -> 10116.367 | R26: =Q26*(Y26/W26) -> 7587.275 | S26: =IF(AND(ISNUMBER(R26),R26>=15000),"Yes",IF(R26="","Unknown","No")) -> No | V26: =Table1[[#This Row],[Office GFA (sf)]]/10.7639 -> 28195.264 | W26: 303491 | X26: =Table1[[#This Row],[Office UFA (Net) (sf)]]/10.7639 -> 21146.448 | Y26: 227618.25 | AC26: =IF(Table1[[#This Row],[For Sale or For Lease?]]="For Lease",Table1[[#This Row],[Office UFA (Net) (sf)]]-Table1[[#This Row],[Pre-leased space (Usable FA) (sf)]]-Table1[[#This Row],[Pre-sold (Usable FA) (sf)]]-Table1[[#This Row],[Self-use space (Usable FA) (sf)]],0) -> 0 | AD26: =IF(Table1[[#This Row],[For Sale or For Lease?]]="For Sale",Table1[[#This Row],[Office UFA (Net) (sf)]]-Table1[[#This Row],[Pre-leased space (Usable FA) (sf)]]-Table1[[#This Row],[Pre-sold (Usable FA) (sf)]]-Table1[[#This Row],[Self-use space (Usable FA) (sf)]],0) -> 227618.25 | AE26: =IF(Table1[[#This Row],[For Sale or For Lease?]]="Uncertain",Table1[[#This Row],[Office UFA (Net) (sf)]]-Table1[[#This Row],[Pre-leased space (Usable FA) (sf)]]-Table1[[#This Row],[Pre-sold (Usable FA) (sf)]]-Table1[[#This Row],[Self-use space (Usable FA) (sf)]],0) -> 0 | AF26: =1-SUM(Table1[[#This Row],[Space available for lease (Usable FA) (sf)]:[Space available uncertain of use (Usable FA) (sf)]])/Table1[[#This Row],[Office UFA (Net) (sf)]] -> 0 | AG26: Commercial | AH26: OP Issued | AI26: BD Monthly Digest | AJ26: 40940 | AK26: 41072 | AL26: Redevelopment | AM26: Billion Development | AN26: Private Sector | AO26: For Sale | AP26: Strata-title | AQ26: 27Sep2011 (HKET): "already sold around 210,000 sf (69%), worth around $1.3 billion, almost $7,000 psf" Sep 2011: Sam (OS) - over 70% has been sold. "King of the King/王上王" bought 3 floors and will most likely get naming rights. The-Sun (17Aug2010): Billion pays HK$260.9Mn premium for converting the land use from industrial to commercial | AR26: KK039
B27: 28 Hennessy Road | C27: 24-34 Hennessy Road | E27: Wan Chai | F27: =VLOOKUP(Table1[[#This Row],[CBRE sub-markets]],Reference!$A$2:$B$31,2,FALSE) -> Wan Chai & Causeway Bay | G27: =VLOOKUP(Table1[[#This Row],[CBRE sub-markets]],Reference!$A$2:$D$31,3,FALSE) -> 3 | H27: =VLOOKUP(Table1[[#This Row],[CBRE sub-markets]],Reference!$A$2:$D$31,4,FALSE) -> Hong Kong Island | I27: 2012 | J27: 3 | K27: =IF(ISNUMBER(Table1[[#This Row],[Qtr]]),CONCATENATE(Table1[[#This Row],[Year]]," Q",Table1[[#This Row],[Qtr]]),CONCATENATE(Table1[[#This Row],[Year]],Table1[[#This Row],[Qtr]])) -> 2012 Q3 | L27: A Office | M27: Completed | N27: 1 | O27: 29+1 basement | Q27: 4935 | R27: =Q27*(Y27/W27) -> 4400.125 | S27: =IF(AND(ISNUMBER(R27),R27>=15000),"Yes",IF(R27="","Unknown","No")) -> No | V27: =W27/10.764 -> 11003.344 | W27: 118440 | X27: =Y27/10.764 -> 9810.7581 | Y27: 105603 | AC27: =IF(Table1[[#This Row],[For Sale or For Lease?]]="For Lease",Table1[[#This Row],[Office UFA (Net) (sf)]]-Table1[[#This Row],[Pre-leased space (Usable FA) (sf)]]-Table1[[#This Row],[Pre-sold (Usable FA) (sf)]]-Table1[[#This Row],[Self-use space (Usable FA) (sf)]],0) -> 105603 | AD27: =IF(Table1[[#This Row],[For Sale or For Lease?]]="For Sale",Table1[[#This Row],[Office UFA (Net) (sf)]]-Table1[[#This Row],[Pre-leased space (Usable FA) (sf)]]-Table1[[#This Row],[Pre-sold (Usable FA) (sf)]]-Table1[[#This Row],[Self-use space (Usable FA) (sf)]],0) -> 0 | AE27: =IF(Table1[[#This Row],[For Sale or For Lease?]]="Uncertain",Table1[[#This Row],[Office UFA (Net) (sf)]]-Table1[[#This Row],[Pre-leased space (Usable FA) (sf)]]-Table1[[#This Row],[Pre-sold (Usable FA) (sf)]]-Table1[[#This Row],[Self-use space (Usable FA) (sf)]],0) -> 0 | AF27: =1-SUM(Table1[[#This Row],[Space available for lease (Usable FA) (sf)]:[Space available uncertain of use (Usable FA) (sf)]])/Table1[[#This Row],[Office UFA (Net) (sf)]] -> 0 | AG27: Commercial | AH27: OP Issued | AI27: BD Monthly Digest | AJ27: 41091 | AK27: 41128 | AL27: Redevelopment | AM27: Swire Properties | AN27: Private Sector | AO27: For Lease | AP27: Single owner | AQ27: Aug 2012 (James): Swire confirm that OP for 28 HR has now been granted (late July) May 2012 (Ian): "the Generali deal to take the whole of 8QRE is complete. The two other parties who were interested have now turned their attention to 28HR. Should know next month if either will proceed. Would mean circa half the building is leased if one does. I believe the average targeting rental for the building is HK$66.66 psf" Aug 2011: Building to be completed around Q2 2012. Low to Top zone levels are built. Approval record of changing the land use at the Planning Department on November 2008 (http://www.ozp.tpb.gov.hk/doc/apply/H5_377_tc.pdf). (Feb 09: Plan w/ 2-12 Anton Street, 1-11 Landale Street - GFA of 279202 sf) | AR27: WC023
A28: 俊匯中心 | B28: Elite Centre | C28: 22 Hung To Road | E28: Kwun Tong | F28: =VLOOKUP(Table1[[#This Row],[CBRE sub-markets]],Reference!$A$2:$B$31,2,FALSE) -> Kowloon East | G28: =VLOOKUP(Table1[[#This Row],[CBRE sub-markets]],Reference!$A$2:$D$31,3,FALSE) -> 7 | H28: =VLOOKUP(Table1[[#This Row],[CBRE sub-markets]],Reference!$A$2:$D$31,4,FALSE) -> Kowloon | I28: 2012 | J28: 3 | K28: =IF(ISNUMBER(Table1[[#This Row],[Qtr]]),CONCATENATE(Table1[[#This Row],[Year]]," Q",Table1[[#This Row],[Qtr]]),CONCATENATE(Table1[[#This Row],[Year]],Table1[[#This Row],[Qtr]])) -> 2012 Q3 | L28: A Office | M28: Completed | N28: 1 | O28: 19 | Q28: 11875 | R28: =Q28*(Y28/W28) -> 8906.25 | S28: =IF(AND(ISNUMBER(R28),R28>=15000),"Yes",IF(R28="","Unknown","No")) -> No | V28: =Table1[[#This Row],[Office GFA (sf)]]/10.7639 -> 23714.174 | W28: 255257 | X28: =Table1[[#This Row],[Office UFA (Net) (sf)]]/10.7639 -> 17785.631 | Y28: 191442.75 | AC28: =IF(Table1[[#This Row],[For Sale or For Lease?]]="For Lease",Table1[[#This Row],[Office UFA (Net) (sf)]]-Table1[[#This Row],[Pre-leased space (Usable FA) (sf)]]-Table1[[#This Row],[Pre-sold (Usable FA) (sf)]]-Table1[[#This Row],[Self-use space (Usable FA) (sf)]],0) -> 0 | AD28: =IF(Table1[[#This Row],[For Sale or For Lease?]]="For Sale",Table1[[#This Row],[Office UFA (Net) (sf)]]-Table1[[#This Row],[Pre-leased space (Usable FA) (sf)]]-Table1[[#This Row],[Pre-sold (Usable FA) (sf)]]-Table1[[#This Row],[Self-use space (Usable FA) (sf)]],0) -> 191442.75 | AE28: =IF(Table1[[#This Row],[For Sale or For Lease?]]="Uncertain",Table1[[#This Row],[Office UFA (Net) (sf)]]-Table1[[#This Row],[Pre-leased space (Usable FA) (sf)]]-Table1[[#This Row],[Pre-sold (Usable FA) (sf)]]-Table1[[#This Row],[Self-use space (Usable FA) (sf)]],0) -> 0 | AF28: =1-SUM(Table1[[#This Row],[Space available for lease (Usable FA) (sf)]:[Space available uncertain of use (Usable FA) (sf)]])/Table1[[#This Row],[Office UFA (Net) (sf)]] -> 0 | AG28: Commercial | AH28: OP Issued | AI28: BD Monthly Digest | AJ28: 41122 | AK28: 41215 | AL28: Redevelopment | AM28: Sun Hung Kai Properties | AN28: Private Sector | AO28: For Sale | AP28: Strata-title | AQ28: Sep 2011: Sam (OS) - Majority of building sold on strata basis. 7/F (restaurant) for sale, askinh HK$9,000 psf; 29/F (top floor) for sale, subject to offer. Maybe 2012 Q3 completion. According to BOAML report May 27, 2011, the building will be sold off strata-title, with ASP at HK$5.3K psf. Sam Li (7 Jun 2011):70% sold (end May 11) | AR28: KK040
B29: CCB Tower | C29: 3 Connaught Road Central | E29: Central | F29: =VLOOKUP(Table1[[#This Row],[CBRE sub-markets]],Reference!$A$2:$B$31,2,FALSE) -> Central | G29: =VLOOKUP(Table1[[#This Row],[CBRE sub-markets]],Reference!$A$2:$D$31,3,FALSE) -> 1 | H29: =VLOOKUP(Table1[[#This Row],[CBRE sub-markets]],Reference!$A$2:$D$31,4,FALSE) -> Hong Kong Island | I29: 2012 | J29: 4 | K29: =IF(ISNUMBER(Table1[[#This Row],[Qtr]]),CONCATENATE(Table1[[#This Row],[Year]]," Q",Table1[[#This Row],[Qtr]]),CONCATENATE(Table1[[#This Row],[Year]],Table1[[#This Row],[Qtr]])) -> 2012 Q4 | L29: A Office | M29: Completed | N29: 1 | O29: 27+4 basement | Q29: =W29/27 -> 8308.1336 | R29: =Q29*(Y29/W29) -> 5610.1569 | S29: =IF(AND(ISNUMBER(R29),R29>=15000),"Yes",IF(R29="","Unknown","No")) -> No | V29: 20839.8 | W29: =+V29*10.764 -> 224319.61 | X29: 14072.3 | Y29: =+X29*10.764 -> 151474.24 | Z29: 88244.1 | AC29: =IF(Table1[[#This Row],[For Sale or For Lease?]]="For Lease",Table1[[#This Row],[Office UFA (Net) (sf)]]-Table1[[#This Row],[Pre-leased space (Usable FA) (sf)]]-Table1[[#This Row],[Pre-sold (Usable FA) (sf)]]-Table1[[#This Row],[Self-use space (Usable FA) (sf)]],0) -> 63230.137 | AD29: =IF(Table1[[#This Row],[For Sale or For Lease?]]="For Sale",Table1[[#This Row],[Office UFA (Net) (sf)]]-Table1[[#This Row],[Pre-leased space (Usable FA) (sf)]]-Table1[[#This Row],[Pre-sold (Usable FA) (sf)]]-Table1[[#This Row],[Self-use space (Usable FA) (sf)]],0) -> 0 | AE29: =IF(Table1[[#This Row],[For Sale or For Lease?]]="Uncertain",Table1[[#This Row],[Office UFA (Net) (sf)]]-Table1[[#This Row],[Pre-leased space (Usable FA) (sf)]]-Table1[[#This Row],[Pre-sold (Usable FA) (sf)]]-Table1[[#This Row],[Self-use space (Usable FA) (sf)]],0) -> 0 | AF29: =1-SUM(Table1[[#This Row],[Space available for lease (Usable FA) (sf)]:[Space available uncertain of use (Usable FA) (sf)]])/Table1[[#This Row],[Office UFA (Net) (sf)]] -> 0.58256837 | AG29: Commercial | AH29: OP Issued | AI29: BD Monthly Digest | AJ29: 41244 | AK29: 41326 | AL29: Redevelopment | AM29: Lai Sun Development / China Construction Bank (50/50) | AN29: Private Sector | AO29: For Lease | AP29: Single owner | AQ29: Jan 2013 (Ian): space totals 170,000 sq ft lettable. The amount of space that was originally available for lease was 73,162 sq ft and there is currently 51,419 sq ft available. Efficiency is approximately 87%. Jul 2012: James (OS) - CCB, as the tenant would take up portions of the building for its own use and now, 15/F up to 27/F (excluding 17/F-Refuge Floor and 18/F-Mechanical Floor) would be put up on market for leasing. Mar 2012 (Ian): Floor plates 8 – 11,000 sq ft Gross; Quoted efficiency a little over 80%; Lift lobby located on 3rd floor; Banking Hall on the ground floor similar to Bank of China Building; 37 Car Parking Spaces; OP expected by end of August 2012; Connection to the MTR will open 2013 Q1 Sep2011: CCB have leased half of the building and have the option to lease rest of the building. Contact: Julius Lau (2741 0391) | AR29: CC040
B30: One Pacific Centre (414 Kwun Tong Road) | C30: 414 Kwun Tong Road | E30: Kwun Tong | F30: =VLOOKUP(Table1[[#This Row],[CBRE sub-markets]],Reference!$A$2:$B$31,2,FALSE) -> Kowloon East | G30: =VLOOKUP(Table1[[#This Row],[CBRE sub-markets]],Reference!$A$2:$D$31,3,FALSE) -> 7 | H30: =VLOOKUP(Table1[[#This Row],[CBRE sub-markets]],Reference!$A$2:$D$31,4,FALSE) -> Kowloon | I30: 2012 | J30: 4 | K30: =IF(ISNUMBER(Table1[[#This Row],[Qtr]]),CONCATENATE(Table1[[#This Row],[Year]]," Q",Table1[[#This Row],[Qtr]]),CONCATENATE(Table1[[#This Row],[Year]],Table1[[#This Row],[Qtr]])) -> 2012 Q4 | L30: B Office | M30: Completed | N30: 1 | O30: 31+4 basement | Q30: =+W30/31 -> 7740.0105 | R30: =Q30*(Y30/W30) -> 5243.0402 | S30: =IF(AND(ISNUMBER(R30),R30>=15000),"Yes",IF(R30="","Unknown","No")) -> No | V30: 22291 | W30: 239940.32 | X30: 15099.8 | Y30: 162534.25 | AC30: =IF(Table1[[#This Row],[For Sale or For Lease?]]="For Lease",Table1[[#This Row],[Office UFA (Net) (sf)]]-Table1[[#This Row],[Pre-leased space (Usable FA) (sf)]]-Table1[[#This Row],[Pre-sold (Usable FA) (sf)]]-Table1[[#This Row],[Self-use space (Usable FA) (sf)]],0) -> 162534.25 | AD30: =IF(Table1[[#This Row],[For Sale or For Lease?]]="For Sale",Table1[[#This Row],[Office UFA (Net) (sf)]]-Table1[[#This Row],[Pre-leased space (Usable FA) (sf)]]-Table1[[#This Row],[Pre-sold (Usable FA) (sf)]]-Table1[[#This Row],[Self-use space (Usable FA) (sf)]],0) -> 0 | AE30: =IF(Table1[[#This Row],[For Sale or For Lease?]]="Uncertain",Table1[[#This Row],[Office UFA (Net) (sf)]]-Table1[[#This Row],[Pre-leased space (Usable FA) (sf)]]-Table1[[#This Row],[Pre-sold (Usable FA) (sf)]]-Table1[[#This Row],[Self-use space (Usable FA) (sf)]],0) -> 0 | AF30: =1-SUM(Table1[[#This Row],[Space available for lease (Usable FA) (sf)]:[Space available uncertain of use (Usable FA) (sf)]])/Table1[[#This Row],[Office UFA (Net) (sf)]] -> 0 | AG30: Commercial | AH30: OP Issued | AI30: BD Monthly Digest | AJ30: 41214 | AK30: 41326 | AL30: Redevelopment | AM30: Hong Kong Pacific Investments Limited | AN30: Private Sector | AO30: For Lease | AP30: Single owner | AQ30: Dec 2012 (MP): OP issued Dec2011 (JD) OP expected March 2012. Oct 2011 (JD): mtg with LL completion expected CNY 2012. Tenant mix will be similar to Crocodile Centre, ie. semi-retail; next to MC5 Apr 2011 (Mark Palmer): Likely to be majority retail like Crocodile Centre. Yet to be confirmed, most likely lease, possible sale. | AR30: NS029
A31: 九龍貿易中心二期 | B31: Kowloon Commerce Centre Tower B | C31: 51-53 Kwai Cheong Road & 12-120 Tai Lin Pai Road | D31: KCTL 215 | E31: Kwai Chung & Tsuen Wan | F31: =VLOOKUP(Table1[[#This Row],[CBRE sub-markets]],Reference!$A$2:$B$31,2,FALSE) -> New Territories | G31: =VLOOKUP(Table1[[#This Row],[CBRE sub-markets]],Reference!$A$2:$D$31,3,FALSE) -> 9 | H31: =VLOOKUP(Table1[[#This Row],[CBRE sub-markets]],Reference!$A$2:$D$31,4,FALSE) -> New Territories | I31: 2012 | J31: 4 | K31: =IF(ISNUMBER(Table1[[#This Row],[Qtr]]),CONCATENATE(Table1[[#This Row],[Year]]," Q",Table1[[#This Row],[Qtr]]),CONCATENATE(Table1[[#This Row],[Year]],Table1[[#This Row],[Qtr]])) -> 2012 Q4 | L31: A Office | M31: Completed | N31: 1 | O31: 25+7 podium | Q31: 26000 | R31: =Q31*(Y31/W31) -> 19500 | S31: =IF(AND(ISNUMBER(R31),R31>=15000),"Yes",IF(R31="","Unknown","No")) -> Yes | V31: =W31/10.764 -> 54816.146 | W31: 590041 | X31: =Y31/10.764 -> 41112.11 | Y31: 442530.75 | AA31: =(W31-208000)*Y31/W31 -> 286530.75 | AC31: =IF(Table1[[#This Row],[For Sale or For Lease?]]="For Lease",Table1[[#This Row],[Office UFA (Net) (sf)]]-Table1[[#This Row],[Pre-leased space (Usable FA) (sf)]]-Table1[[#This Row],[Pre-sold (Usable FA) (sf)]]-Table1[[#This Row],[Self-use space (Usable FA) (sf)]],0) -> 0 | AD31: =IF(Table1[[#This Row],[For Sale or For Lease?]]="For Sale",Table1[[#This Row],[Office UFA (Net) (sf)]]-Table1[[#This Row],[Pre-leased space (Usable FA) (sf)]]-Table1[[#This Row],[Pre-sold (Usable FA) (sf)]]-Table1[[#This Row],[Self-use space (Usable FA) (sf)]],0) -> 156000 | AE31: =IF(Table1[[#This Row],[For Sale or For Lease?]]="Uncertain",Table1[[#This Row],[Office UFA (Net) (sf)]]-Table1[[#This Row],[Pre-leased space (Usable FA) (sf)]]-Table1[[#This Row],[Pre-sold (Usable FA) (sf)]]-Table1[[#This Row],[Self-use space (Usable FA) (sf)]],0) -> 0 | AF31: =1-SUM(Table1[[#This Row],[Space available for lease (Usable FA) (sf)]:[Space available uncertain of use (Usable FA) (sf)]])/Table1[[#This Row],[Office UFA (Net) (sf)]] -> 0.64748212 | AG31: Commercial | AH31: OP Issued | AI31: BD Monthly Digest | AJ31: 41244 | AK31: 41326 | AL31: Site | AM31: Sun Hung Kai Properties | AN31: Private Sector | AO31: For Sale | AP31: Strata-title | AQ31: SHKP: http://202.85.145.73/en/scripts/about/about_upcoming40.php | AR31: KF008
B32: 8 Queen's Road East | C32: 8 Queen's Road East | E32: Wan Chai | F32: =VLOOKUP(Table1[[#This Row],[CBRE sub-markets]],Reference!$A$2:$B$31,2,FALSE) -> Wan Chai & Causeway Bay | G32: =VLOOKUP(Table1[[#This Row],[CBRE sub-markets]],Reference!$A$2:$D$31,3,FALSE) -> 3 | H32: =VLOOKUP(Table1[[#This Row],[CBRE sub-markets]],Reference!$A$2:$D$31,4,FALSE) -> Hong Kong Island | I32: 2013 | J32: 2 | K32: =IF(ISNUMBER(Table1[[#This Row],[Qtr]]),CONCATENATE(Table1[[#This Row],[Year]]," Q",Table1[[#This Row],[Qtr]]),CONCATENATE(Table1[[#This Row],[Year]],Table1[[#This Row],[Qtr]])) -> 2013 Q2 | L32: B Office | M32: Completed | N32: 1 | O32: 18 | Q32: 3930 | R32: =Q32*(Y32/W32) -> 3340.5 | S32: =IF(AND(ISNUMBER(R32),R32>=15000),"Yes",IF(R32="","Unknown","No")) -> No | V32: =W32/10.764 -> 5711.1669 | W32: 61475 | X32: =Y32/10.764 -> 4854.4918 | Y32: =W32*0.85 -> 52253.75 | Z32: =Y32 -> 52253.75 | AC32: =IF(Table1[[#This Row],[For Sale or For Lease?]]="For Lease",Table1[[#This Row],[Office UFA (Net) (sf)]]-Table1[[#This Row],[Pre-leased space (Usable FA) (sf)]]-Table1[[#This Row],[Pre-sold (Usable FA) (sf)]]-Table1[[#This Row],[Self-use space (Usable FA) (sf)]],0) -> 0 | AD32: =IF(Table1[[#This Row],[For Sale or For Lease?]]="For Sale",Table1[[#This Row],[Office UFA (Net) (sf)]]-Table1[[#This Row],[Pre-leased space (Usable FA) (sf)]]-Table1[[#This Row],[Pre-sold (Usable FA) (sf)]]-Table1[[#This Row],[Self-use space (Usable FA) (sf)]],0) -> 0 | AE32: =IF(Table1[[#This Row],[For Sale or For Lease?]]="Uncertain",Table1[[#This Row],[Office UFA (Net) (sf)]]-Table1[[#This Row],[Pre-leased space (Usable FA) (sf)]]-Table1[[#This Row],[Pre-sold (Usable FA) (sf)]]-Table1[[#This Row],[Self-use space (Usable FA) (sf)]],0) -> 0 | AF32: =1-SUM(Table1[[#This Row],[Space available for lease (Usable FA) (sf)]:[Space available uncertain of use (Usable FA) (sf)]])/Table1[[#This Row],[Office UFA (Net) (sf)]] -> 1 | AG32: Commercial | AH32: N/A | AI32: Swire Properties | AK32: 40562 | AL32: Refurbishment | AM32: Swire Properties | AN32: Private Sector | AO32: For Lease | AP32: Single owner | AQ32: May 2012 (Ian): "the Generali deal to take the whole of 8QRE is complete. Rental HK$50 per sf effective, long lease term (apologies do not know exact). C&W advised Generali. The two other parties who were interested have now turned their attention to 28HR. " Feb 2012 (James): "8QRC is delayed and likely to be completed until Jan 2013" Aug 2011 (Cynthia): Major refurb due for completion in Q3 2012. Building rename to 8 Queens Road East. | AR32: NS032 | AV32: MULTIPOLYGON (((114.168127385 22.277488366,114.16796888 22.277589421,114.168056425 22.2776996280001,114.168281618 22.2776808430001,114.168127385 22.277488366)))
B33: 38 Heung Yip Road (20 Wong Chuk Hang Road) | C33: 38 Heung Yip Road | E33: Wong Chuk Hang | F33: =VLOOKUP(Table1[[#This Row],[CBRE sub-markets]],Reference!$A$2:$B$31,2,FALSE) -> Wong Chuk Hang | G33: =VLOOKUP(Table1[[#This Row],[CBRE sub-markets]],Reference!$A$2:$D$31,3,FALSE) -> 5 | H33: =VLOOKUP(Table1[[#This Row],[CBRE sub-markets]],Reference!$A$2:$D$31,4,FALSE) -> Hong Kong Island | I33: 2013 | J33: 2 | K33: =IF(ISNUMBER(Table1[[#This Row],[Qtr]]),CONCATENATE(Table1[[#This Row],[Year]]," Q",Table1[[#This Row],[Qtr]]),CONCATENATE(Table1[[#This Row],[Year]],Table1[[#This Row],[Qtr]])) -> 2013 Q2 | L33: A Office | M33: Completed | N33: 1 | O33: 29+1 basement | Q33: 6000 | R33: =Q33*0.75 -> 4500 | S33: =IF(AND(ISNUMBER(R33),R33>=15000),"Yes",IF(R33="","Unknown","No")) -> No | V33: =Table1[[#This Row],[Office GFA (sf)]]/10.7639 -> 15250.978 | W33: 164160 | X33: =Table1[[#This Row],[Office UFA (Net) (sf)]]/10.7639 -> 12810.821 | Y33: 137894.4 | AC33: =IF(Table1[[#This Row],[For Sale or For Lease?]]="For Lease",Table1[[#This Row],[Office UFA (Net) (sf)]]-Table1[[#This Row],[Pre-leased space (Usable FA) (sf)]]-Table1[[#This Row],[Pre-sold (Usable FA) (sf)]]-Table1[[#This Row],[Self-use space (Usable FA) (sf)]],0) -> 0 | AD33: =IF(Table1[[#This Row],[For Sale or For Lease?]]="For Sale",Table1[[#This Row],[Office UFA (Net) (sf)]]-Table1[[#This Row],[Pre-leased space (Usable FA) (sf)]]-Table1[[#This Row],[Pre-sold (Usable FA) (sf)]]-Table1[[#This Row],[Self-use space (Usable FA) (sf)]],0) -> 137894.4 | AE33: =IF(Table1[[#This Row],[For Sale or For Lease?]]="Uncertain",Table1[[#This Row],[Office UFA (Net) (sf)]]-Table1[[#This Row],[Pre-leased space (Usable FA) (sf)]]-Table1[[#This Row],[Pre-sold (Usable FA) (sf)]]-Table1[[#This Row],[Self-use space (Usable FA) (sf)]],0) -> 0 | AF33: =1-SUM(Table1[[#This Row],[Space available for lease (Usable FA) (sf)]:[Space available uncertain of use (Usable FA) (sf)]])/Table1[[#This Row],[Office UFA (Net) (sf)]] -> 0 | AG33: Commercial | AH33: OP Issued | AI33: BD Monthly Digest | AJ33: 41395 | AK33: 41540 | AL33: Redevelopment | AM33: Casey Co Ltd (Cheung Kong?) | AN33: Private Sector | AO33: For Sale | AP33: Strata-title | AQ33: Sep2011 (Cynthia): After meeting Ken Ko (general manager) at Casey Co Ltd :- • Building is for lease (no intention to stratify / sell) • Currently at the stage of building the podium, expected completion is Q1/Q2 2013 • Window wall building, 30 storeys above ground in total (4 levels of 70 carpark spaces spread on ground and 3 basement levels) • All office, no retail. • 2.7m ceiling height clear • 6,000 sq ft gross floor plate • Casey will move their headquarter in Sheung Wan to take up 3 levels in this new building on Heung Yip Rd. • Their target tenants are international companies’ back office, eg: Morgan Stanley’s back office in Island East. • Current rental expectations around $15-18 psf (as per existing Southmark building) Sep 2011 (Cynthia) & Marcus (OS): currently rebuilding on low zone, TBC Q4 2012 - Q1 2013. Roy (Aug2011): construction began last month | AR33: WCH001
B34: 49 King Yip Street | C34: 49 King Yip Street | E34: Kwun Tong | F34: =VLOOKUP(Table1[[#This Row],[CBRE sub-markets]],Reference!$A$2:$B$31,2,FALSE) -> Kowloon East | G34: =VLOOKUP(Table1[[#This Row],[CBRE sub-markets]],Reference!$A$2:$D$31,3,FALSE) -> 7 | H34: =VLOOKUP(Table1[[#This Row],[CBRE sub-markets]],Reference!$A$2:$D$31,4,FALSE) -> Kowloon | I34: 2013 | J34: 2 | K34: =IF(ISNUMBER(Table1[[#This Row],[Qtr]]),CONCATENATE(Table1[[#This Row],[Year]]," Q",Table1[[#This Row],[Qtr]]),CONCATENATE(Table1[[#This Row],[Year]],Table1[[#This Row],[Qtr]])) -> 2013 Q2 | L34: B Office | M34: Completed | N34: 1 | O34: 24 | Q34: 6309 | R34: =Q34*(Y34/W34) -> 3877.3104 | S34: =IF(AND(ISNUMBER(R34),R34>=15000),"Yes",IF(R34="","Unknown","No")) -> No | V34: =W34/10.764 -> 13942.865 | W34: =(6309*23)+4974 -> 150081 | X34: =Y34/10.764 -> 8568.8406 | Y34: =(3874*23)+3133 -> 92235 | AC34: =IF(Table1[[#This Row],[For Sale or For Lease?]]="For Lease",Table1[[#This Row],[Office UFA (Net) (sf)]]-Table1[[#This Row],[Pre-leased space (Usable FA) (sf)]]-Table1[[#This Row],[Pre-sold (Usable FA) (sf)]]-Table1[[#This Row],[Self-use space (Usable FA) (sf)]],0) -> 0 | AD34: =IF(Table1[[#This Row],[For Sale or For Lease?]]="For Sale",Table1[[#This Row],[Office UFA (Net) (sf)]]-Table1[[#This Row],[Pre-leased space (Usable FA) (sf)]]-Table1[[#This Row],[Pre-sold (Usable FA) (sf)]]-Table1[[#This Row],[Self-use space (Usable FA) (sf)]],0) -> 92235 | AE34: =IF(Table1[[#This Row],[For Sale or For Lease?]]="Uncertain",Table1[[#This Row],[Office UFA (Net) (sf)]]-Table1[[#This Row],[Pre-leased space (Usable FA) (sf)]]-Table1[[#This Row],[Pre-sold (Usable FA) (sf)]]-Table1[[#This Row],[Self-use space (Usable FA) (sf)]],0) -> 0 | AF34: =1-SUM(Table1[[#This Row],[Space available for lease (Usable FA) (sf)]:[Space available uncertain of use (Usable FA) (sf)]])/Table1[[#This Row],[Office UFA (Net) (sf)]] -> 0 | AG34: Commercial | AH34: OP Issued | AI34: BD Monthly Digest | AJ34: 41365 | AK34: 41432 | AM34: Sun Hung Kai Properties | AN34: Private Sector | AO34: For Sale | AP34: Strata-title | AQ34: Sep 2011: Sam (OS) - building rumoured to have sold to a bank (en-bloc), should know more in 1-2 months time. Between Billion's 24 Hing Yip Street and Manulife Financial Centre | AR34: NS039 | AV34: MULTIPOLYGON (((114.225297969 22.308142904,114.225311827 22.3081273720001,114.225324176 22.3081369110001,114.225403248 22.3080482810001,114.225341636 22.3079998710001,114.225351544 22.307988743,114.225206101 22.307876845,114.225093137 22.307990456,114.225222997 22.30809059,114.22520298 22.3081130620001,114.225287327 22.308178215,114.22531032 22.308152444,114.225297969 22.308142904)))
A35: 廣新行貨倉有限公司第三倉 (ext.) | B35: 6 Wang Kwong Road | C35: 6 Wang Kwong Road | E35: Kowloon Bay | F35: =VLOOKUP(Table1[[#This Row],[CBRE sub-markets]],Reference!$A$2:$B$31,2,FALSE) -> Kowloon East | G35: =VLOOKUP(Table1[[#This Row],[CBRE sub-markets]],Reference!$A$2:$D$31,3,FALSE) -> 7 | H35: =VLOOKUP(Table1[[#This Row],[CBRE sub-markets]],Reference!$A$2:$D$31,4,FALSE) -> Kowloon | I35: 2013 | J35: 3 | K35: =IF(ISNUMBER(Table1[[#This Row],[Qtr]]),CONCATENATE(Table1[[#This Row],[Year]]," Q",Table1[[#This Row],[Qtr]]),CONCATENATE(Table1[[#This Row],[Year]],Table1[[#This Row],[Qtr]])) -> 2013 Q3 | L35: A Office | M35: Completed | N35: 1 | O35: 33 | Q35: =+W35/O35 -> 10837.697 | R35: =Q35*(Y35/W35) -> 8128.2727 | S35: =IF(AND(ISNUMBER(R35),R35>=15000),"Yes",IF(R35="","Unknown","No")) -> No | V35: =Table1[[#This Row],[Office GFA (sf)]]/10.7639 -> 33226.247 | W35: 357644 | X35: =Table1[[#This Row],[Office UFA (Net) (sf)]]/10.7639 -> 24919.685 | Y35: 268233 | AC35: =IF(Table1[[#This Row],[For Sale or For Lease?]]="For Lease",Table1[[#This Row],[Office UFA (Net) (sf)]]-Table1[[#This Row],[Pre-leased space (Usable FA) (sf)]]-Table1[[#This Row],[Pre-sold (Usable FA) (sf)]]-Table1[[#This Row],[Self-use space (Usable FA) (sf)]],0) -> 0 | AD35: =IF(Table1[[#This Row],[For Sale or For Lease?]]="For Sale",Table1[[#This Row],[Office UFA (Net) (sf)]]-Table1[[#This Row],[Pre-leased space (Usable FA) (sf)]]-Table1[[#This Row],[Pre-sold (Usable FA) (sf)]]-Table1[[#This Row],[Self-use space (Usable FA) (sf)]],0) -> 268233 | AE35: =IF(Table1[[#This Row],[For Sale or For Lease?]]="Uncertain",Table1[[#This Row],[Office UFA (Net) (sf)]]-Table1[[#This Row],[Pre-leased space (Usable FA) (sf)]]-Table1[[#This Row],[Pre-sold (Usable FA) (sf)]]-Table1[[#This Row],[Self-use space (Usable FA) (sf)]],0) -> 0 | AF35: =1-SUM(Table1[[#This Row],[Space available for lease (Usable FA) (sf)]:[Space available uncertain of use (Usable FA) (sf)]])/Table1[[#This Row],[Office UFA (Net) (sf)]] -> 0 | AG35: Commercial | AH35: OP Issued | AI35: BD Monthly Digest | AJ35: 41518 | AK35: 41518 | AL35: Redevelopment | AM35: Billion Development | AN35: Private Sector | AO35: For Sale | AP35: Strata-title | AQ35: Jun 2013: scaffolding coming off, should get OP in Oct. Jan 2013: Lands Department offered land premium of $5,000. Billion will likely appeal. Dec 2012 (Sing Tao): The developer said it was not in talks with the government on the land premium of the office tower project on No 6 Wang Kwong Road, Kowloon Bay. The psf price might exceed HK$3,000. Nov 2012 (Rocky): Spoken with Billion last week, they still haven’t agree the final amount of land premium with the government therefore no indicated price available yet. However, they will not apply for pre-sale consent on this property. Thus, this property will not be ready for sale before OP. Their expected OP is in Q3 2013. Aug 2012 (JD): half way up already Feb 2012: Foundation done, but Henderson wants to sell adjacent building first Sep 2011: Sam (OS) - building demolished. / JD (OS): land premium only HK$2,200 psf, so they will most likely accept. Approximately 300,000 sq ft on track for Q3 2013. Apple (25/8/09): 億京斥2.9億購入九龍灣工廈/ 未補地價/ Est PR=15x. Sam Li (7 Jun 2011):Demolition of old building in progress Opposite Billion Centre (1 Wang Kwong Road) | AR35: KK022
B36: One Sheung Yuet Road | C36: 1, 1A & 1B Sheung Yuet Road | E36: Kowloon Bay | F36: =VLOOKUP(Table1[[#This Row],[CBRE sub-markets]],Reference!$A$2:$B$31,2,FALSE) -> Kowloon East | G36: =VLOOKUP(Table1[[#This Row],[CBRE sub-markets]],Reference!$A$2:$D$31,3,FALSE) -> 7 | H36: =VLOOKUP(Table1[[#This Row],[CBRE sub-markets]],Reference!$A$2:$D$31,4,FALSE) -> Kowloon | I36: 2013 | J36: 3 | K36: =IF(ISNUMBER(Table1[[#This Row],[Qtr]]),CONCATENATE(Table1[[#This Row],[Year]]," Q",Table1[[#This Row],[Qtr]]),CONCATENATE(Table1[[#This Row],[Year]],Table1[[#This Row],[Qtr]])) -> 2013 Q3 | L36: A Office | M36: Taken out | N36: 1 | O36: 33 | Q36: =W36/O36 -> 8017.5165 | R36: =Y36/O36 -> 6167.4784 | S36: =IF(AND(ISNUMBER(R36),R36>=15000),"Yes",IF(R36="","Unknown","No")) -> No | V36: 24579.9 | W36: =V36*10.764 -> 264578.04 | X36: 18908.1 | Y36: =X36*10.764 -> 203526.79 | AC36: =IF(Table1[[#This Row],[For Sale or For Lease?]]="For Lease",Table1[[#This Row],[Office UFA (Net) (sf)]]-Table1[[#This Row],[Pre-leased space (Usable FA) (sf)]]-Table1[[#This Row],[Pre-sold (Usable FA) (sf)]]-Table1[[#This Row],[Self-use space (Usable FA) (sf)]],0) -> 0 | AD36: =IF(Table1[[#This Row],[For Sale or For Lease?]]="For Sale",Table1[[#This Row],[Office UFA (Net) (sf)]]-Table1[[#This Row],[Pre-leased space (Usable FA) (sf)]]-Table1[[#This Row],[Pre-sold (Usable FA) (sf)]]-Table1[[#This Row],[Self-use space (Usable FA) (sf)]],0) -> 203526.79 | AE36: =IF(Table1[[#This Row],[For Sale or For Lease?]]="Uncertain",Table1[[#This Row],[Office UFA (Net) (sf)]]-Table1[[#This Row],[Pre-leased space (Usable FA) (sf)]]-Table1[[#This Row],[Pre-sold (Usable FA) (sf)]]-Table1[[#This Row],[Self-use space (Usable FA) (sf)]],0) -> 0 | AF36: =1-SUM(Table1[[#This Row],[Space available for lease (Usable FA) (sf)]:[Space available uncertain of use (Usable FA) (sf)]])/Table1[[#This Row],[Office UFA (Net) (sf)]] -> 0 | AG36: Commercial | AH36: OP Issued | AI36: BD Monthly Digest | AJ36: 41518 | AK36: 41894 | AL36: Redevelopment | AM36: Billion Development | AN36: Private Sector | AO36: For Sale | AP36: Strata-title | AR36: NS037
A37: 創紀之城7 | B37: 181 Hoi Bun Road | C37: 181 Hoi Bun Road | E37: Kwun Tong | F37: =VLOOKUP(Table1[[#This Row],[CBRE sub-markets]],Reference!$A$2:$B$31,2,FALSE) -> Kowloon East | G37: =VLOOKUP(Table1[[#This Row],[CBRE sub-markets]],Reference!$A$2:$D$31,3,FALSE) -> 7 | H37: =VLOOKUP(Table1[[#This Row],[CBRE sub-markets]],Reference!$A$2:$D$31,4,FALSE) -> Kowloon | I37: 2013 | J37: 3 | K37: =IF(ISNUMBER(Table1[[#This Row],[Qtr]]),CONCATENATE(Table1[[#This Row],[Year]]," Q",Table1[[#This Row],[Qtr]]),CONCATENATE(Table1[[#This Row],[Year]],Table1[[#This Row],[Qtr]])) -> 2013 Q3 | L37: A Office | M37: Completed | N37: 1 | O37: 25+1 basement | Q37: 18000 | R37: =Q37*(Y37/W37) -> 13140 | S37: =IF(AND(ISNUMBER(R37),R37>=15000),"Yes",IF(R37="","Unknown","No")) -> No | V37: =Table1[[#This Row],[Office GFA (sf)]]/10.7639 -> 34293.983 | W37: 369137 | X37: =Table1[[#This Row],[Office UFA (Net) (sf)]]/10.7639 -> 25034.607 | Y37: 269470.01 | AC37: =IF(Table1[[#This Row],[For Sale or For Lease?]]="For Lease",Table1[[#This Row],[Office UFA (Net) (sf)]]-Table1[[#This Row],[Pre-leased space (Usable FA) (sf)]]-Table1[[#This Row],[Pre-sold (Usable FA) (sf)]]-Table1[[#This Row],[Self-use space (Usable FA) (sf)]],0) -> 0 | AD37: =IF(Table1[[#This Row],[For Sale or For Lease?]]="For Sale",Table1[[#This Row],[Office UFA (Net) (sf)]]-Table1[[#This Row],[Pre-leased space (Usable FA) (sf)]]-Table1[[#This Row],[Pre-sold (Usable FA) (sf)]]-Table1[[#This Row],[Self-use space (Usable FA) (sf)]],0) -> 269470.01 | AE37: =IF(Table1[[#This Row],[For Sale or For Lease?]]="Uncertain",Table1[[#This Row],[Office UFA (Net) (sf)]]-Table1[[#This Row],[Pre-leased space (Usable FA) (sf)]]-Table1[[#This Row],[Pre-sold (Usable FA) (sf)]]-Table1[[#This Row],[Self-use space (Usable FA) (sf)]],0) -> 0 | AF37: =1-SUM(Table1[[#This Row],[Space available for lease (Usable FA) (sf)]:[Space available uncertain of use (Usable FA) (sf)]])/Table1[[#This Row],[Office UFA (Net) (sf)]] -> 0 | AG37: Commercial | AH37: OP Issued | AI37: BD Monthly Digest | AJ37: 41518 | AK37: 41730 | AL37: Redevelopment & Site | AM37: Sun Hung Kai Properties (64.3%)/ Wong's International | AN37: Private Sector | AO37: For Sale | AP37: Strata-title | AQ37: Mar 2013: alreadt fitting curtain wall Jun 2012: Sam & JD (OS) - SHK will now entertain en-bloc purchase; now up to 12th floor; Phase 1 development will be slightly bigger than C-Bon, both site GFA and typical floor area. At this stage, assume a typical floor area of 18,700 sq ft GROSS which is 10% bigger than C-Bon. For site GFA assume 340,000 sq ft GROSS. Not sure about the ownership structure of the development but likely this will be JV between SHK and Wongs. Feb 2012: Construction started Sep 2011: Sam (OS) - need to check which part SHKP & Wong's are responsible for. Now building is standing on Wong's part, while bare site is on SHKP's part. Right now, no information could be released from SHKP. Originally owned by Jebsen Properties but was sold to a local industrialist at 127.8 million or 413 psf a.v.. The buyer is considering to redevelop the site into a commercial bldg to serve as the headquarter of his production business (Early 2010) Land Premium: $270.4M; (2007) SHKP acquired the Ind Bldg for $345M | AR37: KK037
A38: 億利達工業大廈 (existing) | B38: Rykaden Capital Tower (135 Hoi Bun Road) | C38: 135-137 Hoi Bun Road | E38: Kwun Tong | F38: =VLOOKUP(Table1[[#This Row],[CBRE sub-markets]],Reference!$A$2:$B$31,2,FALSE) -> Kowloon East | G38: =VLOOKUP(Table1[[#This Row],[CBRE sub-markets]],Reference!$A$2:$D$31,3,FALSE) -> 7 | H38: =VLOOKUP(Table1[[#This Row],[CBRE sub-markets]],Reference!$A$2:$D$31,4,FALSE) -> Kowloon | I38: 2013 | J38: 3 | K38: =IF(ISNUMBER(Table1[[#This Row],[Qtr]]),CONCATENATE(Table1[[#This Row],[Year]]," Q",Table1[[#This Row],[Qtr]]),CONCATENATE(Table1[[#This Row],[Year]],Table1[[#This Row],[Qtr]])) -> 2013 Q3 | L38: A Office | M38: Completed | N38: 1 | O38: 25 | Q38: =+W38/O38 -> 10114.08 | R38: =Q38*(Y38/W38) -> 7079.856 | S38: =IF(AND(ISNUMBER(R38),R38>=15000),"Yes",IF(R38="","Unknown","No")) -> No | V38: =Table1[[#This Row],[Office GFA (sf)]]/10.7639 -> 23490.742 | W38: 252852 | X38: =Table1[[#This Row],[Office UFA (Net) (sf)]]/10.7639 -> 16443.52 | Y38: 176996.4 | AC38: =IF(Table1[[#This Row],[For Sale or For Lease?]]="For Lease",Table1[[#This Row],[Office UFA (Net) (sf)]]-Table1[[#This Row],[Pre-leased space (Usable FA) (sf)]]-Table1[[#This Row],[Pre-sold (Usable FA) (sf)]]-Table1[[#This Row],[Self-use space (Usable FA) (sf)]],0) -> 0 | AD38: =IF(Table1[[#This Row],[For Sale or For Lease?]]="For Sale",Table1[[#This Row],[Office UFA (Net) (sf)]]-Table1[[#This Row],[Pre-leased space (Usable FA) (sf)]]-Table1[[#This Row],[Pre-sold (Usable FA) (sf)]]-Table1[[#This Row],[Self-use space (Usable FA) (sf)]],0) -> 176996.4 | AE38: =IF(Table1[[#This Row],[For Sale or For Lease?]]="Uncertain",Table1[[#This Row],[Office UFA (Net) (sf)]]-Table1[[#This Row],[Pre-leased space (Usable FA) (sf)]]-Table1[[#This Row],[Pre-sold (Usable FA) (sf)]]-Table1[[#This Row],[Self-use space (Usable FA) (sf)]],0) -> 0 | AF38: =1-SUM(Table1[[#This Row],[Space available for lease (Usable FA) (sf)]:[Space available uncertain of use (Usable FA) (sf)]])/Table1[[#This Row],[Office UFA (Net) (sf)]] -> 0 | AG38: Commercial | AH38: OP Issued | AI38: BD Monthly Digest | AJ38: 41518 | AK38: 41530 | AL38: Redevelopment | AM38: Sundart international Holdings | AN38: Private Sector | AO38: For Sale | AP38: Strata-title | AQ38: Oct 2012: Rocky - The landlord is still getting the presale consent from the Government. It is expected to be granted by end of this month. The initial asking for low and mid zone is ranging from HK$7,000psfg to HK$8,000psfg. Oct 2011: Rocky (OS) - Sundart paid HK$386.5M (HK$1,867psf for 207,000sf) land premium to change it to office use. Sep 2011: Sam (OS) - building demolished 1-2 months ago, now a bare site May 2011: Demolition issued | AR38: KK036
B39: Exchange Square - The Forum | C39: 8 Connaught Place | E39: Central | F39: =VLOOKUP(Table1[[#This Row],[CBRE sub-markets]],Reference!$A$2:$B$31,2,FALSE) -> Central | G39: =VLOOKUP(Table1[[#This Row],[CBRE sub-markets]],Reference!$A$2:$D$31,3,FALSE) -> 1 | H39: =VLOOKUP(Table1[[#This Row],[CBRE sub-markets]],Reference!$A$2:$D$31,4,FALSE) -> Hong Kong Island | I39: 2013 | J39: 4 | K39: =IF(ISNUMBER(Table1[[#This Row],[Qtr]]),CONCATENATE(Table1[[#This Row],[Year]]," Q",Table1[[#This Row],[Qtr]]),CONCATENATE(Table1[[#This Row],[Year]],Table1[[#This Row],[Qtr]])) -> 2013 Q4 | L39: A Office | M39: Completed | N39: 1 | O39: 5 | Q39: 10000 | R39: =Q39*(Y39/W39) -> 10000 | S39: =IF(AND(ISNUMBER(R39),R39>=15000),"Yes",IF(R39="","Unknown","No")) -> No | V39: =Table1[[#This Row],[Office GFA (sf)]]/10.7639 -> 4645.1565 | W39: 50000 | X39: =Table1[[#This Row],[Office UFA (Net) (sf)]]/10.7639 -> 4645.1565 | Y39: 50000 | Z39: =Y39 -> 50000 | AC39: =IF(Table1[[#This Row],[For Sale or For Lease?]]="For Lease",Table1[[#This Row],[Office UFA (Net) (sf)]]-Table1[[#This Row],[Pre-leased space (Usable FA) (sf)]]-Table1[[#This Row],[Pre-sold (Usable FA) (sf)]]-Table1[[#This Row],[Self-use space (Usable FA) (sf)]],0) -> 0 | AD39: =IF(Table1[[#This Row],[For Sale or For Lease?]]="For Sale",Table1[[#This Row],[Office UFA (Net) (sf)]]-Table1[[#This Row],[Pre-leased space (Usable FA) (sf)]]-Table1[[#This Row],[Pre-sold (Usable FA) (sf)]]-Table1[[#This Row],[Self-use space (Usable FA) (sf)]],0) -> 0 | AE39: =IF(Table1[[#This Row],[For Sale or For Lease?]]="Uncertain",Table1[[#This Row],[Office UFA (Net) (sf)]]-Table1[[#This Row],[Pre-leased space (Usable FA) (sf)]]-Table1[[#This Row],[Pre-sold (Usable FA) (sf)]]-Table1[[#This Row],[Self-use space (Usable FA) (sf)]],0) -> 0 | AF39: =1-SUM(Table1[[#This Row],[Space available for lease (Usable FA) (sf)]:[Space available uncertain of use (Usable FA) (sf)]])/Table1[[#This Row],[Office UFA (Net) (sf)]] -> 1 | AG39: Commercial | AH39: OP Issued | AI39: BD Monthly Digest | AJ39: 41609 | AK39: 41677 | AL39: Redevelopment | AM39: Hongkong Land | AN39: Private Sector | AO39: For Lease | AP39: Single owner | AQ39: Sep 2013: from HKLand website "The Forum commenced redevelopment in Dec 2011. The new Forum will be a 7-storey building, 5 of which are designed for office use. Inspired by crystal formations, the new Forum is designed to resemble a cut gemstone nestled within natural surroundings, and the plaza includes a landscaped roof garden, stepped terraces and fountains as well as sculptures by celebrated artists such as Henry Moore, Ju Ming and Dame Elisabeth Frink. The Forum redevelopment, including the plaza area, is scheduled for completion in early 2014." Feb2012: Demolition issued Jan2012: The entire building is pre-let to Standard Chartered, The lowest floor (1st) and the 2nd floor is planned for retail BANKING use and the 3rd, 4th and 5th floors for SCB’s Wealth Management business though this is not yet confirmed. The entire development is OFFICE use, not retail. Dec2012: “ Hongkong Land announced details of its plans for the HK$560 million (US$72 million) redevelopment of The Forum. It will be a 7-storey building, five of which are designed for office use. It will have a total GFA of some 48,000 sq. ft, approximately 15% larger than the current building. The redeveloped Forum is designed to achieve the highest possible environmental rating.” | AR39: CC042
B40: Global Trade Square | C40: 19-21 Wong Chuk Hang Road | E40: Wong Chuk Hang | F40: =VLOOKUP(Table1[[#This Row],[CBRE sub-markets]],Reference!$A$2:$B$31,2,FALSE) -> Wong Chuk Hang | G40: =VLOOKUP(Table1[[#This Row],[CBRE sub-markets]],Reference!$A$2:$D$31,3,FALSE) -> 5 | H40: =VLOOKUP(Table1[[#This Row],[CBRE sub-markets]],Reference!$A$2:$D$31,4,FALSE) -> Hong Kong Island | I40: 2013 | J40: 4 | K40: =IF(ISNUMBER(Table1[[#This Row],[Qtr]]),CONCATENATE(Table1[[#This Row],[Year]]," Q",Table1[[#This Row],[Qtr]]),CONCATENATE(Table1[[#This Row],[Year]],Table1[[#This Row],[Qtr]])) -> 2013 Q4 | L40: A Office | M40: Completed | N40: 1 | O40: 31 | Q40: 9700 | R40: =Q40*(Y40/W40) -> 7275 | S40: =IF(AND(ISNUMBER(R40),R40>=15000),"Yes",IF(R40="","Unknown","No")) -> No | V40: =Table1[[#This Row],[Office GFA (sf)]]/10.7639 -> 23915.031 | W40: 257419 | X40: =Table1[[#This Row],[Office UFA (Net) (sf)]]/10.7639 -> 17936.273 | Y40: 193064.25 | AC40: =IF(Table1[[#This Row],[For Sale or For Lease?]]="For Lease",Table1[[#This Row],[Office UFA (Net) (sf)]]-Table1[[#This Row],[Pre-leased space (Usable FA) (sf)]]-Table1[[#This Row],[Pre-sold (Usable FA) (sf)]]-Table1[[#This Row],[Self-use space (Usable FA) (sf)]],0) -> 0 | AD40: =IF(Table1[[#This Row],[For Sale or For Lease?]]="For Sale",Table1[[#This Row],[Office UFA (Net) (sf)]]-Table1[[#This Row],[Pre-leased space (Usable FA) (sf)]]-Table1[[#This Row],[Pre-sold (Usable FA) (sf)]]-Table1[[#This Row],[Self-use space (Usable FA) (sf)]],0) -> 193064.25 | AE40: =IF(Table1[[#This Row],[For Sale or For Lease?]]="Uncertain",Table1[[#This Row],[Office UFA (Net) (sf)]]-Table1[[#This Row],[Pre-leased space (Usable FA) (sf)]]-Table1[[#This Row],[Pre-sold (Usable FA) (sf)]]-Table1[[#This Row],[Self-use space (Usable FA) (sf)]],0) -> 0 | AF40: =1-SUM(Table1[[#This Row],[Space available for lease (Usable FA) (sf)]:[Space available uncertain of use (Usable FA) (sf)]])/Table1[[#This Row],[Office UFA (Net) (sf)]] -> 0 | AG40: Commercial | AH40: OP Issued | AI40: BD Monthly Digest | AJ40: 41609 | AK40: 41677 | AL40: Redevelopment | AM40: Henderson & Hip Hing Hong | AN40: Private Sector | AO40: For Sale | AP40: Strata-title | AQ40: Developer Contact: Steve Tse 2908 8380/ 2909 8543) Mar 2013: The pre-sale consent of the office project of Henderson will be issue soon with indicative price of $10,000 psf on strata-basis, but can also try en-bloc. Aug 2011 (Cynthia):met with Steve from henderson, he advised Q1 2014 completion. Approx 32 floors. Currently at the stage of getting design approvals. Aug 2011 - Marcus (OS): This is possibly for sale. HKET(16Dec2010): LandsD has annouced the land premium has paid by the developers of $100.18M, or $467 psf for lease modification from industrial to commercial use. The developers have submitted the plan as early as 2001 for developing a 24-storeys commercial bldgs with GFA 214.5k sf. | AR40: WCH002
B41: 33 Des Voeux Road Central | C41: 31-37 Des Voeux Road Central | E41: Central | F41: =VLOOKUP(Table1[[#This Row],[CBRE sub-markets]],Reference!$A$2:$B$31,2,FALSE) -> Central | G41: =VLOOKUP(Table1[[#This Row],[CBRE sub-markets]],Reference!$A$2:$D$31,3,FALSE) -> 1 | H41: =VLOOKUP(Table1[[#This Row],[CBRE sub-markets]],Reference!$A$2:$D$31,4,FALSE) -> Hong Kong Island | I41: 2014 | J41: 1 | K41: =IF(ISNUMBER(Table1[[#This Row],[Qtr]]),CONCATENATE(Table1[[#This Row],[Year]]," Q",Table1[[#This Row],[Qtr]]),CONCATENATE(Table1[[#This Row],[Year]],Table1[[#This Row],[Qtr]])) -> 2014 Q1 | L41: A Office | M41: Completed | N41: 1 | O41: 27 | Q41: =+W41/O41 -> 2731.7407 | R41: =Q41*(Y41/W41) -> 1912.2222 | S41: =IF(AND(ISNUMBER(R41),R41>=15000),"Yes",IF(R41="","Unknown","No")) -> No | V41: =W41/10.7639 -> 6852.2562 | W41: 73757 | X41: =Y41/10.7639 -> 4796.5886 | Y41: 51630 | AC41: =IF(Table1[[#This Row],[For Sale or For Lease?]]="For Lease",Table1[[#This Row],[Office UFA (Net) (sf)]]-Table1[[#This Row],[Pre-leased space (Usable FA) (sf)]]-Table1[[#This Row],[Pre-sold (Usable FA) (sf)]]-Table1[[#This Row],[Self-use space (Usable FA) (sf)]],0) -> 51630 | AD41: =IF(Table1[[#This Row],[For Sale or For Lease?]]="For Sale",Table1[[#This Row],[Office UFA (Net) (sf)]]-Table1[[#This Row],[Pre-leased space (Usable FA) (sf)]]-Table1[[#This Row],[Pre-sold (Usable FA) (sf)]]-Table1[[#This Row],[Self-use space (Usable FA) (sf)]],0) -> 0 | AE41: =IF(Table1[[#This Row],[For Sale or For Lease?]]="Uncertain",Table1[[#This Row],[Office UFA (Net) (sf)]]-Table1[[#This Row],[Pre-leased space (Usable FA) (sf)]]-Table1[[#This Row],[Pre-sold (Usable FA) (sf)]]-Table1[[#This Row],[Self-use space (Usable FA) (sf)]],0) -> 0 | AF41: =1-SUM(Table1[[#This Row],[Space available for lease (Usable FA) (sf)]:[Space available uncertain of use (Usable FA) (sf)]])/Table1[[#This Row],[Office UFA (Net) (sf)]] -> 0 | AG41: Commercial | AH41: OP Issued | AI41: BD Monthly Digest | AJ41: 41640 | AK41: 41718 | AL41: Redevelopment | AM41: The Bank of East Asia Ltd | AN41: Private Sector | AO41: For Lease | AP41: Single owner | AQ41: Jun 2013: JLL are sole leasing agent. Contact: Peter Hsiao 3608 6128 Mar 2013: Bank of East Asia could take 1 retail floor and 1 or 2 office floor, but not yet confirmed. Feb 2013 (Roy): superstructure seems to be done up to top level, the hoarding says completion for 2013. Jun 2012 (Ian): Clear site with work currently being undertaken on basement level. Will ask Gerry to see if he can find out more details through a contact he has. Sep 2011 (Cynthia): TAGRET TO BUILD CRM FOR FUTURE PITCHING. Cynthia called and left msg for Peter to call back. Sep 2011 (Cynthia): getting rebuilt on low zone, will be completed around Q1, 2013. 2006/8/16 Sing Tao Daily 東 亞 銀 行 所 持 的 中 環 中 國 聯 合 銀 行 大 廈 四 分 之 三 業 權 ， 消 息 人 士 指 本 周 末 、 下 周 初 將 正 式 揭 盅 ， 預 料 交 易 涉 資 約 五 億 元 ， 平 均 呎 價 約 七 千 八 百 元 ， 據 了 解 ， 發 展 商 莊 士 機 構 及 有 關 人 士 可 望 「 爆 冷 門 」 ， 壓 倒 現 持 有 該 廈 其 餘 四 分 之 一 業 權 的 「 奪 標 大 熱 」 陳 姓 資 深 投 資 者 及 有 關 人 士 。 本 報 昨 日 致 電 負 責 標 售 的 仲 量 聯 行 查 詢 ， 惟 截 稿 前 還 沒 有 聯 絡 上 。 不 過 ， 昨 日 市 場 傳 聞 ， 資 本 策 略 及 有 關 人 士 以 約 五 億 一 千 萬 元 購 入 該 物 業 。 http://www.singtao.com/archive/fullstory.asp?andor=or&year1=2006&month1=8&day1=16&year2=2006&month2=8&day2=16&category=all&id=20060816h09&keyword1=&keyword2= MingPao (26May2010): 東亞發言人表示, 公司是1995年購入該物業, 物業有16層, 樓面主要以自用為主, 部分樓面分租出去, 重建後主要都會作自用. HKET (26May2010): 2006年, 東亞銀行當時持有該廈四分三業權, 並推出標售, 當時市值約4.3億元, 吸引多個有 興趣買家入標. 但業主最終收回物業, 並統一業權. | AR41: CC041
A42: 億京中心 II | B42: Billion Plaza II (Lee Hang Building redevelopment) | C42: 10 Cheung Yue Street | E42: Cheung Sha Wan | F42: =VLOOKUP(Table1[[#This Row],[CBRE sub-markets]],Reference!$A$2:$B$31,2,FALSE) -> Kowloon Others | G42: =VLOOKUP(Table1[[#This Row],[CBRE sub-markets]],Reference!$A$2:$D$31,3,FALSE) -> 8 | H42: =VLOOKUP(Table1[[#This Row],[CBRE sub-markets]],Reference!$A$2:$D$31,4,FALSE) -> Kowloon | I42: 2014 | J42: 1 | K42: =IF(ISNUMBER(Table1[[#This Row],[Qtr]]),CONCATENATE(Table1[[#This Row],[Year]]," Q",Table1[[#This Row],[Qtr]]),CONCATENATE(Table1[[#This Row],[Year]],Table1[[#This Row],[Qtr]])) -> 2014 Q1 | L42: A Office | M42: Completed | N42: 1 | O42: 29 | Q42: =+W42/O42 -> 7162.8852 | R42: =Q42*(Y42/W42) -> 5551.3289 | S42: =IF(AND(ISNUMBER(R42),R42>=15000),"Yes",IF(R42="","Unknown","No")) -> No | V42: 19298 | W42: =V42*10.764 -> 207723.67 | X42: 14956.2 | Y42: =X42*10.764 -> 160988.54 | AC42: =IF(Table1[[#This Row],[For Sale or For Lease?]]="For Lease",Table1[[#This Row],[Office UFA (Net) (sf)]]-Table1[[#This Row],[Pre-leased space (Usable FA) (sf)]]-Table1[[#This Row],[Pre-sold (Usable FA) (sf)]]-Table1[[#This Row],[Self-use space (Usable FA) (sf)]],0) -> 0 | AD42: =IF(Table1[[#This Row],[For Sale or For Lease?]]="For Sale",Table1[[#This Row],[Office UFA (Net) (sf)]]-Table1[[#This Row],[Pre-leased space (Usable FA) (sf)]]-Table1[[#This Row],[Pre-sold (Usable FA) (sf)]]-Table1[[#This Row],[Self-use space (Usable FA) (sf)]],0) -> 160988.54 | AE42: =IF(Table1[[#This Row],[For Sale or For Lease?]]="Uncertain",Table1[[#This Row],[Office UFA (Net) (sf)]]-Table1[[#This Row],[Pre-leased space (Usable FA) (sf)]]-Table1[[#This Row],[Pre-sold (Usable FA) (sf)]]-Table1[[#This Row],[Self-use space (Usable FA) (sf)]],0) -> 0 | AF42: =1-SUM(Table1[[#This Row],[Space available for lease (Usable FA) (sf)]:[Space available uncertain of use (Usable FA) (sf)]])/Table1[[#This Row],[Office UFA (Net) (sf)]] -> 0 | AG42: Commercial | AH42: OP Issued | AI42: BD Monthly Digest | AJ42: 41640 | AK42: 41730 | AL42: Redevelopment | AM42: Billion Development | AN42: Private Sector | AO42: For Sale | AP42: Strata-title | AQ42: Apr 2014: To be completed in May 2014 according to Billion online brochure. Jun 2013: should get pre-sale consent this month. Dec 2012 (Sing Tao): Billion has applied for pre-sale consent for the second phase of Billion Plaza, No 10 Cheung Yue Street, Cheung Sha Wan. It is expected that it would receive the approval in the first to the second quarter of next year. The indicative psf price is nearly HK$10,000. Aug 2012 (JD): foundation stage 27Sep2011 (HKET): "Earliest Billion can release this project is 1H 2011, around $7,000 psf" Sep 2011: JD (OS) - currently bare site and have started construction. OP is expected around Q3 2013 (latest from landlord). Demolition Issued March 2011 | AR42: CS010
B43: Wong Tsz Building | C43: 71 Hoi Yuen Road | E43: Kwun Tong | F43: =VLOOKUP(Table1[[#This Row],[CBRE sub-markets]],Reference!$A$2:$B$31,2,FALSE) -> Kowloon East | G43: =VLOOKUP(Table1[[#This Row],[CBRE sub-markets]],Reference!$A$2:$D$31,3,FALSE) -> 7 | H43: =VLOOKUP(Table1[[#This Row],[CBRE sub-markets]],Reference!$A$2:$D$31,4,FALSE) -> Kowloon | I43: 2014 | J43: 1 | K43: =IF(ISNUMBER(Table1[[#This Row],[Qtr]]),CONCATENATE(Table1[[#This Row],[Year]]," Q",Table1[[#This Row],[Qtr]]),CONCATENATE(Table1[[#This Row],[Year]],Table1[[#This Row],[Qtr]])) -> 2014 Q1 | L43: Revitalization | M43: Completed | N43: 1 | S43: =IF(AND(ISNUMBER(R43),R43>=15000),"Yes",IF(R43="","Unknown","No")) -> Unknown | V43: =W43/10.764 -> 9476.0312 | W43: 102000 | X43: =Y43/10.764 -> 6633.2219 | Y43: =W43*0.7 -> 71400 | AC43: =IF(Table1[[#This Row],[For Sale or For Lease?]]="For Lease",Table1[[#This Row],[Office UFA (Net) (sf)]]-Table1[[#This Row],[Pre-leased space (Usable FA) (sf)]]-Table1[[#This Row],[Pre-sold (Usable FA) (sf)]]-Table1[[#This Row],[Self-use space (Usable FA) (sf)]],0) -> 0 | AD43: =IF(Table1[[#This Row],[For Sale or For Lease?]]="For Sale",Table1[[#This Row],[Office UFA (Net) (sf)]]-Table1[[#This Row],[Pre-leased space (Usable FA) (sf)]]-Table1[[#This Row],[Pre-sold (Usable FA) (sf)]]-Table1[[#This Row],[Self-use space (Usable FA) (sf)]],0) -> 0 | AE43: =IF(Table1[[#This Row],[For Sale or For Lease?]]="Uncertain",Table1[[#This Row],[Office UFA (Net) (sf)]]-Table1[[#This Row],[Pre-leased space (Usable FA) (sf)]]-Table1[[#This Row],[Pre-sold (Usable FA) (sf)]]-Table1[[#This Row],[Self-use space (Usable FA) (sf)]],0) -> 0 | AF43: =1-SUM(Table1[[#This Row],[Space available for lease (Usable FA) (sf)]:[Space available uncertain of use (Usable FA) (sf)]])/Table1[[#This Row],[Office UFA (Net) (sf)]] -> 1 | AL43: Revitalization | AN43: Private Sector | AP43: Single owner | AR43: NS047 | AV43: MULTIPOLYGON (((114.225081949 22.3112402570001,114.225266912 22.311031689,114.225044049 22.310854717,114.224854612 22.3110645470001,114.225081949 22.3112402570001)))
B44: Pioneer Place | C44: 213 Wai Yip Street | D44: KTIL 294 | E44: Kwun Tong | F44: =VLOOKUP(Table1[[#This Row],[CBRE sub-markets]],Reference!$A$2:$B$31,2,FALSE) -> Kowloon East | G44: =VLOOKUP(Table1[[#This Row],[CBRE sub-markets]],Reference!$A$2:$D$31,3,FALSE) -> 7 | H44: =VLOOKUP(Table1[[#This Row],[CBRE sub-markets]],Reference!$A$2:$D$31,4,FALSE) -> Kowloon | I44: 2014 | J44: 2 | K44: =IF(ISNUMBER(Table1[[#This Row],[Qtr]]),CONCATENATE(Table1[[#This Row],[Year]]," Q",Table1[[#This Row],[Qtr]]),CONCATENATE(Table1[[#This Row],[Year]],Table1[[#This Row],[Qtr]])) -> 2014 Q2 | L44: Revitalization | M44: Completed | N44: 1 | O44: 10 | Q44: =W44/O44 -> 23093.4 | R44: =Q44*0.75 -> 17320.05 | S44: =IF(AND(ISNUMBER(R44),R44>=15000),"Yes",IF(R44="","Unknown","No")) -> Yes | V44: =W44/10.764 -> 21454.292 | W44: 230934 | X44: =V44*0.75 -> 16090.719 | Y44: =X44*10.764 -> 173200.5 | AC44: =IF(Table1[[#This Row],[For Sale or For Lease?]]="For Lease",Table1[[#This Row],[Office UFA (Net) (sf)]]-Table1[[#This Row],[Pre-leased space (Usable FA) (sf)]]-Table1[[#This Row],[Pre-sold (Usable FA) (sf)]]-Table1[[#This Row],[Self-use space (Usable FA) (sf)]],0) -> 173200.5 | AD44: =IF(Table1[[#This Row],[For Sale or For Lease?]]="For Sale",Table1[[#This Row],[Office UFA (Net) (sf)]]-Table1[[#This Row],[Pre-leased space (Usable FA) (sf)]]-Table1[[#This Row],[Pre-sold (Usable FA) (sf)]]-Table1[[#This Row],[Self-use space (Usable FA) (sf)]],0) -> 0 | AE44: =IF(Table1[[#This Row],[For Sale or For Lease?]]="Uncertain",Table1[[#This Row],[Office UFA (Net) (sf)]]-Table1[[#This Row],[Pre-leased space (Usable FA) (sf)]]-Table1[[#This Row],[Pre-sold (Usable FA) (sf)]]-Table1[[#This Row],[Self-use space (Usable FA) (sf)]],0) -> 0 | AF44: =1-SUM(Table1[[#This Row],[Space available for lease (Usable FA) (sf)]:[Space available uncertain of use (Usable FA) (sf)]])/Table1[[#This Row],[Office UFA (Net) (sf)]] -> 0 | AK44: 41429 | AL44: Revitalization | AM44: Pioneer Global Group Limited (Gaw) | AN44: Private Sector | AO44: For Lease | AP44: Single owner | AQ44: Jun 2013: The proposed scheme has been approved by the government in May 2012. The conversion works will start in 2nd quarter of 2013, and completion is expected by the middle of 2014. | AR44: KK046B | AV44: MULTIPOLYGON (((114.222365464 22.3095479070001,114.222384817 22.3095619280001,114.22272006 22.3091872300001,114.222644615 22.309130409,114.222622333 22.3091553150001,114.222481264 22.3090459900001,114.222350142001 22.309055596,114.222095843 22.3093391790001,114.222365464 22.3095479070001)))
B45: South Asia Commercial Centre | C45: 64 Tsun Yip Street | E45: Kwun Tong | F45: =VLOOKUP(Table1[[#This Row],[CBRE sub-markets]],Reference!$A$2:$B$31,2,FALSE) -> Kowloon East | G45: =VLOOKUP(Table1[[#This Row],[CBRE sub-markets]],Reference!$A$2:$D$31,3,FALSE) -> 7 | H45: =VLOOKUP(Table1[[#This Row],[CBRE sub-markets]],Reference!$A$2:$D$31,4,FALSE) -> Kowloon | I45: 2014 | J45: 2 | K45: =IF(ISNUMBER(Table1[[#This Row],[Qtr]]),CONCATENATE(Table1[[#This Row],[Year]]," Q",Table1[[#This Row],[Qtr]]),CONCATENATE(Table1[[#This Row],[Year]],Table1[[#This Row],[Qtr]])) -> 2014 Q2 | L45: Revitalization | M45: Completed | N45: 1 | S45: =IF(AND(ISNUMBER(R45),R45>=15000),"Yes",IF(R45="","Unknown","No")) -> Unknown | V45: =W45/10.764 -> 11148.272 | W45: 120000 | X45: =Y45/10.764 -> 7803.7904 | Y45: =W45*0.7 -> 84000 | AC45: =IF(Table1[[#This Row],[For Sale or For Lease?]]="For Lease",Table1[[#This Row],[Office UFA (Net) (sf)]]-Table1[[#This Row],[Pre-leased space (Usable FA) (sf)]]-Table1[[#This Row],[Pre-sold (Usable FA) (sf)]]-Table1[[#This Row],[Self-use space (Usable FA) (sf)]],0) -> 0 | AD45: =IF(Table1[[#This Row],[For Sale or For Lease?]]="For Sale",Table1[[#This Row],[Office UFA (Net) (sf)]]-Table1[[#This Row],[Pre-leased space (Usable FA) (sf)]]-Table1[[#This Row],[Pre-sold (Usable FA) (sf)]]-Table1[[#This Row],[Self-use space (Usable FA) (sf)]],0) -> 0 | AE45: =IF(Table1[[#This Row],[For Sale or For Lease?]]="Uncertain",Table1[[#This Row],[Office UFA (Net) (sf)]]-Table1[[#This Row],[Pre-leased space (Usable FA) (sf)]]-Table1[[#This Row],[Pre-sold (Usable FA) (sf)]]-Table1[[#This Row],[Self-use space (Usable FA) (sf)]],0) -> 0 | AF45: =1-SUM(Table1[[#This Row],[Space available for lease (Usable FA) (sf)]:[Space available uncertain of use (Usable FA) (sf)]])/Table1[[#This Row],[Office UFA (Net) (sf)]] -> 1 | AL45: Revitalization | AM45: South Asia Real Estate Development (South Asia Textiles) | AN45: Private Sector | AP45: Single owner | AR45: NS045 | AV45: MULTIPOLYGON (((114.22321758 22.311698273,114.22335021 22.3118011930001,114.223673823 22.311437202,114.223540679 22.3113342830001,114.22321758 22.311698273)))
B46: Hung To Centre | C46: 94-96 How Ming Street | E46: Kwun Tong | F46: =VLOOKUP(Table1[[#This Row],[CBRE sub-markets]],Reference!$A$2:$B$31,2,FALSE) -> Kowloon East | G46: =VLOOKUP(Table1[[#This Row],[CBRE sub-markets]],Reference!$A$2:$D$31,3,FALSE) -> 7 | H46: =VLOOKUP(Table1[[#This Row],[CBRE sub-markets]],Reference!$A$2:$D$31,4,FALSE) -> Kowloon | I46: 2014 | J46: 3 | K46: =IF(ISNUMBER(Table1[[#This Row],[Qtr]]),CONCATENATE(Table1[[#This Row],[Year]]," Q",Table1[[#This Row],[Qtr]]),CONCATENATE(Table1[[#This Row],[Year]],Table1[[#This Row],[Qtr]])) -> 2014 Q3 | L46: Revitalization | M46: Completed | N46: 1 | S46: =IF(AND(ISNUMBER(R46),R46>=15000),"Yes",IF(R46="","Unknown","No")) -> Unknown | V46: =W46/10.764 -> 10405.054 | W46: 112000 | X46: =Y46/10.764 -> 7283.5377 | Y46: =W46*0.7 -> 78400 | AC46: =IF(Table1[[#This Row],[For Sale or For Lease?]]="For Lease",Table1[[#This Row],[Office UFA (Net) (sf)]]-Table1[[#This Row],[Pre-leased space (Usable FA) (sf)]]-Table1[[#This Row],[Pre-sold (Usable FA) (sf)]]-Table1[[#This Row],[Self-use space (Usable FA) (sf)]],0) -> 0 | AD46: =IF(Table1[[#This Row],[For Sale or For Lease?]]="For Sale",Table1[[#This Row],[Office UFA (Net) (sf)]]-Table1[[#This Row],[Pre-leased space (Usable FA) (sf)]]-Table1[[#This Row],[Pre-sold (Usable FA) (sf)]]-Table1[[#This Row],[Self-use space (Usable FA) (sf)]],0) -> 0 | AE46: =IF(Table1[[#This Row],[For Sale or For Lease?]]="Uncertain",Table1[[#This Row],[Office UFA (Net) (sf)]]-Table1[[#This Row],[Pre-leased space (Usable FA) (sf)]]-Table1[[#This Row],[Pre-sold (Usable FA) (sf)]]-Table1[[#This Row],[Self-use space (Usable FA) (sf)]],0) -> 0 | AF46: =1-SUM(Table1[[#This Row],[Space available for lease (Usable FA) (sf)]:[Space available uncertain of use (Usable FA) (sf)]])/Table1[[#This Row],[Office UFA (Net) (sf)]] -> 1 | AL46: Revitalization | AM46: Jointak Labels | AN46: Private Sector | AP46: Single owner | AR46: NS046 | AV46: MULTIPOLYGON (((114.220268647 22.312620328,114.220149508 22.312728737,114.220157576 22.3128393880001,114.220443895 22.3130591190001,114.220590384 22.3129254380001,114.220268647 22.312620328)))
B47: The Octagon | C47: 6 Sha Tsui Road | E47: Kwai Chung & Tsuen Wan | F47: =VLOOKUP(Table1[[#This Row],[CBRE sub-markets]],Reference!$A$2:$B$31,2,FALSE) -> New Territories | G47: =VLOOKUP(Table1[[#This Row],[CBRE sub-markets]],Reference!$A$2:$D$31,3,FALSE) -> 9 | H47: =VLOOKUP(Table1[[#This Row],[CBRE sub-markets]],Reference!$A$2:$D$31,4,FALSE) -> New Territories | I47: 2014 | J47: 3 | K47: =IF(ISNUMBER(Table1[[#This Row],[Qtr]]),CONCATENATE(Table1[[#This Row],[Year]]," Q",Table1[[#This Row],[Qtr]]),CONCATENATE(Table1[[#This Row],[Year]],Table1[[#This Row],[Qtr]])) -> 2014 Q3 | L47: A Office | M47: Completed | N47: 1 | O47: 33 | P47: 22 | Q47: 15251 | R47: =Q47*0.74 -> 11285.74 | S47: =IF(AND(ISNUMBER(R47),R47>=15000),"Yes",IF(R47="","Unknown","No")) -> No | V47: =W47/10.764 -> 36838.164 | W47: 396526 | X47: =Y47/10.764 -> 27260.242 | Y47: 293429.24 | Z47: 11285.74 | AC47: =IF(Table1[[#This Row],[For Sale or For Lease?]]="For Lease",Table1[[#This Row],[Office UFA (Net) (sf)]]-Table1[[#This Row],[Pre-leased space (Usable FA) (sf)]]-Table1[[#This Row],[Pre-sold (Usable FA) (sf)]]-Table1[[#This Row],[Self-use space (Usable FA) (sf)]],0) -> 282143.5 | AD47: =IF(Table1[[#This Row],[For Sale or For Lease?]]="For Sale",Table1[[#This Row],[Office UFA (Net) (sf)]]-Table1[[#This Row],[Pre-leased space (Usable FA) (sf)]]-Table1[[#This Row],[Pre-sold (Usable FA) (sf)]]-Table1[[#This Row],[Self-use space (Usable FA) (sf)]],0) -> 0 | AE47: =IF(Table1[[#This Row],[For Sale or For Lease?]]="Uncertain",Table1[[#This Row],[Office UFA (Net) (sf)]]-Table1[[#This Row],[Pre-leased space (Usable FA) (sf)]]-Table1[[#This Row],[Pre-sold (Usable FA) (sf)]]-Table1[[#This Row],[Self-use space (Usable FA) (sf)]],0) -> 0 | AF47: =1-SUM(Table1[[#This Row],[Space available for lease (Usable FA) (sf)]:[Space available uncertain of use (Usable FA) (sf)]])/Table1[[#This Row],[Office UFA (Net) (sf)]] -> 0.038461538 | AG47: Commercial | AH47: OP Issued | AI47: BD Monthly Digest | AJ47: 41913 | AK47: 41997 | AL47: Redevelopment | AM47: K Wah Group | AN47: Private Sector | AO47: For Lease | AP47: Single owner | AQ47: Jan 2013 (Ming Pao): K. Wah is looking to pre-sell the unfinished units as soon as after CNY. Floor plate of approx. 18,000 sf, and scheduled to be completed in Q3 2014. The tentative price is around $10,000 psf Sep 2011: Sam (OS) - highly unlikely to be office, existing use is industrial. Need to check with Darren Benson. | AR47: KF009
B48: Southland Building | C48: 48 Connaught Road Central | E48: Central | F48: =VLOOKUP(Table1[[#This Row],[CBRE sub-markets]],Reference!$A$2:$B$31,2,FALSE) -> Central | G48: =VLOOKUP(Table1[[#This Row],[CBRE sub-markets]],Reference!$A$2:$D$31,3,FALSE) -> 1 | H48: =VLOOKUP(Table1[[#This Row],[CBRE sub-markets]],Reference!$A$2:$D$31,4,FALSE) -> Hong Kong Island | I48: 2014 | J48: 4 | K48: =IF(ISNUMBER(Table1[[#This Row],[Qtr]]),CONCATENATE(Table1[[#This Row],[Year]]," Q",Table1[[#This Row],[Qtr]]),CONCATENATE(Table1[[#This Row],[Year]],Table1[[#This Row],[Qtr]])) -> 2014 Q4 | L48: B Office | M48: Completed | N48: 1 | O48: 25 | Q48: =Table1[[#This Row],[Office GFA (sf)]]/25 -> 1542.0506 | R48: =Table1[[#This Row],[Office UFA (Net) (sf)]]/25 -> 793.3068 | S48: =IF(AND(ISNUMBER(R48),R48>=15000),"Yes",IF(R48="","Unknown","No")) -> No | V48: 3581.5 | W48: =Table1[[#This Row],[Office GFA (sm)]]*10.764 -> 38551.266 | X48: 1842.5 | Y48: =Table1[[#This Row],[Office UFA (Net) (sm)]]*10.764 -> 19832.67 | AC48: =IF(Table1[[#This Row],[For Sale or For Lease?]]="For Lease",Table1[[#This Row],[Office UFA (Net) (sf)]]-Table1[[#This Row],[Pre-leased space (Usable FA) (sf)]]-Table1[[#This Row],[Pre-sold (Usable FA) (sf)]]-Table1[[#This Row],[Self-use space (Usable FA) (sf)]],0) -> 19832.67 | AD48: =IF(Table1[[#This Row],[For Sale or For Lease?]]="For Sale",Table1[[#This Row],[Office UFA (Net) (sf)]]-Table1[[#This Row],[Pre-leased space (Usable FA) (sf)]]-Table1[[#This Row],[Pre-sold (Usable FA) (sf)]]-Table1[[#This Row],[Self-use space (Usable FA) (sf)]],0) -> 0 | AE48: =IF(Table1[[#This Row],[For Sale or For Lease?]]="Uncertain",Table1[[#This Row],[Office UFA (Net) (sf)]]-Table1[[#This Row],[Pre-leased space (Usable FA) (sf)]]-Table1[[#This Row],[Pre-sold (Usable FA) (sf)]]-Table1[[#This Row],[Self-use space (Usable FA) (sf)]],0) -> 0 | AF48: =1-SUM(Table1[[#This Row],[Space available for lease (Usable FA) (sf)]:[Space available uncertain of use (Usable FA) (sf)]])/Table1[[#This Row],[Office UFA (Net) (sf)]] -> 0 | AG48: Commercial | AH48: OP Issued | AI48: BD Monthly Digest | AJ48: 41913 | AK48: 42116 | AL48: Redevelopment | AM48: Southland Co Ltd | AN48: Private Sector | AO48: For Lease | AP48: Single owner | AR48: NS041 | AV48: MULTIPOLYGON (((114.156082121 22.284894273,114.156070856 22.284907698,114.156036824 22.284882963,114.155987252 22.284942038,114.15598755 22.284968744,114.156076646 22.285033498,114.156151696 22.284944061,114.156082121 22.284894273)))
B49: The Wellington | C49: 198 Wellington Street | E49: Sheung Wan | F49: =VLOOKUP(Table1[[#This Row],[CBRE sub-markets]],Reference!$A$2:$B$31,2,FALSE) -> Admiralty & Sheung Wan | G49: =VLOOKUP(Table1[[#This Row],[CBRE sub-markets]],Reference!$A$2:$D$31,3,FALSE) -> 2 | H49: =VLOOKUP(Table1[[#This Row],[CBRE sub-markets]],Reference!$A$2:$D$31,4,FALSE) -> Hong Kong Island | I49: 2014 | J49: 4 | K49: =IF(ISNUMBER(Table1[[#This Row],[Qtr]]),CONCATENATE(Table1[[#This Row],[Year]]," Q",Table1[[#This Row],[Qtr]]),CONCATENATE(Table1[[#This Row],[Year]],Table1[[#This Row],[Qtr]])) -> 2014 Q4 | L49: B Office | M49: Completed | N49: 1 | O49: 29 | P49: 18 | Q49: =Table1[[#This Row],[Office GFA (sf)]]/Table1[[#This Row],[No. of Storeys]] -> 2914.7427 | R49: =Table1[[#This Row],[Office UFA (Net) (sf)]]/Table1[[#This Row],[No. of Storeys]] -> 1857.6808 | S49: =IF(AND(ISNUMBER(R49),R49>=15000),"Yes",IF(R49="","Unknown","No")) -> No | V49: 7852.8 | W49: =V49*10.764 -> 84527.539 | X49: 5004.9 | Y49: =X49*10.764 -> 53872.744 | AC49: =IF(Table1[[#This Row],[For Sale or For Lease?]]="For Lease",Table1[[#This Row],[Office UFA (Net) (sf)]]-Table1[[#This Row],[Pre-leased space (Usable FA) (sf)]]-Table1[[#This Row],[Pre-sold (Usable FA) (sf)]]-Table1[[#This Row],[Self-use space (Usable FA) (sf)]],0) -> 53872.744 | AD49: =IF(Table1[[#This Row],[For Sale or For Lease?]]="For Sale",Table1[[#This Row],[Office UFA (Net) (sf)]]-Table1[[#This Row],[Pre-leased space (Usable FA) (sf)]]-Table1[[#This Row],[Pre-sold (Usable FA) (sf)]]-Table1[[#This Row],[Self-use space (Usable FA) (sf)]],0) -> 0 | AE49: =IF(Table1[[#This Row],[For Sale or For Lease?]]="Uncertain",Table1[[#This Row],[Office UFA (Net) (sf)]]-Table1[[#This Row],[Pre-leased space (Usable FA) (sf)]]-Table1[[#This Row],[Pre-sold (Usable FA) (sf)]]-Table1[[#This Row],[Self-use space (Usable FA) (sf)]],0) -> 0 | AF49: =1-SUM(Table1[[#This Row],[Space available for lease (Usable FA) (sf)]:[Space available uncertain of use (Usable FA) (sf)]])/Table1[[#This Row],[Office UFA (Net) (sf)]] -> 0 | AG49: Commercial | AH49: OP Issued | AI49: BD Monthly Digest | AJ49: 41974 | AK49: 42116 | AL49: Redevelopment | AM49: Nan Fung Resources | AN49: Private Sector | AO49: For Lease | AP49: Single owner | AR49: SW06B | AV49: MULTIPOLYGON (((114.152910576 22.2849401170001,114.153114842 22.2847421660001,114.153062951 22.2847068030001,114.153027612 22.284741059,114.152997418 22.2847161610001,114.152972792 22.2847404900001,114.152978472 22.284759325,114.152882334 22.284828167,114.152910576 22.2849401170001)))
B50: 10 Shing Yip Street | C50: 10 Shing Yip Street | E50: Kwun Tong | F50: =VLOOKUP(Table1[[#This Row],[CBRE sub-markets]],Reference!$A$2:$B$31,2,FALSE) -> Kowloon East | G50: =VLOOKUP(Table1[[#This Row],[CBRE sub-markets]],Reference!$A$2:$D$31,3,FALSE) -> 7 | H50: =VLOOKUP(Table1[[#This Row],[CBRE sub-markets]],Reference!$A$2:$D$31,4,FALSE) -> Kowloon | I50: 2014 | J50: 4 | K50: =IF(ISNUMBER(Table1[[#This Row],[Qtr]]),CONCATENATE(Table1[[#This Row],[Year]]," Q",Table1[[#This Row],[Qtr]]),CONCATENATE(Table1[[#This Row],[Year]],Table1[[#This Row],[Qtr]])) -> 2014 Q4 | L50: A Office | M50: Completed | N50: 1 | O50: 31 | P50: 14 | Q50: =3813+802+901+937+855+831+740+2066+1787 -> 12732 | R50: =2594+545+612+637+581+565+503+1405+1215 -> 8657 | S50: =IF(AND(ISNUMBER(R50),R50>=15000),"Yes",IF(R50="","Unknown","No")) -> No | V50: =W50/10.7639 -> 16559.797 | W50: =(3813+802+901+937+855+831+740+2066+1787)*12+12732*2 -> 178248 | X50: =Y50/10.7639 -> 12332.054 | Y50: =(2594+545+612+637+581+565+503+1405+1215)*12+9619*3 -> 132741 | AC50: =IF(Table1[[#This Row],[For Sale or For Lease?]]="For Lease",Table1[[#This Row],[Office UFA (Net) (sf)]]-Table1[[#This Row],[Pre-leased space (Usable FA) (sf)]]-Table1[[#This Row],[Pre-sold (Usable FA) (sf)]]-Table1[[#This Row],[Self-use space (Usable FA) (sf)]],0) -> 0 | AD50: =IF(Table1[[#This Row],[For Sale or For Lease?]]="For Sale",Table1[[#This Row],[Office UFA (Net) (sf)]]-Table1[[#This Row],[Pre-leased space (Usable FA) (sf)]]-Table1[[#This Row],[Pre-sold (Usable FA) (sf)]]-Table1[[#This Row],[Self-use space (Usable FA) (sf)]],0) -> 132741 | AE50: =IF(Table1[[#This Row],[For Sale or For Lease?]]="Uncertain",Table1[[#This Row],[Office UFA (Net) (sf)]]-Table1[[#This Row],[Pre-leased space (Usable FA) (sf)]]-Table1[[#This Row],[Pre-sold (Usable FA) (sf)]]-Table1[[#This Row],[Self-use space (Usable FA) (sf)]],0) -> 0 | AF50: =1-SUM(Table1[[#This Row],[Space available for lease (Usable FA) (sf)]:[Space available uncertain of use (Usable FA) (sf)]])/Table1[[#This Row],[Office UFA (Net) (sf)]] -> 0 | AG50: Commercial | AH50: OP Issued | AI50: BD Monthly Digest | AJ50: 41974 | AK50: 42052 | AL50: Redevelopment | AM50: Billion Development | AN50: Private Sector | AO50: For Sale | AP50: Strata-title | AQ50: Feb 2015 (RN): got OP in Dec 2014 Feb 2015 (JN): NFA updated according to Feb3 price list Nov 2014 (RN): should be able to complete this year. Jun 2013: foundation done. Dec 2012 (Sing Tao): Billion has paid land premium of around $2,700-$2,800 psf. They will apply for pre-sale consent this month at the earliest. They may be approved and put up for sale in the third and the fourth quarter of next year. The indicative psf price is more than HK$10,000. Aug 2012 (JD): delayed due to land premium issue. Clear site at the moment, no foundation. Jun 2012: Demolished. Could be delayed subject to lease modification. Nov 2011 (Roy): Demolition issued in October. Sep 2011: JD (OS) - could be delayed from 2013 to 2014 Q1 earliest / Sam (OS) - developer appealing against land premium, if land premium is exceeds $3,000 psf, then they will only refurbish. Only scaffolding, no demolition works yet. Billion bought in Q3 2009 for $340m. existing bldg: Trinity Textile Industrial Building (No demolition record from BD yet) | AR50: KK042
B51: The Mark | C51: 164 Wai Yip Street | E51: Kwun Tong | F51: =VLOOKUP(Table1[[#This Row],[CBRE sub-markets]],Reference!$A$2:$B$31,2,FALSE) -> Kowloon East | G51: =VLOOKUP(Table1[[#This Row],[CBRE sub-markets]],Reference!$A$2:$D$31,3,FALSE) -> 7 | H51: =VLOOKUP(Table1[[#This Row],[CBRE sub-markets]],Reference!$A$2:$D$31,4,FALSE) -> Kowloon | I51: 2014 | J51: 4 | K51: =IF(ISNUMBER(Table1[[#This Row],[Qtr]]),CONCATENATE(Table1[[#This Row],[Year]]," Q",Table1[[#This Row],[Qtr]]),CONCATENATE(Table1[[#This Row],[Year]],Table1[[#This Row],[Qtr]])) -> 2014 Q4 | L51: Revitalization | M51: Completed | N51: 1 | S51: =IF(AND(ISNUMBER(R51),R51>=15000),"Yes",IF(R51="","Unknown","No")) -> Unknown | V51: =W51/10.764 -> 6224.4519 | W51: 67000 | X51: =Y51/10.764 -> 4357.1163 | Y51: =W51*0.7 -> 46900 | AC51: =IF(Table1[[#This Row],[For Sale or For Lease?]]="For Lease",Table1[[#This Row],[Office UFA (Net) (sf)]]-Table1[[#This Row],[Pre-leased space (Usable FA) (sf)]]-Table1[[#This Row],[Pre-sold (Usable FA) (sf)]]-Table1[[#This Row],[Self-use space (Usable FA) (sf)]],0) -> 0 | AD51: =IF(Table1[[#This Row],[For Sale or For Lease?]]="For Sale",Table1[[#This Row],[Office UFA (Net) (sf)]]-Table1[[#This Row],[Pre-leased space (Usable FA) (sf)]]-Table1[[#This Row],[Pre-sold (Usable FA) (sf)]]-Table1[[#This Row],[Self-use space (Usable FA) (sf)]],0) -> 0 | AE51: =IF(Table1[[#This Row],[For Sale or For Lease?]]="Uncertain",Table1[[#This Row],[Office UFA (Net) (sf)]]-Table1[[#This Row],[Pre-leased space (Usable FA) (sf)]]-Table1[[#This Row],[Pre-sold (Usable FA) (sf)]]-Table1[[#This Row],[Self-use space (Usable FA) (sf)]],0) -> 0 | AF51: =1-SUM(Table1[[#This Row],[Space available for lease (Usable FA) (sf)]:[Space available uncertain of use (Usable FA) (sf)]])/Table1[[#This Row],[Office UFA (Net) (sf)]] -> 1 | AL51: Revitalization | AM51: Pamfleet | AN51: Private Sector | AP51: Single owner | AR51: NS048 | AV51: MULTIPOLYGON (((114.220275762 22.310913575,114.220267733 22.310885894,114.220285466 22.310867102,114.220301158 22.3108850710001,114.220371643 22.3108067820001,114.220236785 22.310703346,114.220144819001 22.310812569,114.220275762 22.310913575)))
B52: Genesis Centre | C52: 33-35 Wong Chuk Hang Road | E52: Wong Chuk Hang | F52: =VLOOKUP(Table1[[#This Row],[CBRE sub-markets]],Reference!$A$2:$B$31,2,FALSE) -> Wong Chuk Hang | G52: =VLOOKUP(Table1[[#This Row],[CBRE sub-markets]],Reference!$A$2:$D$31,3,FALSE) -> 5 | H52: =VLOOKUP(Table1[[#This Row],[CBRE sub-markets]],Reference!$A$2:$D$31,4,FALSE) -> Hong Kong Island | I52: 2015 | J52: 1 | K52: =IF(ISNUMBER(Table1[[#This Row],[Qtr]]),CONCATENATE(Table1[[#This Row],[Year]]," Q",Table1[[#This Row],[Qtr]]),CONCATENATE(Table1[[#This Row],[Year]],Table1[[#This Row],[Qtr]])) -> 2015 Q1 | L52: Revitalization | M52: Completed | N52: 1 | O52: 23 | Q52: 10254 | R52: =Q52*0.75 -> 7690.5 | S52: =IF(AND(ISNUMBER(R52),R52>=15000),"Yes",IF(R52="","Unknown","No")) -> No | V52: =W52/10.764 -> 22296.544 | W52: 240000 | X52: =Y52/10.764 -> 15607.581 | Y52: =W52*0.7 -> 168000 | AC52: =IF(Table1[[#This Row],[For Sale or For Lease?]]="For Lease",Table1[[#This Row],[Office UFA (Net) (sf)]]-Table1[[#This Row],[Pre-leased space (Usable FA) (sf)]]-Table1[[#This Row],[Pre-sold (Usable FA) (sf)]]-Table1[[#This Row],[Self-use space (Usable FA) (sf)]],0) -> 168000 | AD52: =IF(Table1[[#This Row],[For Sale or For Lease?]]="For Sale",Table1[[#This Row],[Office UFA (Net) (sf)]]-Table1[[#This Row],[Pre-leased space (Usable FA) (sf)]]-Table1[[#This Row],[Pre-sold (Usable FA) (sf)]]-Table1[[#This Row],[Self-use space (Usable FA) (sf)]],0) -> 0 | AE52: =IF(Table1[[#This Row],[For Sale or For Lease?]]="Uncertain",Table1[[#This Row],[Office UFA (Net) (sf)]]-Table1[[#This Row],[Pre-leased space (Usable FA) (sf)]]-Table1[[#This Row],[Pre-sold (Usable FA) (sf)]]-Table1[[#This Row],[Self-use space (Usable FA) (sf)]],0) -> 0 | AF52: =1-SUM(Table1[[#This Row],[Space available for lease (Usable FA) (sf)]:[Space available uncertain of use (Usable FA) (sf)]])/Table1[[#This Row],[Office UFA (Net) (sf)]] -> 0 | AG52: Commercial | AI52: Collier's | AJ52: 41306 | AK52: 42125 | AL52: Revitalization | AM52: Hip Shing Hong | AN52: Private Sector | AO52: For Lease | AP52: Single owner | AQ52: Jason (May 2014): Flatted factory, undergoing revialization for office-use. Wholesale conversion | AR52: NS053 | AV52: MULTIPOLYGON (((114.165393499 22.248636931,114.165385083 22.248693363,114.165612667 22.248737566,114.165857361 22.2488261290001,114.165957554 22.248571019,114.16576346 22.2485070960001,114.165423676 22.248437988,114.165393499 22.248636931)))
A53: 美心食品第三廠 redevelopment | B53: Maxim's Centre | C53: 17 Cheung Shun Street | E53: Cheung Sha Wan | F53: =VLOOKUP(Table1[[#This Row],[CBRE sub-markets]],Reference!$A$2:$B$31,2,FALSE) -> Kowloon Others | G53: =VLOOKUP(Table1[[#This Row],[CBRE sub-markets]],Reference!$A$2:$D$31,3,FALSE) -> 8 | H53: =VLOOKUP(Table1[[#This Row],[CBRE sub-markets]],Reference!$A$2:$D$31,4,FALSE) -> Kowloon | I53: 2015 | J53: 1 | K53: =IF(ISNUMBER(Table1[[#This Row],[Qtr]]),CONCATENATE(Table1[[#This Row],[Year]]," Q",Table1[[#This Row],[Qtr]]),CONCATENATE(Table1[[#This Row],[Year]],Table1[[#This Row],[Qtr]])) -> 2015 Q1 | L53: A Office | M53: Completed | N53: 1 | O53: 24+3 basement | Q53: =W53/24 -> 7915.442 | R53: =Table1[[#This Row],[Office UFA (Net) (sf)]]/24 -> 4803.5833 | S53: =IF(AND(ISNUMBER(R53),R53>=15000),"Yes",IF(R53="","Unknown","No")) -> No | V53: 17648.7 | W53: =V53*10.764 -> 189970.61 | X53: 11088.2 | Y53: 115286 | AB53: =Table1[[#This Row],[Office UFA (Net) (sf)]] -> 115286 | AC53: =IF(Table1[[#This Row],[For Sale or For Lease?]]="For Lease",Table1[[#This Row],[Office UFA (Net) (sf)]]-Table1[[#This Row],[Pre-leased space (Usable FA) (sf)]]-Table1[[#This Row],[Pre-sold (Usable FA) (sf)]]-Table1[[#This Row],[Self-use space (Usable FA) (sf)]],0) -> 0 | AD53: =IF(Table1[[#This Row],[For Sale or For Lease?]]="For Sale",Table1[[#This Row],[Office UFA (Net) (sf)]]-Table1[[#This Row],[Pre-leased space (Usable FA) (sf)]]-Table1[[#This Row],[Pre-sold (Usable FA) (sf)]]-Table1[[#This Row],[Self-use space (Usable FA) (sf)]],0) -> 0 | AE53: =IF(Table1[[#This Row],[For Sale or For Lease?]]="Uncertain",Table1[[#This Row],[Office UFA (Net) (sf)]]-Table1[[#This Row],[Pre-leased space (Usable FA) (sf)]]-Table1[[#This Row],[Pre-sold (Usable FA) (sf)]]-Table1[[#This Row],[Self-use space (Usable FA) (sf)]],0) -> 0 | AF53: =1-SUM(Table1[[#This Row],[Space available for lease (Usable FA) (sf)]:[Space available uncertain of use (Usable FA) (sf)]])/Table1[[#This Row],[Office UFA (Net) (sf)]] -> 1 | AG53: Commercial | AH53: OP Issued | AI53: BD Monthly Digest | AJ53: 42064 | AK53: 42144 | AL53: Redevelopment | AM53: Luk Yeung Restaurant Ltd (Maxim's) | AN53: Private Sector | AO53: For Lease | AP53: Single owner | AQ53: May 2015: OP received in March, Rocky says whole building should be for self-use. Apr 2015: Lease modification executed with a land premium of $418,180,000 in Feb 2013. Mar2012: Demolition issued Mar2012: Sam (OS) - Existing an old industrial building by Maxim’s Group and Maxim will redevelop the building into a Grade A office. Demolition will carry out soon. Maxim will use most of the floor spaces as their headquarters from 14/F to 27/F and 7/F to 13/F (approx. 60,222 s.f.) will be for lease. Whilst 1/F to 5/F will be reserved for restaurant use and will be handled by the Maxim in-house leasing team. | AR53: CS011
B54: 15 Chong Yip Street | C54: 15 Chong Yip Street | E54: Kwun Tong | F54: =VLOOKUP(Table1[[#This Row],[CBRE sub-markets]],Reference!$A$2:$B$31,2,FALSE) -> Kowloon East | G54: =VLOOKUP(Table1[[#This Row],[CBRE sub-markets]],Reference!$A$2:$D$31,3,FALSE) -> 7 | H54: =VLOOKUP(Table1[[#This Row],[CBRE sub-markets]],Reference!$A$2:$D$31,4,FALSE) -> Kowloon | I54: 2015 | J54: 1 | K54: =IF(ISNUMBER(Table1[[#This Row],[Qtr]]),CONCATENATE(Table1[[#This Row],[Year]]," Q",Table1[[#This Row],[Qtr]]),CONCATENATE(Table1[[#This Row],[Year]],Table1[[#This Row],[Qtr]])) -> 2015 Q1 | L54: A Office | M54: Completed | N54: 1 | O54: 37 | Q54: =+W54/O54 -> 7200.796 | R54: =Table1[[#This Row],[Office UFA (Net) (sf)]]/Table1[[#This Row],[No. of Storeys]] -> 5597.5418 | S54: =IF(AND(ISNUMBER(R54),R54>=15000),"Yes",IF(R54="","Unknown","No")) -> No | V54: 24751.9 | W54: =+V54*10.764 -> 266429.45 | X54: 19240.9 | Y54: =X54*10.764 -> 207109.05 | AC54: =IF(Table1[[#This Row],[For Sale or For Lease?]]="For Lease",Table1[[#This Row],[Office UFA (Net) (sf)]]-Table1[[#This Row],[Pre-leased space (Usable FA) (sf)]]-Table1[[#This Row],[Pre-sold (Usable FA) (sf)]]-Table1[[#This Row],[Self-use space (Usable FA) (sf)]],0) -> 0 | AD54: =IF(Table1[[#This Row],[For Sale or For Lease?]]="For Sale",Table1[[#This Row],[Office UFA (Net) (sf)]]-Table1[[#This Row],[Pre-leased space (Usable FA) (sf)]]-Table1[[#This Row],[Pre-sold (Usable FA) (sf)]]-Table1[[#This Row],[Self-use space (Usable FA) (sf)]],0) -> 207109.05 | AE54: =IF(Table1[[#This Row],[For Sale or For Lease?]]="Uncertain",Table1[[#This Row],[Office UFA (Net) (sf)]]-Table1[[#This Row],[Pre-leased space (Usable FA) (sf)]]-Table1[[#This Row],[Pre-sold (Usable FA) (sf)]]-Table1[[#This Row],[Self-use space (Usable FA) (sf)]],0) -> 0 | AF54: =1-SUM(Table1[[#This Row],[Space available for lease (Usable FA) (sf)]:[Space available uncertain of use (Usable FA) (sf)]])/Table1[[#This Row],[Office UFA (Net) (sf)]] -> 0 | AG54: Commercial | AH54: OP Issued | AI54: BD Monthly Digest | AJ54: 42036 | AK54: 42116 | AL54: Redevelopment | AM54: Billion Development | AN54: Private Sector | AO54: For Sale | AP54: Strata-title | AQ54: Apr 2014 (Roy): Called Billion, it's not available for sale/lease yet, possibly will be this month. May 2014: Land premium paid for HKD 1.122 Billion, average premium psf = HKD 4,200 psf (~267,000 sqft) Jun 2013: foundation done. Jun 2012: Demolished. Feb 2012: to be sold on strata basis. Demolition issued November 2011. Sep 2011: JD (OS) - demolition begun 1-2 months ago. Billion indicated that it could be delayed from 2013 to Q1 2014 at the earliest. | AR54: KK044
B55: 56 Tsun Yip Street | C55: 52-56 Tsun Yip Street | E55: Kwun Tong | F55: =VLOOKUP(Table1[[#This Row],[CBRE sub-markets]],Reference!$A$2:$B$31,2,FALSE) -> Kowloon East | G55: =VLOOKUP(Table1[[#This Row],[CBRE sub-markets]],Reference!$A$2:$D$31,3,FALSE) -> 7 | H55: =VLOOKUP(Table1[[#This Row],[CBRE sub-markets]],Reference!$A$2:$D$31,4,FALSE) -> Kowloon | I55: 2015 | J55: 1 | K55: =IF(ISNUMBER(Table1[[#This Row],[Qtr]]),CONCATENATE(Table1[[#This Row],[Year]]," Q",Table1[[#This Row],[Qtr]]),CONCATENATE(Table1[[#This Row],[Year]],Table1[[#This Row],[Qtr]])) -> 2015 Q1 | L55: A Office | M55: Completed | N55: 1 | O55: 35 | P55: 18 | Q55: =2296+1600+1187+1459+1329+1445+1715+1908+2061 -> 15000 | R55: =1561+1088+807+992+904+982+1166+1298+1402 -> 10200 | S55: =IF(AND(ISNUMBER(R55),R55>=15000),"Yes",IF(R55="","Unknown","No")) -> No | V55: =Table1[[#This Row],[Office GFA (sf)]]/10.764 -> 25286.696 | W55: =(2296+1600+1187+1459+1329+1445+1715+1908+1487)+(2296+1600+1187+1459+1329+1445+1715+1908+1503)+(2296+1600+1187+1459+1329+1445+1715+1908+2061)*8+(2296+1590+1151+1418+1294+1439+3627+2062)*2+(2296+1763+1201+1449+1331+1437+3627+2490)*3+15594*3 -> 272186 | X55: =Y55/10.764 -> 17540.598 | Y55: =(1561+1088+807+992+904+982+1166+1298+1011)+(1561+1088+807+992+904+982+1166+1298+1023)+(1561+1088+807+992+904+982+1166+1298+1402)*8+(1561+1081+783+964+880+978+2502+1402)*2+(1561+1199+817+985+905+977+2502+1693)*3+11786*3 -> 188807 | AA55: =1561+1298+1561+1088+807+992+904+982+1088+982+1166+1298+2502+2502+2502+1693+2502+977+2502 -> 28907 | AC55: =IF(Table1[[#This Row],[For Sale or For Lease?]]="For Lease",Table1[[#This Row],[Office UFA (Net) (sf)]]-Table1[[#This Row],[Pre-leased space (Usable FA) (sf)]]-Table1[[#This Row],[Pre-sold (Usable FA) (sf)]]-Table1[[#This Row],[Self-use space (Usable FA) (sf)]],0) -> 0 | AD55: =IF(Table1[[#This Row],[For Sale or For Lease?]]="For Sale",Table1[[#This Row],[Office UFA (Net) (sf)]]-Table1[[#This Row],[Pre-leased space (Usable FA) (sf)]]-Table1[[#This Row],[Pre-sold (Usable FA) (sf)]]-Table1[[#This Row],[Self-use space (Usable FA) (sf)]],0) -> 159900 | AE55: =IF(Table1[[#This Row],[For Sale or For Lease?]]="Uncertain",Table1[[#This Row],[Office UFA (Net) (sf)]]-Table1[[#This Row],[Pre-leased space (Usable FA) (sf)]]-Table1[[#This Row],[Pre-sold (Usable FA) (sf)]]-Table1[[#This Row],[Self-use space (Usable FA) (sf)]],0) -> 0 | AF55: =1-SUM(Table1[[#This Row],[Space available for lease (Usable FA) (sf)]:[Space available uncertain of use (Usable FA) (sf)]])/Table1[[#This Row],[Office UFA (Net) (sf)]] -> 0.15310343 | AG55: Commercial | AH55: OP Issued | AI55: BD Monthly Digest | AJ55: 42005 | AK55: 42116 | AL55: Redevelopment & Site | AM55: Billion Development | AN55: Private Sector | AO55: For Sale | AP55: Strata-title | AQ55: Dec 2012 (Sing Tao): Billion paid land premium of around $2,700-$2,800. They will apply for pre-sale consent this month at the earliest. They may be approved and put up for sale in the third and the fourth quarter of next year. The indicative psf price is more than HK$10,000. Jun 2012: Foundation stage. 27Sep2011 (HKET): land premium was approved at $3,400 psf, and will appeal Sep 2011: (OS) - they are appealing the land premium. | AR55: KK043
B56: SML Tower | C56: 165 Hoi Bun Road | E56: Kwun Tong | F56: =VLOOKUP(Table1[[#This Row],[CBRE sub-markets]],Reference!$A$2:$B$31,2,FALSE) -> Kowloon East | G56: =VLOOKUP(Table1[[#This Row],[CBRE sub-markets]],Reference!$A$2:$D$31,3,FALSE) -> 7 | H56: =VLOOKUP(Table1[[#This Row],[CBRE sub-markets]],Reference!$A$2:$D$31,4,FALSE) -> Kowloon | I56: 2015 | J56: 1 | K56: =IF(ISNUMBER(Table1[[#This Row],[Qtr]]),CONCATENATE(Table1[[#This Row],[Year]]," Q",Table1[[#This Row],[Qtr]]),CONCATENATE(Table1[[#This Row],[Year]],Table1[[#This Row],[Qtr]])) -> 2015 Q1 | L56: Revitalization | M56: Completed | N56: 1 | S56: =IF(AND(ISNUMBER(R56),R56>=15000),"Yes",IF(R56="","Unknown","No")) -> Unknown | V56: =W56/10.764 -> 13985.229 | W56: 150537 | X56: =Y56/10.764 -> 9789.66 | Y56: =W56*0.7 -> 105375.9 | AC56: =IF(Table1[[#This Row],[For Sale or For Lease?]]="For Lease",Table1[[#This Row],[Office UFA (Net) (sf)]]-Table1[[#This Row],[Pre-leased space (Usable FA) (sf)]]-Table1[[#This Row],[Pre-sold (Usable FA) (sf)]]-Table1[[#This Row],[Self-use space (Usable FA) (sf)]],0) -> 0 | AD56: =IF(Table1[[#This Row],[For Sale or For Lease?]]="For Sale",Table1[[#This Row],[Office UFA (Net) (sf)]]-Table1[[#This Row],[Pre-leased space (Usable FA) (sf)]]-Table1[[#This Row],[Pre-sold (Usable FA) (sf)]]-Table1[[#This Row],[Self-use space (Usable FA) (sf)]],0) -> 0 | AE56: =IF(Table1[[#This Row],[For Sale or For Lease?]]="Uncertain",Table1[[#This Row],[Office UFA (Net) (sf)]]-Table1[[#This Row],[Pre-leased space (Usable FA) (sf)]]-Table1[[#This Row],[Pre-sold (Usable FA) (sf)]]-Table1[[#This Row],[Self-use space (Usable FA) (sf)]],0) -> 0 | AF56: =1-SUM(Table1[[#This Row],[Space available for lease (Usable FA) (sf)]:[Space available uncertain of use (Usable FA) (sf)]])/Table1[[#This Row],[Office UFA (Net) (sf)]] -> 1 | AL56: Revitalization | AM56: Full Will Industrial Limited | AN56: Private Sector | AP56: Single owner | AR56: KK062B | AV56: MULTIPOLYGON (((114.219605532 22.311053401,114.219729618 22.310906191,114.219330096 22.3106037860001,114.219308013 22.3106147060001,114.219256109 22.3106621850001,114.219230262 22.3107283390001,114.219212403 22.310715105,114.219194521 22.3107392800001,114.219605532 22.311053401)))
B57: KC100 | C57: 100 Kwai Cheong Road | E57: Kwai Chung & Tsuen Wan | F57: =VLOOKUP(Table1[[#This Row],[CBRE sub-markets]],Reference!$A$2:$B$31,2,FALSE) -> New Territories | G57: =VLOOKUP(Table1[[#This Row],[CBRE sub-markets]],Reference!$A$2:$D$31,3,FALSE) -> 9 | H57: =VLOOKUP(Table1[[#This Row],[CBRE sub-markets]],Reference!$A$2:$D$31,4,FALSE) -> New Territories | I57: 2015 | J57: 1 | K57: =IF(ISNUMBER(Table1[[#This Row],[Qtr]]),CONCATENATE(Table1[[#This Row],[Year]]," Q",Table1[[#This Row],[Qtr]]),CONCATENATE(Table1[[#This Row],[Year]],Table1[[#This Row],[Qtr]])) -> 2015 Q1 | L57: Revitalization | M57: Completed | N57: 1 | O57: 13 | Q57: =W57/O57 -> 23076.923 | R57: =Q57*0.75 -> 17307.692 | S57: =IF(AND(ISNUMBER(R57),R57>=15000),"Yes",IF(R57="","Unknown","No")) -> Yes | V57: =W57/10.764 -> 27870.68 | W57: 300000 | X57: =V57*0.75 -> 20903.01 | Y57: =X57*10.764 -> 225000 | AC57: =IF(Table1[[#This Row],[For Sale or For Lease?]]="For Lease",Table1[[#This Row],[Office UFA (Net) (sf)]]-Table1[[#This Row],[Pre-leased space (Usable FA) (sf)]]-Table1[[#This Row],[Pre-sold (Usable FA) (sf)]]-Table1[[#This Row],[Self-use space (Usable FA) (sf)]],0) -> 225000 | AD57: =IF(Table1[[#This Row],[For Sale or For Lease?]]="For Sale",Table1[[#This Row],[Office UFA (Net) (sf)]]-Table1[[#This Row],[Pre-leased space (Usable FA) (sf)]]-Table1[[#This Row],[Pre-sold (Usable FA) (sf)]]-Table1[[#This Row],[Self-use space (Usable FA) (sf)]],0) -> 0 | AE57: =IF(Table1[[#This Row],[For Sale or For Lease?]]="Uncertain",Table1[[#This Row],[Office UFA (Net) (sf)]]-Table1[[#This Row],[Pre-leased space (Usable FA) (sf)]]-Table1[[#This Row],[Pre-sold (Usable FA) (sf)]]-Table1[[#This Row],[Self-use space (Usable FA) (sf)]],0) -> 0 | AF57: =1-SUM(Table1[[#This Row],[Space available for lease (Usable FA) (sf)]:[Space available uncertain of use (Usable FA) (sf)]])/Table1[[#This Row],[Office UFA (Net) (sf)]] -> 0 | AK57: 41429 | AL57: Revitalization | AM57: Campbell Property Development Limited | AN57: Private Sector | AO57: For Lease | AP57: Single owner | AR57: KF010B | AV57: MULTIPOLYGON (((114.132156113 22.361163731,114.132700114 22.3609980950001,114.132674181 22.360925756,114.132700755 22.360916284,114.132651162 22.360777766,114.132624163 22.360786236,114.132598965 22.360715946,114.132057844 22.3608816060001,114.132082434 22.3609522010001,114.132054838 22.3609616630001,114.132103739 22.361102057,114.132131412 22.3610928150001,114.132156113 22.361163731)))
B58: W50 | C58: 50 Wong Chuk Hang Road | E58: Wong Chuk Hang | F58: =VLOOKUP(Table1[[#This Row],[CBRE sub-markets]],Reference!$A$2:$B$31,2,FALSE) -> Wong Chuk Hang | G58: =VLOOKUP(Table1[[#This Row],[CBRE sub-markets]],Reference!$A$2:$D$31,3,FALSE) -> 5 | H58: =VLOOKUP(Table1[[#This Row],[CBRE sub-markets]],Reference!$A$2:$D$31,4,FALSE) -> Hong Kong Island | I58: 2015 | J58: 2 | K58: =IF(ISNUMBER(Table1[[#This Row],[Qtr]]),CONCATENATE(Table1[[#This Row],[Year]]," Q",Table1[[#This Row],[Qtr]]),CONCATENATE(Table1[[#This Row],[Year]],Table1[[#This Row],[Qtr]])) -> 2015 Q2 | L58: A Office | M58: Completed | N58: 1 | O58: 32 | P58: 27 | Q58: 5225 | R58: 3135 | S58: =IF(AND(ISNUMBER(R58),R58>=15000),"Yes",IF(R58="","Unknown","No")) -> No | V58: =W58/10.764 -> 12756.968 | W58: 137316 | X58: =Y58/10.764 -> 7654.2178 | Y58: 82390 | AA58: =Y58 -> 82390 | AC58: =IF(Table1[[#This Row],[For Sale or For Lease?]]="For Lease",Table1[[#This Row],[Office UFA (Net) (sf)]]-Table1[[#This Row],[Pre-leased space (Usable FA) (sf)]]-Table1[[#This Row],[Pre-sold (Usable FA) (sf)]]-Table1[[#This Row],[Self-use space (Usable FA) (sf)]],0) -> 0 | AD58: =IF(Table1[[#This Row],[For Sale or For Lease?]]="For Sale",Table1[[#This Row],[Office UFA (Net) (sf)]]-Table1[[#This Row],[Pre-leased space (Usable FA) (sf)]]-Table1[[#This Row],[Pre-sold (Usable FA) (sf)]]-Table1[[#This Row],[Self-use space (Usable FA) (sf)]],0) -> 0 | AE58: =IF(Table1[[#This Row],[For Sale or For Lease?]]="Uncertain",Table1[[#This Row],[Office UFA (Net) (sf)]]-Table1[[#This Row],[Pre-leased space (Usable FA) (sf)]]-Table1[[#This Row],[Pre-sold (Usable FA) (sf)]]-Table1[[#This Row],[Self-use space (Usable FA) (sf)]],0) -> 0 | AF58: =1-SUM(Table1[[#This Row],[Space available for lease (Usable FA) (sf)]:[Space available uncertain of use (Usable FA) (sf)]])/Table1[[#This Row],[Office UFA (Net) (sf)]] -> 1 | AG58: Commercial | AH58: OP Issued | AI58: BD Monthly Digest | AJ58: 42125 | AK58: 42199 | AL58: Redevelopment | AM58: Sun Hung Kai Properties | AN58: Private Sector | AO58: For Sale | AP58: Strata-title | AQ58: http://www.50wchr.com/ SHK Annual Report 2012/13: Expected completion in 2014/15 SHK contact: Fillipe Leung: 2828 8660 / Amos Kwok: 2828 5178 / 2827 8111 Aug 2011 (Cynthia): Potential only. No definite plans yet. Inspection made: building unknocekd yet. Aug 2011 (Cynthia): Amos advised development plan is indefinite. | AR58: WCH006
B59: KOHO | C59: 73-75 Hung To Road | E59: Kwun Tong | F59: =VLOOKUP(Table1[[#This Row],[CBRE sub-markets]],Reference!$A$2:$B$31,2,FALSE) -> Kowloon East | G59: =VLOOKUP(Table1[[#This Row],[CBRE sub-markets]],Reference!$A$2:$D$31,3,FALSE) -> 7 | H59: =VLOOKUP(Table1[[#This Row],[CBRE sub-markets]],Reference!$A$2:$D$31,4,FALSE) -> Kowloon | I59: 2015 | J59: 2 | K59: =IF(ISNUMBER(Table1[[#This Row],[Qtr]]),CONCATENATE(Table1[[#This Row],[Year]]," Q",Table1[[#This Row],[Qtr]]),CONCATENATE(Table1[[#This Row],[Year]],Table1[[#This Row],[Qtr]])) -> 2015 Q2 | L59: Revitalization | M59: Completed | N59: 1 | O59: 12 | Q59: =W59/O59 -> 17185.417 | R59: =Q59*0.75 -> 12889.062 | S59: =IF(AND(ISNUMBER(R59),R59>=15000),"Yes",IF(R59="","Unknown","No")) -> No | V59: =W59/10.764 -> 19158.77 | W59: 206225 | X59: =V59*0.75 -> 14369.077 | Y59: =X59*10.764 -> 154668.75 | AC59: =IF(Table1[[#This Row],[For Sale or For Lease?]]="For Lease",Table1[[#This Row],[Office UFA (Net) (sf)]]-Table1[[#This Row],[Pre-leased space (Usable FA) (sf)]]-Table1[[#This Row],[Pre-sold (Usable FA) (sf)]]-Table1[[#This Row],[Self-use space (Usable FA) (sf)]],0) -> 154668.75 | AD59: =IF(Table1[[#This Row],[For Sale or For Lease?]]="For Sale",Table1[[#This Row],[Office UFA (Net) (sf)]]-Table1[[#This Row],[Pre-leased space (Usable FA) (sf)]]-Table1[[#This Row],[Pre-sold (Usable FA) (sf)]]-Table1[[#This Row],[Self-use space (Usable FA) (sf)]],0) -> 0 | AE59: =IF(Table1[[#This Row],[For Sale or For Lease?]]="Uncertain",Table1[[#This Row],[Office UFA (Net) (sf)]]-Table1[[#This Row],[Pre-leased space (Usable FA) (sf)]]-Table1[[#This Row],[Pre-sold (Usable FA) (sf)]]-Table1[[#This Row],[Self-use space (Usable FA) (sf)]],0) -> 0 | AF59: =1-SUM(Table1[[#This Row],[Space available for lease (Usable FA) (sf)]:[Space available uncertain of use (Usable FA) (sf)]])/Table1[[#This Row],[Office UFA (Net) (sf)]] -> 0 | AK59: 41429 | AL59: Revitalization | AM59: Pamfleet | AN59: Private Sector | AO59: For Lease | AP59: Single owner | AR59: KK047B | AV59: MULTIPOLYGON (((114.224443212 22.308866494,114.224149984 22.308640323,114.223854827001 22.308971884,114.224148927 22.309198844,114.224443212 22.308866494)))
B60: The Rays | C60: 71 Hung To Road | E60: Kwun Tong | F60: =VLOOKUP(Table1[[#This Row],[CBRE sub-markets]],Reference!$A$2:$B$31,2,FALSE) -> Kowloon East | G60: =VLOOKUP(Table1[[#This Row],[CBRE sub-markets]],Reference!$A$2:$D$31,3,FALSE) -> 7 | H60: =VLOOKUP(Table1[[#This Row],[CBRE sub-markets]],Reference!$A$2:$D$31,4,FALSE) -> Kowloon | I60: 2015 | J60: 2 | K60: =IF(ISNUMBER(Table1[[#This Row],[Qtr]]),CONCATENATE(Table1[[#This Row],[Year]]," Q",Table1[[#This Row],[Qtr]]),CONCATENATE(Table1[[#This Row],[Year]],Table1[[#This Row],[Qtr]])) -> 2015 Q2 | L60: Revitalization | M60: Completed | N60: 1 | S60: =IF(AND(ISNUMBER(R60),R60>=15000),"Yes",IF(R60="","Unknown","No")) -> Unknown | V60: =W60/10.764 -> 9694.3515 | W60: 104350 | X60: =Y60/10.764 -> 6786.0461 | Y60: =W60*0.7 -> 73045 | AC60: =IF(Table1[[#This Row],[For Sale or For Lease?]]="For Lease",Table1[[#This Row],[Office UFA (Net) (sf)]]-Table1[[#This Row],[Pre-leased space (Usable FA) (sf)]]-Table1[[#This Row],[Pre-sold (Usable FA) (sf)]]-Table1[[#This Row],[Self-use space (Usable FA) (sf)]],0) -> 0 | AD60: =IF(Table1[[#This Row],[For Sale or For Lease?]]="For Sale",Table1[[#This Row],[Office UFA (Net) (sf)]]-Table1[[#This Row],[Pre-leased space (Usable FA) (sf)]]-Table1[[#This Row],[Pre-sold (Usable FA) (sf)]]-Table1[[#This Row],[Self-use space (Usable FA) (sf)]],0) -> 0 | AE60: =IF(Table1[[#This Row],[For Sale or For Lease?]]="Uncertain",Table1[[#This Row],[Office UFA (Net) (sf)]]-Table1[[#This Row],[Pre-leased space (Usable FA) (sf)]]-Table1[[#This Row],[Pre-sold (Usable FA) (sf)]]-Table1[[#This Row],[Self-use space (Usable FA) (sf)]],0) -> 0 | AF60: =1-SUM(Table1[[#This Row],[Space available for lease (Usable FA) (sf)]:[Space available uncertain of use (Usable FA) (sf)]])/Table1[[#This Row],[Office UFA (Net) (sf)]] -> 1 | AL60: Revitalization | AN60: Private Sector | AP60: Single owner | AR60: NS062 | AV60: MULTIPOLYGON (((114.22386678 22.3093727180001,114.224031708 22.309188324,114.223851447 22.309049448,114.223686558 22.309235244,114.22386678 22.3093727180001)))
B61: One Bay East (Citi Tower & Manulife Tower) | C61: J/O Wai Yip Street, Shun Yip Street & Hoi Bun Road | D61: NKIL 6269 | E61: Ngau Tau Kok | F61: =VLOOKUP(Table1[[#This Row],[CBRE sub-markets]],Reference!$A$2:$B$31,2,FALSE) -> Kowloon East | G61: =VLOOKUP(Table1[[#This Row],[CBRE sub-markets]],Reference!$A$2:$D$31,3,FALSE) -> 7 | H61: =VLOOKUP(Table1[[#This Row],[CBRE sub-markets]],Reference!$A$2:$D$31,4,FALSE) -> Kowloon | I61: 2015 | J61: 2 | K61: =IF(ISNUMBER(Table1[[#This Row],[Qtr]]),CONCATENATE(Table1[[#This Row],[Year]]," Q",Table1[[#This Row],[Qtr]]),CONCATENATE(Table1[[#This Row],[Year]],Table1[[#This Row],[Qtr]])) -> 2015 Q2 | L61: A Office | M61: Completed | N61: 2 | O61: 21+2 basement | Q61: =+W61/N61/21 -> 21781.62 | R61: =Table1[[#This Row],[Office UFA (Net) (sf)]]/Table1[[#This Row],[No. of Blocks]]/21 -> 16533.914 | S61: =IF(AND(ISNUMBER(R61),R61>=15000),"Yes",IF(R61="","Unknown","No")) -> Yes | V61: =Table1[[#This Row],[Office GFA (sf)]]/10.7639 -> 84990.39 | W61: 914828.05 | X61: =Table1[[#This Row],[Office UFA (Net) (sf)]]/10.7639 -> 64514.199 | Y61: 694424.39 | AA61: =Y61 -> 694424.39 | AC61: =IF(Table1[[#This Row],[For Sale or For Lease?]]="For Lease",Table1[[#This Row],[Office UFA (Net) (sf)]]-Table1[[#This Row],[Pre-leased space (Usable FA) (sf)]]-Table1[[#This Row],[Pre-sold (Usable FA) (sf)]]-Table1[[#This Row],[Self-use space (Usable FA) (sf)]],0) -> 0 | AD61: =IF(Table1[[#This Row],[For Sale or For Lease?]]="For Sale",Table1[[#This Row],[Office UFA (Net) (sf)]]-Table1[[#This Row],[Pre-leased space (Usable FA) (sf)]]-Table1[[#This Row],[Pre-sold (Usable FA) (sf)]]-Table1[[#This Row],[Self-use space (Usable FA) (sf)]],0) -> 0 | AE61: =IF(Table1[[#This Row],[For Sale or For Lease?]]="Uncertain",Table1[[#This Row],[Office UFA (Net) (sf)]]-Table1[[#This Row],[Pre-leased space (Usable FA) (sf)]]-Table1[[#This Row],[Pre-sold (Usable FA) (sf)]]-Table1[[#This Row],[Self-use space (Usable FA) (sf)]],0) -> 0 | AF61: =1-SUM(Table1[[#This Row],[Space available for lease (Usable FA) (sf)]:[Space available uncertain of use (Usable FA) (sf)]])/Table1[[#This Row],[Office UFA (Net) (sf)]] -> 1 | AG61: Commercial | AH61: OP Issued | AI61: BD Monthly Digest | AJ61: 42125 | AK61: 42144 | AL61: Site | AM61: Wheelock Properties | AN61: Private Sector | AO61: For Sale | AP61: Single owner | AQ61: May 2015: OP received in May according to PjM May 2014: Rod metioned Sep 2015 Apr 2013: Manulife (International) Limited have signed a sale-and-purchase agreement for One Bay East–West Tower at 83 Hoi Bun Road, Kowloon East for HK$4.5 billion (US$577 million), marking the largest single office tower purchase in Kowloon. One Bay East–West Tower will be named Manulife Tower and will serve as the headquarters for Manulife’s Hong Kong operations. Manulife plans to take occupancy in Manulife Tower in 2016. 6 Dec 2012: (JD) - Wharf looking to sell one tower en-bloc and the other tower strata sale. 2 or 3 major occupiers (an insurance company and mainland chinese banks) are already looking to buy one of the towers en-bloc. The site went to Wheelock for 3.53 billion (3,856/buildable sf), near the lower end of market expectations. "We plan to invest 2-2.5 billion for 2 grade A office bldgs with total GFA of 910,000 sf," Wheelock executive director Ricky Wong Kwong-yiu said, adding they will continue to focus more on commercial areas in both Kowloon East and Wong Chuk Hang. The site is designated for non-residential use. 6 tenders were received for the site. | AR61: KK045
B62: 8 Observatory Road | C62: 2-12 Observatory Road | E62: Tsim Sha Tsui | F62: =VLOOKUP(Table1[[#This Row],[CBRE sub-markets]],Reference!$A$2:$B$31,2,FALSE) -> Tsim Sha Tsui | G62: =VLOOKUP(Table1[[#This Row],[CBRE sub-markets]],Reference!$A$2:$D$31,3,FALSE) -> 6 | H62: =VLOOKUP(Table1[[#This Row],[CBRE sub-markets]],Reference!$A$2:$D$31,4,FALSE) -> Kowloon | I62: 2015 | J62: 2 | K62: =IF(ISNUMBER(Table1[[#This Row],[Qtr]]),CONCATENATE(Table1[[#This Row],[Year]]," Q",Table1[[#This Row],[Qtr]]),CONCATENATE(Table1[[#This Row],[Year]],Table1[[#This Row],[Qtr]])) -> 2015 Q2 | L62: A Office | M62: Completed | N62: 1 | O62: 19+3 basement | P62: 9 | Q62: 9634 | R62: =Table1[[#This Row],[Floor Plate (GFA) (sf)]]*0.7 -> 6743.8 | S62: =IF(AND(ISNUMBER(R62),R62>=15000),"Yes",IF(R62="","Unknown","No")) -> No | V62: =W62/10.764 -> 8081.1037 | W62: =9874+9834+9774+9714+9634+9578+9525+9473+9579 -> 86985 | X62: =Y62/10.764 -> 5656.7726 | Y62: =+W62*0.7 -> 60889.5 | Z62: =(9473+9874)*0.7 -> 13542.9 | AC62: =IF(Table1[[#This Row],[For Sale or For Lease?]]="For Lease",Table1[[#This Row],[Office UFA (Net) (sf)]]-Table1[[#This Row],[Pre-leased space (Usable FA) (sf)]]-Table1[[#This Row],[Pre-sold (Usable FA) (sf)]]-Table1[[#This Row],[Self-use space (Usable FA) (sf)]],0) -> 47346.6 | AD62: =IF(Table1[[#This Row],[For Sale or For Lease?]]="For Sale",Table1[[#This Row],[Office UFA (Net) (sf)]]-Table1[[#This Row],[Pre-leased space (Usable FA) (sf)]]-Table1[[#This Row],[Pre-sold (Usable FA) (sf)]]-Table1[[#This Row],[Self-use space (Usable FA) (sf)]],0) -> 0 | AE62: =IF(Table1[[#This Row],[For Sale or For Lease?]]="Uncertain",Table1[[#This Row],[Office UFA (Net) (sf)]]-Table1[[#This Row],[Pre-leased space (Usable FA) (sf)]]-Table1[[#This Row],[Pre-sold (Usable FA) (sf)]]-Table1[[#This Row],[Self-use space (Usable FA) (sf)]],0) -> 0 | AF62: =1-SUM(Table1[[#This Row],[Space available for lease (Usable FA) (sf)]:[Space available uncertain of use (Usable FA) (sf)]])/Table1[[#This Row],[Office UFA (Net) (sf)]] -> 0.22241766 | AG62: Commercial | AH62: OP Issued | AI62: BD Monthly Digest | AJ62: 42156 | AK62: 42237 | AL62: Redevelopment | AM62: Henderson Land & Lai Sun (50:50) | AN62: Private Sector | AO62: For Lease | AP62: Single owner | AQ62: May 2015 (Clinton): An insurance company, guessing mass mutual, is still under negotiations for +80% of the office portion. The price has not been agreed and amount of space has not been confirmed, it is intended for consolidation. 5/F & 7/F has been leased to two Chinese restaurants @ $40psf & mid $40psf respectively. Apr 2015 (Jen): They have reduced the asking rent: 2/F – 9/F for F&B/ Retail tenant asking $43- $45; 10/F and above for Office tenant asking $38, reduced from $44.5; Top floor asking $70. Mar 2015 (Clinton): Spoke with Lai Sun, I was told they are finalising on securing an 8 floors anchor tenant and negotiating with at least 2 retail occupiers. OP in June, final completion in October. Additionally, they have been receiving purchase offers through Henderson. Henderson manage purchase interest and LSD strictly leasing. Apr 2014: 133.72 HK$ Mn Land Premium paid for site. 809 HK$ psf. Jun 2013: foundation work done. Sep 2011: used to be 3 old residential buildings, likely to be a bare site at the moment. OS to investigate and to check it's usage. | AR62: TS035
A63: 中央樓 (redevelopment) | B63: Tower 535 | C63: 535 Jaffe Road | E63: Causeway Bay | F63: =VLOOKUP(Table1[[#This Row],[CBRE sub-markets]],Reference!$A$2:$B$31,2,FALSE) -> Wan Chai & Causeway Bay | G63: =VLOOKUP(Table1[[#This Row],[CBRE sub-markets]],Reference!$A$2:$D$31,3,FALSE) -> 3 | H63: =VLOOKUP(Table1[[#This Row],[CBRE sub-markets]],Reference!$A$2:$D$31,4,FALSE) -> Hong Kong Island | I63: 2015 | J63: 3 | K63: =IF(ISNUMBER(Table1[[#This Row],[Qtr]]),CONCATENATE(Table1[[#This Row],[Year]]," Q",Table1[[#This Row],[Qtr]]),CONCATENATE(Table1[[#This Row],[Year]],Table1[[#This Row],[Qtr]])) -> 2015 Q3 | L63: A Office | M63: Completed | N63: 1 | O63: 24+1 basement | P63: 16 | Q63: 11712 | R63: =Q63*0.7 -> 8198.4 | S63: =IF(AND(ISNUMBER(R63),R63>=15000),"Yes",IF(R63="","Unknown","No")) -> No | V63: =Table1[[#This Row],[Office GFA (sf)]]/10.764 -> 17031.865 | W63: =10034+9329+11712*14 -> 183331 | X63: =Table1[[#This Row],[Office UFA (Net) (sf)]]/10.764 -> 11922.306 | Y63: =Table1[[#This Row],[Office GFA (sf)]]*0.7 -> 128331.7 | Z63: =(10034+9329+11712+5758)*0.7 -> 25783.1 | AC63: =IF(Table1[[#This Row],[For Sale or For Lease?]]="For Lease",Table1[[#This Row],[Office UFA (Net) (sf)]]-Table1[[#This Row],[Pre-leased space (Usable FA) (sf)]]-Table1[[#This Row],[Pre-sold (Usable FA) (sf)]]-Table1[[#This Row],[Self-use space (Usable FA) (sf)]],0) -> 102548.6 | AD63: =IF(Table1[[#This Row],[For Sale or For Lease?]]="For Sale",Table1[[#This Row],[Office UFA (Net) (sf)]]-Table1[[#This Row],[Pre-leased space (Usable FA) (sf)]]-Table1[[#This Row],[Pre-sold (Usable FA) (sf)]]-Table1[[#This Row],[Self-use space (Usable FA) (sf)]],0) -> 0 | AE63: =IF(Table1[[#This Row],[For Sale or For Lease?]]="Uncertain",Table1[[#This Row],[Office UFA (Net) (sf)]]-Table1[[#This Row],[Pre-leased space (Usable FA) (sf)]]-Table1[[#This Row],[Pre-sold (Usable FA) (sf)]]-Table1[[#This Row],[Self-use space (Usable FA) (sf)]],0) -> 0 | AF63: =1-SUM(Table1[[#This Row],[Space available for lease (Usable FA) (sf)]:[Space available uncertain of use (Usable FA) (sf)]])/Table1[[#This Row],[Office UFA (Net) (sf)]] -> 0.20090983 | AG63: Commercial (major revision) | AH63: OP Issued | AI63: BD Monthly Digest | AJ63: 42248 | AK63: 42360 | AL63: Redevelopment | AM63: Phoenix Property Investors | AN63: Private Sector | AO63: For Lease | AP63: Single owner | AQ63: Oct 2014 (David Massbery): • Floor plates of 11,700 sf Gross • 70% efficiency • Office floors located on levels 5-20 (no level 14) • Dedicated office lobby on Level 3 • Retail provided on LG, G, 1st and 2nd floors • Floors 21 and 22 shall be dedicated to F&B • Side core design • 3-metre clear height on office floors • Raised floors of 150mm • 7 passenger lifts – One likely to be dedicated to levels 21 & 22 • OP now due September 2015 Sep 2013: demolished. From Phoenix website (http://www.ppinvestors.com/investments/?data=2): acquired in Jul 2010; Mixed-Use development; Estimated Total Project Costs US$545 million; Estimated GFA 230,000 sf; No. of Floors 23; Target Completion 3Q 2013; American architectural & engineering firm, Skidmore, Owings & Merrill (SOM) has been appointed as the design architect with Ronald LU & Partners serving as the project architect. Jun 2012: (Ian) - At present demolition is underway and property management is reviewing existing plans. My contact does nto expect the building to be completed until 2015+, maybe we put Q1 2016 to be safe. Senior management is away at present therefore no further update until late August/early September when he will contact me again. Sep 2011: Cynthia f/u with Oscar to see if he has a contact at Phoenix. Developer Contact: 2589 3691, to continue to f/u. Sep 2011 (Cynthia): Residential building unknocked yet, currently occupied and one block down from World Trade. Ground floor retail tenants to move out end of this year. SCMP: Central Mansion occupies a site area of about 15,235 square feet. It will be redeveloped into a 230,000 sqft Ginza-style complex with shops, speciality restaurants and a grade A office tower. | AR63: CW018
B64: 41 Heung Yip Road | C64: 41 Heung Yip Road | D64: AIL 354 | E64: Wong Chuk Hang | F64: =VLOOKUP(Table1[[#This Row],[CBRE sub-markets]],Reference!$A$2:$B$31,2,FALSE) -> Wong Chuk Hang | G64: =VLOOKUP(Table1[[#This Row],[CBRE sub-markets]],Reference!$A$2:$D$31,3,FALSE) -> 5 | H64: =VLOOKUP(Table1[[#This Row],[CBRE sub-markets]],Reference!$A$2:$D$31,4,FALSE) -> Hong Kong Island | I64: 2015 | J64: 4 | K64: =IF(ISNUMBER(Table1[[#This Row],[Qtr]]),CONCATENATE(Table1[[#This Row],[Year]]," Q",Table1[[#This Row],[Qtr]]),CONCATENATE(Table1[[#This Row],[Year]],Table1[[#This Row],[Qtr]])) -> 2015 Q4 | L64: A Office | M64: Completed | N64: 1 | O64: 33+4 basement | P64: 10 | Q64: 11744 | R64: =Table1[[#This Row],[Floor Plate (GFA) (sf)]]*0.65 -> 7633.6 | S64: =IF(AND(ISNUMBER(R64),R64>=15000),"Yes",IF(R64="","Unknown","No")) -> No | V64: =Table1[[#This Row],[Office GFA (sf)]]/10.7639 -> 30549.522 | W64: =28*Table1[[#This Row],[Floor Plate (GFA) (sf)]] -> 328832 | X64: =Table1[[#This Row],[Office UFA (Net) (sf)]]/10.7639 -> 19857.189 | Y64: =Table1[[#This Row],[Office GFA (sf)]]*0.65 -> 213740.8 | AC64: =IF(Table1[[#This Row],[For Sale or For Lease?]]="For Lease",Table1[[#This Row],[Office UFA (Net) (sf)]]-Table1[[#This Row],[Pre-leased space (Usable FA) (sf)]]-Table1[[#This Row],[Pre-sold (Usable FA) (sf)]]-Table1[[#This Row],[Self-use space (Usable FA) (sf)]],0) -> 213740.8 | AD64: =IF(Table1[[#This Row],[For Sale or For Lease?]]="For Sale",Table1[[#This Row],[Office UFA (Net) (sf)]]-Table1[[#This Row],[Pre-leased space (Usable FA) (sf)]]-Table1[[#This Row],[Pre-sold (Usable FA) (sf)]]-Table1[[#This Row],[Self-use space (Usable FA) (sf)]],0) -> 0 | AE64: =IF(Table1[[#This Row],[For Sale or For Lease?]]="Uncertain",Table1[[#This Row],[Office UFA (Net) (sf)]]-Table1[[#This Row],[Pre-leased space (Usable FA) (sf)]]-Table1[[#This Row],[Pre-sold (Usable FA) (sf)]]-Table1[[#This Row],[Self-use space (Usable FA) (sf)]],0) -> 0 | AF64: =1-SUM(Table1[[#This Row],[Space available for lease (Usable FA) (sf)]:[Space available uncertain of use (Usable FA) (sf)]])/Table1[[#This Row],[Office UFA (Net) (sf)]] -> 0 | AG64: Commercial | AH64: OP Issued | AI64: BD Monthly Digest | AJ64: 42339 | AK64: 42419 | AL64: Redevelopment | AM64: L'Avenue International Holdings (Angela Leong) | AN64: Private Sector | AO64: For Lease | AP64: Single owner | AQ64: Feb 2016 (Roy): looks to be more or less complete May 2015 (Jerry): brochure saved in: I:\CBRE Research\Hong Kong\02. Databases\Office Database\Supply info\41 Heung Yip Road Angela Leong bought the building from Cheung Kong. July 2013: Office, for sale according to: http://opengov.jmsc.hku.hk/2013/07/02/office-booms-in-wong-chuk-hang/ 2012 AR: Commercial development, expected completion Mar 2015 Hotel or Office??? | AR64: WCH009
A65: 嘉尚匯 | B65: Vertical Sq | C65: 28 Heung Yip Road | E65: Wong Chuk Hang | F65: =VLOOKUP(Table1[[#This Row],[CBRE sub-markets]],Reference!$A$2:$B$31,2,FALSE) -> Wong Chuk Hang | G65: =VLOOKUP(Table1[[#This Row],[CBRE sub-markets]],Reference!$A$2:$D$31,3,FALSE) -> 5 | H65: =VLOOKUP(Table1[[#This Row],[CBRE sub-markets]],Reference!$A$2:$D$31,4,FALSE) -> Hong Kong Island | I65: 2015 | J65: 4 | K65: =IF(ISNUMBER(Table1[[#This Row],[Qtr]]),CONCATENATE(Table1[[#This Row],[Year]]," Q",Table1[[#This Row],[Qtr]]),CONCATENATE(Table1[[#This Row],[Year]],Table1[[#This Row],[Qtr]])) -> 2015 Q4 | L65: A Office | M65: Completed | N65: 1 | O65: 27+5 carpark | P65: 26 | Q65: 7050 | R65: =Q65*0.75 -> 5287.5 | S65: =IF(AND(ISNUMBER(R65),R65>=15000),"Yes",IF(R65="","Unknown","No")) -> No | V65: =W65/10.7639 -> 17029.144 | W65: =Table1[[#This Row],[Floor Plate (GFA) (sf)]]*Table1[[#This Row],[No. of Storeys for Office]] -> 183300 | X65: =Y65/10.764 -> 12771.739 | Y65: =+W65*0.75 -> 137475 | AC65: =IF(Table1[[#This Row],[For Sale or For Lease?]]="For Lease",Table1[[#This Row],[Office UFA (Net) (sf)]]-Table1[[#This Row],[Pre-leased space (Usable FA) (sf)]]-Table1[[#This Row],[Pre-sold (Usable FA) (sf)]]-Table1[[#This Row],[Self-use space (Usable FA) (sf)]],0) -> 137475 | AD65: =IF(Table1[[#This Row],[For Sale or For Lease?]]="For Sale",Table1[[#This Row],[Office UFA (Net) (sf)]]-Table1[[#This Row],[Pre-leased space (Usable FA) (sf)]]-Table1[[#This Row],[Pre-sold (Usable FA) (sf)]]-Table1[[#This Row],[Self-use space (Usable FA) (sf)]],0) -> 0 | AE65: =IF(Table1[[#This Row],[For Sale or For Lease?]]="Uncertain",Table1[[#This Row],[Office UFA (Net) (sf)]]-Table1[[#This Row],[Pre-leased space (Usable FA) (sf)]]-Table1[[#This Row],[Pre-sold (Usable FA) (sf)]]-Table1[[#This Row],[Self-use space (Usable FA) (sf)]],0) -> 0 | AF65: =1-SUM(Table1[[#This Row],[Space available for lease (Usable FA) (sf)]:[Space available uncertain of use (Usable FA) (sf)]])/Table1[[#This Row],[Office UFA (Net) (sf)]] -> 0 | AG65: Commercial | AH65: OP Issued | AI65: BD Monthly Digest | AJ65: 42309 | AK65: 42369 | AL65: Redevelopment | AM65: K Wah Properties | AN65: Private Sector | AO65: For Lease | AP65: Single owner | AQ65: May 2015 (HKET): aiming $18 psf. Dec 2014: Kerry Wong • Completion: Q1 2016 • Total GFA: 190,000 sfg • Typical floor: 7,500 sfg • Use: office • Accessibility: 2 minutes to MTR • Rental: to be confirmed • Specifications: not high Grade A, will be general June 2014: Premium paid 30.93 mn HKD. Nov 2012: demolition on the existing industrial building issued in November 2012. Aug 2011 (Cynthia): Matthew Hon (Industrial) has good contact with landlord, no plans to redevelop yet, just submit plans to save future waiver costs. Inspection made: building unknocked yet. | AR65: WCH008
B66: Kings Wing Plaza 1 | C66: J/O On Kwan Street & On Muk Street | D66: STTL 412 | E66: Sha Tin | F66: =VLOOKUP(Table1[[#This Row],[CBRE sub-markets]],Reference!$A$2:$B$31,2,FALSE) -> New Territories | G66: =VLOOKUP(Table1[[#This Row],[CBRE sub-markets]],Reference!$A$2:$D$31,3,FALSE) -> 9 | H66: =VLOOKUP(Table1[[#This Row],[CBRE sub-markets]],Reference!$A$2:$D$31,4,FALSE) -> New Territories | I66: 2015 | J66: 4 | K66: =IF(ISNUMBER(Table1[[#This Row],[Qtr]]),CONCATENATE(Table1[[#This Row],[Year]]," Q",Table1[[#This Row],[Qtr]]),CONCATENATE(Table1[[#This Row],[Year]],Table1[[#This Row],[Qtr]])) -> 2015 Q4 | L66: A Office | M66: Completed | N66: 1 | O66: 20+1 basement | P66: 16 | Q66: =1728+759+853+1303+801+757+734+1299+775+876+1722+965+100+1054 -> 13726 | R66: =1175+516+580+886+545+515+499+883+527+596+1171+656+680+717 -> 9946 | S66: =IF(AND(ISNUMBER(R66),R66>=15000),"Yes",IF(R66="","Unknown","No")) -> No | V66: =Table1[[#This Row],[Office GFA (sf)]]/10.764 -> 21938.592 | W66: =(1728+759+853+1303+801+757+734+1299+775+876+1722+965+1000+1054)+(6860+1419+1303+801+757+734+1299+1453)+(1728+759+853+1303+801+757+734+1299+775+876+1722+965+1000+1054)*4+(1728+759+853+1306+801+757+734+1299+775+876+1725+965+1000+1054)+(1728+759+853+1315+801+757+734+1299+775+876+1734+965+1000+1054)+(1728+762+856+1329+797+757+729+1299+778+879+1749+962+1000+1051)+(1728+762+856+1349+797+757+729+1299+778+879+1768+962+1000+1051)+(1728+762+856+1374+799+757+729+1299+778+879+1793+962+1000+1051)+(1728+762+856+1397+806+757+729+1299+778+879+1816+969+1000+1051)+(1728+762+856+1419+818+757+729+1299+778+879+1838+981+1000+1051)+(1728+762+856+1443+832+762+729+1299+778+879+1862+994+1006+1051)+(1728+762+856+1466+846+772+729+1299+778+879+1885+1006+1016+1051)+(1728+762+856+1488+860+785+731+1299+778+879+1907+1019+1029+1054) -> 236147 | X66: 26584 | Y66: =(1175+516+580+886+545+515+499+883+527+896+1171+656+680+717)+(5072+965+886+545+515+499+883+988)+(1175+516+580+886+545+515+499+883+527+596+1171+656+680+717)*4+(1175+516+580+888+545+515+499+883+527+596+1173+656+680+717)+(1175+516+580+894+545+515+499+883+527+596+1179+656+680+717)+(1175+518+582+904+542+515+496+883+529+598+1189+654+680+715)+(1175+518+582+917+542+515+496+883+529+598+1202+654+680+715)+(1175+518+582+934+543+515+496+883+529+598+1219+654+680+715)+(1175+518+582+950+548+515+496+883+529+598+1235+659+680+715)+(1175+518+582+965+556+515+496+883+529+598+1250+667+680+715)+(1175+518+582+981+556+518+496+883+529+598+1266+676+9684+715)+(1175+518+582+997+575+525+496+883+529+598+1282+684+691+715)+(1175+518+582+1012+585+534+497+883+529+598+1297+693+700+717) -> 170281 | AA66: =Table1[[#This Row],[Office UFA (Net) (sf)]]-(556+515+496+598+950+518+904+894+516) -> 164334 | AC66: =IF(Table1[[#This Row],[For Sale or For Lease?]]="For Lease",Table1[[#This Row],[Office UFA (Net) (sf)]]-Table1[[#This Row],[Pre-leased space (Usable FA) (sf)]]-Table1[[#This Row],[Pre-sold (Usable FA) (sf)]]-Table1[[#This Row],[Self-use space (Usable FA) (sf)]],0) -> 0 | AD66: =IF(Table1[[#This Row],[For Sale or For Lease?]]="For Sale",Table1[[#This Row],[Office UFA (Net) (sf)]]-Table1[[#This Row],[Pre-leased space (Usable FA) (sf)]]-Table1[[#This Row],[Pre-sold (Usable FA) (sf)]]-Table1[[#This Row],[Self-use space (Usable FA) (sf)]],0) -> 5947 | AE66: =IF(Table1[[#This Row],[For Sale or For Lease?]]="Uncertain",Table1[[#This Row],[Office UFA (Net) (sf)]]-Table1[[#This Row],[Pre-leased space (Usable FA) (sf)]]-Table1[[#This Row],[Pre-sold (Usable FA) (sf)]]-Table1[[#This Row],[Self-use space (Usable FA) (sf)]],0) -> 0 | AF66: =1-SUM(Table1[[#This Row],[Space available for lease (Usable FA) (sf)]:[Space available uncertain of use (Usable FA) (sf)]])/Table1[[#This Row],[Office UFA (Net) (sf)]] -> 0.96507538 | AG66: Commercial (major revision) | AH66: OP Issued | AI66: BD Monthly Digest | AJ66: 42278 | AK66: 42360 | AL66: Site | AM66: Billion Development | AN66: Private Sector | AO66: For Sale | AP66: Strata-title | AQ66: Dec 2014: applied for pre-sale consent Sep 2014 (HKET): asking price at around $6,800/sf, minimum $6Mil; a Chinese-HK food company reserved retail and office for $720Mil (refer to Investment Database) Dec 2012 (Sing Tao): Billion will build an office tower which has two to three floors of retail spaces and more than ten office space. Jun 2012: Retail | AR66: ST006
B67: Shanghai Commercial Bank Tower | C67: 10-12 Queen's Road Central | E67: Central | F67: =VLOOKUP(Table1[[#This Row],[CBRE sub-markets]],Reference!$A$2:$B$31,2,FALSE) -> Central | G67: =VLOOKUP(Table1[[#This Row],[CBRE sub-markets]],Reference!$A$2:$D$31,3,FALSE) -> 1 | H67: =VLOOKUP(Table1[[#This Row],[CBRE sub-markets]],Reference!$A$2:$D$31,4,FALSE) -> Hong Kong Island | I67: 2016 | J67: 1 | K67: =IF(ISNUMBER(Table1[[#This Row],[Qtr]]),CONCATENATE(Table1[[#This Row],[Year]]," Q",Table1[[#This Row],[Qtr]]),CONCATENATE(Table1[[#This Row],[Year]],Table1[[#This Row],[Qtr]])) -> 2016 Q1 | L67: A Office | M67: Completed | N67: 1 | O67: 27+1 basement | P67: 21 | Q67: 4235 | R67: =Table1[[#This Row],[Floor Plate (GFA) (sf)]]*0.7 -> 2964.5 | S67: =IF(AND(ISNUMBER(R67),R67>=15000),"Yes",IF(R67="","Unknown","No")) -> No | V67: =Table1[[#This Row],[Office GFA (sf)]]/10.764 -> 8212.932 | W67: =4100+4235*14+4275+4148*4+4147 -> 88404 | X67: =Table1[[#This Row],[Office UFA (Net) (sf)]]/10.764 -> 5749.0524 | Y67: =Table1[[#This Row],[Office GFA (sf)]]*0.7 -> 61882.8 | Z67: =2965*4+5929+2904*2 -> 23597 | AB67: =2870+2964*6+2992+2903+2902 -> 29451 | AC67: =IF(Table1[[#This Row],[For Sale or For Lease?]]="For Lease",Table1[[#This Row],[Office UFA (Net) (sf)]]-Table1[[#This Row],[Pre-leased space (Usable FA) (sf)]]-Table1[[#This Row],[Pre-sold (Usable FA) (sf)]]-Table1[[#This Row],[Self-use space (Usable FA) (sf)]],0) -> 8834.8 | AD67: =IF(Table1[[#This Row],[For Sale or For Lease?]]="For Sale",Table1[[#This Row],[Office UFA (Net) (sf)]]-Table1[[#This Row],[Pre-leased space (Usable FA) (sf)]]-Table1[[#This Row],[Pre-sold (Usable FA) (sf)]]-Table1[[#This Row],[Self-use space (Usable FA) (sf)]],0) -> 0 | AE67: =IF(Table1[[#This Row],[For Sale or For Lease?]]="Uncertain",Table1[[#This Row],[Office UFA (Net) (sf)]]-Table1[[#This Row],[Pre-leased space (Usable FA) (sf)]]-Table1[[#This Row],[Pre-sold (Usable FA) (sf)]]-Table1[[#This Row],[Self-use space (Usable FA) (sf)]],0) -> 0 | AF67: =1-SUM(Table1[[#This Row],[Space available for lease (Usable FA) (sf)]:[Space available uncertain of use (Usable FA) (sf)]])/Table1[[#This Row],[Office UFA (Net) (sf)]] -> 0.85723335 | AG67: Commercial | AH67: OP Issued | AI67: BD Monthly Digest | AJ67: 42401 | AK67: 42480 | AL67: Redevelopment | AM67: Shanghai Commercial Bank Ltd | AN67: Private Sector | AO67: For Lease | AP67: Single owner | AQ67: Feb 2016 (Roy): almost complete Jun 2015: Curtain wall almost complete; internal base fitout underway Feb 2013 (Roy): bare site Mar 2012 (Roy): Retail Space includes Basement, G/F & 1/F (all together around 20,000sf) 2/F - Bank Hall & Main lobby 3-13/F & 27-29/F reserved by the bank 15/F - 26/F office floor (approx. 5,000sf per floor); 4 passenger lifts + 1 disable lift; Architect: ROCCO; Target completion date: June 2015 Mar 2012 (Roy): Demolition issued January 2012 Contact: 2818 0281 Sep 2011 (Cynthia): Ian advised This is being redeveloped for their own use however there may be a little amount of space available for lease. Sep 2011 (Cynthia): Building is vacant. Workers onsite currently defitting interior, landlord will have final inspection in 2 mths time and then start knocking down. Located opp Landmark (Gucci side) 12 QRC bought in 2008 for 1.38B Plans to demolish the bldgs in 2011 and completion will be 2013-14 | AR67: CC046
B68: One HarbourGate | C68: J/O Hung Luen Road and Kin Wan Street | D68: KIL 11111 | E68: Hung Hom | F68: =VLOOKUP(Table1[[#This Row],[CBRE sub-markets]],Reference!$A$2:$B$31,2,FALSE) -> Kowloon Others | G68: =VLOOKUP(Table1[[#This Row],[CBRE sub-markets]],Reference!$A$2:$D$31,3,FALSE) -> 8 | H68: =VLOOKUP(Table1[[#This Row],[CBRE sub-markets]],Reference!$A$2:$D$31,4,FALSE) -> Kowloon | I68: 2016 | J68: 1 | K68: =IF(ISNUMBER(Table1[[#This Row],[Qtr]]),CONCATENATE(Table1[[#This Row],[Year]]," Q",Table1[[#This Row],[Qtr]]),CONCATENATE(Table1[[#This Row],[Year]],Table1[[#This Row],[Qtr]])) -> 2016 Q1 | L68: A Office | M68: Completed | N68: 2 | O68: 2/15+2 basement | P68: 14 | Q68: =(24000+17000)/2 -> 20500 | R68: =Q68*(Y68/W68) -> 14965 | S68: =IF(AND(ISNUMBER(R68),R68>=15000),"Yes",IF(R68="","Unknown","No")) -> No | V68: =W68/10.764 -> 56856.187 | W68: =357000+255000 -> 612000 | X68: =Y68/10.764 -> 41505.017 | Y68: =W68*0.73 -> 446760 | AA68: =357000*0.68 -> 242760 | AC68: =IF(Table1[[#This Row],[For Sale or For Lease?]]="For Lease",Table1[[#This Row],[Office UFA (Net) (sf)]]-Table1[[#This Row],[Pre-leased space (Usable FA) (sf)]]-Table1[[#This Row],[Pre-sold (Usable FA) (sf)]]-Table1[[#This Row],[Self-use space (Usable FA) (sf)]],0) -> 0 | AD68: =IF(Table1[[#This Row],[For Sale or For Lease?]]="For Sale",Table1[[#This Row],[Office UFA (Net) (sf)]]-Table1[[#This Row],[Pre-leased space (Usable FA) (sf)]]-Table1[[#This Row],[Pre-sold (Usable FA) (sf)]]-Table1[[#This Row],[Self-use space (Usable FA) (sf)]],0) -> 204000 | AE68: =IF(Table1[[#This Row],[For Sale or For Lease?]]="Uncertain",Table1[[#This Row],[Office UFA (Net) (sf)]]-Table1[[#This Row],[Pre-leased space (Usable FA) (sf)]]-Table1[[#This Row],[Pre-sold (Usable FA) (sf)]]-Table1[[#This Row],[Self-use space (Usable FA) (sf)]],0) -> 0 | AF68: =1-SUM(Table1[[#This Row],[Space available for lease (Usable FA) (sf)]:[Space available uncertain of use (Usable FA) (sf)]])/Table1[[#This Row],[Office UFA (Net) (sf)]] -> 0.543379 | AG68: Commercial | AH68: OP Issued | AI68: BD Monthly Digest | AJ68: 42370 | AK68: 42446 | AL68: Site | AM68: Wheelock Properties & China Life (West Tower) | AN68: Private Sector | AO68: For Sale | AP68: Single owner | AQ68: Apr 2014 (2014 Annual Report): Presale is planned in 2015. Jun 2013: more site investigations to be done due to its location along the waterfront. Aug 2012 (JD): plan to finish Hoi Bun Road project first Sep 2011: Sam (OS) - Wheelocks plans for Strata sales, not for long-term hold. 5Aug2011: Wheelock outbid 4 others to win this site, 20% more than most analysts expected, at a price of nearly 6,900 psf, analysts forecasted a price of 2.9-3.5 billion, between 4,915-5,932 psf. The 147,499 sf site has been awarded on a 50-year land grant for a premium of 4.028 billion. The max. permitted GFA is 589,996 sf, so the average cost of the site is 6,827 psf. | AR68: HH005
B69: 3 Tai Yau Street (萬迪廣場) | C69: 3 Tai Yau Street | D69: NKIL 4899 | E69: San Po Kong | F69: =VLOOKUP(Table1[[#This Row],[CBRE sub-markets]],Reference!$A$2:$B$31,2,FALSE) -> Kowloon Others | G69: =VLOOKUP(Table1[[#This Row],[CBRE sub-markets]],Reference!$A$2:$D$31,3,FALSE) -> 8 | H69: =VLOOKUP(Table1[[#This Row],[CBRE sub-markets]],Reference!$A$2:$D$31,4,FALSE) -> Kowloon | I69: 2016 | J69: 2 | K69: =IF(ISNUMBER(Table1[[#This Row],[Qtr]]),CONCATENATE(Table1[[#This Row],[Year]]," Q",Table1[[#This Row],[Qtr]]),CONCATENATE(Table1[[#This Row],[Year]],Table1[[#This Row],[Qtr]])) -> 2016 Q2 | L69: A Office | M69: Completed | N69: 1 | O69: 28 | P69: 16 | Q69: 18923 | R69: 12889 | S69: =IF(AND(ISNUMBER(R69),R69>=15000),"Yes",IF(R69="","Unknown","No")) -> No | V69: =W69/10.764 -> 28278.428 | W69: 304389 | X69: =Y69/10.764 -> 19404.496 | Y69: 208870 | AA69: =Table1[[#This Row],[Office UFA (Net) (sf)]] -> 208870 | AC69: =IF(Table1[[#This Row],[For Sale or For Lease?]]="For Lease",Table1[[#This Row],[Office UFA (Net) (sf)]]-Table1[[#This Row],[Pre-leased space (Usable FA) (sf)]]-Table1[[#This Row],[Pre-sold (Usable FA) (sf)]]-Table1[[#This Row],[Self-use space (Usable FA) (sf)]],0) -> 0 | AD69: =IF(Table1[[#This Row],[For Sale or For Lease?]]="For Sale",Table1[[#This Row],[Office UFA (Net) (sf)]]-Table1[[#This Row],[Pre-leased space (Usable FA) (sf)]]-Table1[[#This Row],[Pre-sold (Usable FA) (sf)]]-Table1[[#This Row],[Self-use space (Usable FA) (sf)]],0) -> 0 | AE69: =IF(Table1[[#This Row],[For Sale or For Lease?]]="Uncertain",Table1[[#This Row],[Office UFA (Net) (sf)]]-Table1[[#This Row],[Pre-leased space (Usable FA) (sf)]]-Table1[[#This Row],[Pre-sold (Usable FA) (sf)]]-Table1[[#This Row],[Self-use space (Usable FA) (sf)]],0) -> 0 | AF69: =1-SUM(Table1[[#This Row],[Space available for lease (Usable FA) (sf)]:[Space available uncertain of use (Usable FA) (sf)]])/Table1[[#This Row],[Office UFA (Net) (sf)]] -> 1 | AG69: Commercial | AH69: OP Issued | AI69: BD Monthly Digest | AJ69: 42461 | AK69: 41206 | AL69: Redevelopment | AM69: Billion Development | AN69: Private Sector | AO69: For Sale | AP69: Strata-title | AQ69: Feb 2016 (Roy): more or less complete Dec 2014: applied for pre-sale consent Jun 2013: building demolition and land premium paid. Dec 2012: demolition issued in December. Land premium agreed at $15,000 psf. Aug 2012 (JD): have not agreed modification, building still exists and may need to push date back at end of the year. Feb 2012: Land premium agreed, tenants to move out at the end of the year and demolition to start next year 27Sep2011: land premium was approved at $1,800 psf, and Billion will appeal Sep 2011: Billiong pruchased from Windsor but may keep lease or put redevelopment plans on hold. Kln OS suggested and newspaper/ Source: Ming Pao http://finance.sina.com/bg/chinamkt/mingpao/20100611/115275849.html | AR69: SP003
B70: Kings Wing Plaza 2 | C70: 1 On Kwan Street | D70: STTL 463 | E70: Sha Tin | F70: =VLOOKUP(Table1[[#This Row],[CBRE sub-markets]],Reference!$A$2:$B$31,2,FALSE) -> New Territories | G70: =VLOOKUP(Table1[[#This Row],[CBRE sub-markets]],Reference!$A$2:$D$31,3,FALSE) -> 9 | H70: =VLOOKUP(Table1[[#This Row],[CBRE sub-markets]],Reference!$A$2:$D$31,4,FALSE) -> New Territories | I70: 2016 | J70: 2 | K70: =IF(ISNUMBER(Table1[[#This Row],[Qtr]]),CONCATENATE(Table1[[#This Row],[Year]]," Q",Table1[[#This Row],[Qtr]]),CONCATENATE(Table1[[#This Row],[Year]],Table1[[#This Row],[Qtr]])) -> 2016 Q2 | L70: A Office | M70: Completed | N70: 1 | O70: 24+1 basement | P70: 20 | Q70: =39980.8*10.7639/25 -> 17213.973 | R70: =Q70*(Y70/W70) -> 11822.535 | S70: =IF(AND(ISNUMBER(R70),R70>=15000),"Yes",IF(R70="","Unknown","No")) -> No | V70: =Table1[[#This Row],[Office GFA (sf)]]/10.764 -> 29144.556 | W70: =(868+1437+726+832+747+694+1470+900+900+1560+729+790+882+766+1524+865)*11+15690+(868+1438+725+832+747+710+1454+894+894+1541+749+790+882+765+1525+865)*6+(1072+1438+725+832+747+710+1454+1096+7605)*2 -> 313712 | X70: =Table1[[#This Row],[Office UFA (Net) (sf)]]/10.764 -> 20016.444 | Y70: =(590+977+494+566+508+472+1000+612+612+1061+496+537+600+521+1036+588)*11+11865+(590+978+493+566+508+483+989+608+608+1048+509+537+600+520+1037+588)*6+(729+978+493+566+508+483+989+745+5634)*2 -> 215457 | AA70: =Table1[[#This Row],[Office UFA (Net) (sf)]]-(590+989+520+588+1000+1061+590+977+1000*4+612*5+612*3+1061*3+1036*4+588*2) -> 191743 | AC70: =IF(Table1[[#This Row],[For Sale or For Lease?]]="For Lease",Table1[[#This Row],[Office UFA (Net) (sf)]]-Table1[[#This Row],[Pre-leased space (Usable FA) (sf)]]-Table1[[#This Row],[Pre-sold (Usable FA) (sf)]]-Table1[[#This Row],[Self-use space (Usable FA) (sf)]],0) -> 0 | AD70: =IF(Table1[[#This Row],[For Sale or For Lease?]]="For Sale",Table1[[#This Row],[Office UFA (Net) (sf)]]-Table1[[#This Row],[Pre-leased space (Usable FA) (sf)]]-Table1[[#This Row],[Pre-sold (Usable FA) (sf)]]-Table1[[#This Row],[Self-use space (Usable FA) (sf)]],0) -> 23714 | AE70: =IF(Table1[[#This Row],[For Sale or For Lease?]]="Uncertain",Table1[[#This Row],[Office UFA (Net) (sf)]]-Table1[[#This Row],[Pre-leased space (Usable FA) (sf)]]-Table1[[#This Row],[Pre-sold (Usable FA) (sf)]]-Table1[[#This Row],[Self-use space (Usable FA) (sf)]],0) -> 0 | AF70: =1-SUM(Table1[[#This Row],[Space available for lease (Usable FA) (sf)]:[Space available uncertain of use (Usable FA) (sf)]])/Table1[[#This Row],[Office UFA (Net) (sf)]] -> 0.88993627 | AG70: Commercial | AH70: OP Issued | AI70: BD Monthly Digest | AJ70: 41883 | AK70: 41982 | AL70: Site | AM70: Billion Development | AN70: Private Sector | AO70: For Sale | AP70: Strata-title | AQ70: Jul 2016: OP issued in May 2016 Dec 2014: applied for pre-sale consent Dec 2012 (Sing Tao): Billion will build an office tower which has two to three floors of retail spaces and more than ten office space. Billion was the tender submitted for the site, for HK$828 million, HK$1,942 psf; price was below the low end of the market estimate of HK$830 million. | AR70: ST007
B71: Chinachem Central I | C71: 22 & 22A Des Voeux Road Central | E71: Central | F71: =VLOOKUP(Table1[[#This Row],[CBRE sub-markets]],Reference!$A$2:$B$31,2,FALSE) -> Central | G71: =VLOOKUP(Table1[[#This Row],[CBRE sub-markets]],Reference!$A$2:$D$31,3,FALSE) -> 1 | H71: =VLOOKUP(Table1[[#This Row],[CBRE sub-markets]],Reference!$A$2:$D$31,4,FALSE) -> Hong Kong Island | I71: 2016 | J71: 4 | K71: =IF(ISNUMBER(Table1[[#This Row],[Qtr]]),CONCATENATE(Table1[[#This Row],[Year]]," Q",Table1[[#This Row],[Qtr]]),CONCATENATE(Table1[[#This Row],[Year]],Table1[[#This Row],[Qtr]])) -> 2016 Q4 | L71: B Office | M71: Completed | N71: 1 | O71: 26+1 basement | Q71: 3475 | R71: =Q71*(Y71/W71) -> 1542.3556 | S71: =IF(AND(ISNUMBER(R71),R71>=15000),"Yes",IF(R71="","Unknown","No")) -> No | V71: 7578.8 | W71: =IF(ISBLANK(V71),"",V71*10.764) -> 81578.203 | X71: 3363.8 | Y71: =IF(ISBLANK(X71),"",X71*10.764) -> 36207.943 | AC71: =IF(Table1[[#This Row],[For Sale or For Lease?]]="For Lease",Table1[[#This Row],[Office UFA (Net) (sf)]]-Table1[[#This Row],[Pre-leased space (Usable FA) (sf)]]-Table1[[#This Row],[Pre-sold (Usable FA) (sf)]]-Table1[[#This Row],[Self-use space (Usable FA) (sf)]],0) -> 36207.943 | AD71: =IF(Table1[[#This Row],[For Sale or For Lease?]]="For Sale",Table1[[#This Row],[Office UFA (Net) (sf)]]-Table1[[#This Row],[Pre-leased space (Usable FA) (sf)]]-Table1[[#This Row],[Pre-sold (Usable FA) (sf)]]-Table1[[#This Row],[Self-use space (Usable FA) (sf)]],0) -> 0 | AE71: =IF(Table1[[#This Row],[For Sale or For Lease?]]="Uncertain",Table1[[#This Row],[Office UFA (Net) (sf)]]-Table1[[#This Row],[Pre-leased space (Usable FA) (sf)]]-Table1[[#This Row],[Pre-sold (Usable FA) (sf)]]-Table1[[#This Row],[Self-use space (Usable FA) (sf)]],0) -> 0 | AF71: =1-SUM(Table1[[#This Row],[Space available for lease (Usable FA) (sf)]:[Space available uncertain of use (Usable FA) (sf)]])/Table1[[#This Row],[Office UFA (Net) (sf)]] -> 0 | AG71: Commercial | AH71: OP Issued | AI71: BD Monthly Digest | AJ71: 42675 | AK71: 43282 | AL71: Redevelopment | AM71: Chinachem | AN71: Private Sector | AO71: For Lease | AP71: Single owner | AQ71: 10 Jan 2014: Ian met with Chinachem CEO & COO. There will be two office buildings 22 & 26 Des Voeux Rd Central. with Retail Podium Aug 2013 (Ian & Alan): Chinachem confirmed this will be retail. Feb 2013: Chinachame: "The two Wing On buildings “frame” the Liu Chong Hing Bank building. Long ago, there were talks between Mrs Wang and the Liu’s about cooperating to redevelop the whole site, but that was before the Bank built its own new building. Its CEO, Mr Liu, told me recently that this was because he couldn’t come to terms with Mrs Wang" Feb 2013 (Roy): bare site Jun 2012 (Ian): Demolished, currently clear site to ground level, no sign of any work at present. This site and 26 DVRC site are separated by Chon Hing Bank Centre. Sep 2011 (Cynthia): CN asked Oscar if he knows anyone well at Chinachem that he could introduce. Aug 2011 (Cynthia): Existing building is vacant, commenced knocking down. Will be completed around Q2, 2015. Demolition issued May 2011. May2011: Demolition issued Contact: Doug Chiu 2368 4968 SCMP 31Oct09: Asian Hse, covering 21, 000sf of site area, will have a GFA of about 300,000 sf. Ng said the est redevelopment cost would be >HK$1 Bn [In the same article also mentioned the redevelopment of Wing On Life Bldg (22 Connaught Rd C) GFA will be increased from 50k sf to >80k sf, redev cost ~HK$500 Mn] /Right behing LHT Tower | AR71: NS067 | AV71: MULTIPOLYGON (((114.156940949 22.283695181,114.156848526 22.2838377040001,114.156989033 22.283933959,114.157112098 22.283780044,114.156957901 22.2836740600001,114.156940949 22.283695181)))
B72: Big Star Centre | C72: 8 Wang Kwong Road | D72: NKIL 5866 | E72: Kowloon Bay | F72: =VLOOKUP(Table1[[#This Row],[CBRE sub-markets]],Reference!$A$2:$B$31,2,FALSE) -> Kowloon East | G72: =VLOOKUP(Table1[[#This Row],[CBRE sub-markets]],Reference!$A$2:$D$31,3,FALSE) -> 7 | H72: =VLOOKUP(Table1[[#This Row],[CBRE sub-markets]],Reference!$A$2:$D$31,4,FALSE) -> Kowloon | I72: 2016 | J72: 4 | K72: =IF(ISNUMBER(Table1[[#This Row],[Qtr]]),CONCATENATE(Table1[[#This Row],[Year]]," Q",Table1[[#This Row],[Qtr]]),CONCATENATE(Table1[[#This Row],[Year]],Table1[[#This Row],[Qtr]])) -> 2016 Q4 | L72: Revitalization | M72: Completed | N72: 1 | Q72: 18754 | R72: =Q72*0.75 -> 14065.5 | S72: =IF(AND(ISNUMBER(R72),R72>=15000),"Yes",IF(R72="","Unknown","No")) -> No | V72: =W72/10.764 -> 16299.424 | W72: 175447 | X72: =Y72/10.764 -> 12224.568 | Y72: =W72*0.75 -> 131585.25 | AC72: =IF(Table1[[#This Row],[For Sale or For Lease?]]="For Lease",Table1[[#This Row],[Office UFA (Net) (sf)]]-Table1[[#This Row],[Pre-leased space (Usable FA) (sf)]]-Table1[[#This Row],[Pre-sold (Usable FA) (sf)]]-Table1[[#This Row],[Self-use space (Usable FA) (sf)]],0) -> 131585.25 | AD72: =IF(Table1[[#This Row],[For Sale or For Lease?]]="For Sale",Table1[[#This Row],[Office UFA (Net) (sf)]]-Table1[[#This Row],[Pre-leased space (Usable FA) (sf)]]-Table1[[#This Row],[Pre-sold (Usable FA) (sf)]]-Table1[[#This Row],[Self-use space (Usable FA) (sf)]],0) -> 0 | AE72: =IF(Table1[[#This Row],[For Sale or For Lease?]]="Uncertain",Table1[[#This Row],[Office UFA (Net) (sf)]]-Table1[[#This Row],[Pre-leased space (Usable FA) (sf)]]-Table1[[#This Row],[Pre-sold (Usable FA) (sf)]]-Table1[[#This Row],[Self-use space (Usable FA) (sf)]],0) -> 0 | AF72: =1-SUM(Table1[[#This Row],[Space available for lease (Usable FA) (sf)]:[Space available uncertain of use (Usable FA) (sf)]])/Table1[[#This Row],[Office UFA (Net) (sf)]] -> 0 | AG72: Commercial | AI72: Patrick Stevens | AJ72: 42110 | AK72: 42110 | AL72: Revitalization | AN72: Private Sector | AO72: For Lease | AP72: Single owner | AR72: NS069 | AV72: MULTIPOLYGON (((114.206469273 22.321991672,114.206458827 22.3221000730001,114.206408884 22.3220958400001,114.206387891 22.322306699,114.206438494 22.322311075,114.206428099 22.322418946,114.206731057 22.322445997,114.206741671 22.3223372940001,114.206793659 22.322341791,114.206814942 22.3221302630001,114.20676232 22.322125802,114.206772867 22.322017782,114.206469273 22.321991672)))
